Workbook

Sheet Assessment
A1: Req ID | B1: Source document | C1: Section | D1: Requirement (verbatim) | E1: Obligation level | F1: Topic | G1: Impact rating | H1: Rationale (specific to this process) | I1: Affected activities / deliverables | J1: Required changes / actions | K1: Evidence to produce | L1: Owner role | M1: Dependencies on other processes | N1: Effort (S/M/L) | O1: Notes / assumptions
A2: TR1-001 | B2: BSI TR-03183-1 v1.0.0 | C2: 3 Overview Cyber Resilience Act | D2: Manufacturers need to take responsibility for cybersecurity during the entire support period of the PwDE. | E2: MUST (equiv. 'need to') | F2: Lifecycle responsibility | G2: Medium | H2: Maintenance must carry cybersecurity responsibility for every delivered release until its support period ends - not just until acceptance or warranty end. | I2: Long-term maintenance of all supported release lines | J2: Plan PSIRT and engineering capacity per supported release line until its support end date. | K2: Support-period register per release; capacity plan | L2: Service Delivery Manager / PSIRT Lead | M2: Support periods from 1. Presale | N2: M
A3: TR1-002 | B3: BSI TR-03183-1 v1.0.0 | C3: 3.1 New Legislative Framework | D3: The framework obliges manufacturers to ensure that the PwDE fulfils the applicable legal requirements. | E3: MUST (equiv. 'obliges') | F3: CRA conformity - general | G3: Low | H3: The obligation continues after delivery for the whole support period (the NLF obliges manufacturers to ensure the product fulfils the applicable legal requirements). | I3: Post-market obligations | J3: Cover the obligation in the post-market process (monitoring, updates, reviews). | K3: Post-market records | L3: Product Security Officer / PSIRT Lead | M3: Inputs from 2. and 3. | N3: S
A4: TR1-003 | B4: BSI TR-03183-1 v1.0.0 | C4: 3.1 New Legislative Framework | D4: Manufacturers are free to choose any technical solution to meet these requirements. | E4: MAY (equiv. 'are free to') | F4: CRA conformity - general | G4: Nil | H4: Nil - no change needed in 5. Solution Maintenance (RUN). Handled in 2. Solution Development (Head of Engineering / Security Architect). | I4: None for this process | J4: No action in this process. | K4: n/a | L4: n/a | M4: Handled in 2. Solution Development | N4: n/a
A5: TR1-004 | B5: BSI TR-03183-1 v1.0.0 | C5: 3.2 Scope of the CRA | D5: Besides physical PwDEs, which are generally required to affix the CE mark, software commercially distributed on the European Market will now be subject to the CE mark, indicating that the requirements set out in the CRA are fulfilled. | E5: MUST (equiv. 'required') | F5: EU declaration of conformity / CE marking | G5: Low | H5: Conformity must be maintained across updates; a substantial modification requires a new assessment (commercially distributed software is now subject to CE marking). | I5: Change impact assessment of updates | J5: Assess each update for substantial modification and update the DoC where needed. | K5: Change impact assessment record | L5: CRA Compliance Manager | M5: Changes from 2./3. | N5: S
A6: TR1-005 | B6: BSI TR-03183-1 v1.0.0 | C6: 3.4 Timeline | D6: The reporting obligations (Article 14 CRA) for manufacturers to report actively exploited vulnerabilities and severe incidents will start on 11 September 2026. | E6: Applicability rule (no modal verb) | F6: CRA timeline - reporting obligations | G6: Critical | H6: Art. 14 reporting has applied since 11 Sep 2026 (today is 18 Oct 2026): the 24h / 72h / final-report procedure via the single reporting platform must already be operational - the most urgent CRA obligation for the business. | I6: Vulnerability handling / PSIRT procedures, service management | J6: Set up an interim reporting capability immediately: name reporters and deputies, register on the single reporting platform, prepare templates, define awareness criteria and a 24/7 escalation path; rehearse once. | K6: Reporting procedure (approved); platform registration; on-call roster; exercise record | L6: PSIRT Lead / Service Delivery Manager | M6: Needs SBOM and release data from 3. Integration/Build; feeds 4. Deployment (patch roll-out) | N6: L | O6: Applicability rule without a modal verb; registered because it decides when CRA obligations apply to our solutions. Today is 18 Oct 2026, so this obligation is already in force.
A7: TR1-006 | B7: BSI TR-03183-1 v1.0.0 | C7: 3.4 Timeline | D7: This applies also to PwDEs already placed on the European market. | E7: Applicability rule (no modal verb) | F7: CRA timeline - reporting obligations | G7: Critical | H7: Reporting covers the whole installed base, including solutions delivered years ago to airports and government customers - their versions, sites and contacts must be known to the PSIRT now. | I7: Vulnerability handling / PSIRT procedures, service management | J7: Build or complete the installed-base register for all delivered solutions still in operation and link it to the PSIRT reporting procedure. | K7: Installed-base register covering legacy deliveries | L7: PSIRT Lead / Service Delivery Manager | M7: Needs SBOM and release data from 3. Integration/Build; feeds 4. Deployment (patch roll-out) | N7: L | O7: Applicability rule without a modal verb; registered because it decides when CRA obligations apply to our solutions.
A8: TR1-007 | B8: BSI TR-03183-1 v1.0.0 | C8: 3.4 Timeline | D8: From 11 December 2027 onwards, all products with digital elements in scope of the CRA that are made available on the European Market after this date must adhere to all CRA requirements. | E8: MUST (equiv. 'must') | F8: CRA timeline | G8: Medium | H8: Updates delivered after 11 Dec 2027 must keep conformity; a substantial modification of an installed legacy solution brings it fully into CRA scope. | I8: Vulnerability handling / PSIRT procedures, service management | J8: Embed 'from 11 Dec 2027 all in-scope products made available must meet all CRA requirements' in the PSIRT / vulnerability-handling procedure and service-management tooling. | K8: Procedure document; tickets/records proving execution; periodic review record | L8: PSIRT Lead / Service Delivery Manager | M8: Needs SBOM and release data from 3. Integration/Build; feeds 4. Deployment (patch roll-out) | N8: M | O8: Assumption: today is 18 Oct 2026; reporting obligations already apply since 11 Sep 2026, all other obligations from 11 Dec 2027.
A9: TR1-008 | B9: BSI TR-03183-1 v1.0.0 | C9: 3.4 Timeline | D9: Obligations laid down in Article 14 apply to all products with digital elements that fall within the scope of this Regulation that have been placed on the market before 11 December 2027 (Article 69(3) CRA). | E9: Applicability rule (no modal verb) | F9: CRA timeline - legacy products | G9: High | H9: Legacy installations remain subject to Art. 14 reporting even if they never become CRA-conformant products. | I9: Vulnerability handling / PSIRT procedures, service management | J9: Embed 'Art. 14 obligations apply to all in-scope products placed on the market before 11 Dec 2027' in the PSIRT / vulnerability-handling procedure and service-management tooling. | K9: Procedure document; tickets/records proving execution; periodic review record | L9: PSIRT Lead / Service Delivery Manager | M9: Needs SBOM and release data from 3. Integration/Build; feeds 4. Deployment (patch roll-out) | N9: M | O9: Applicability rule without a modal verb; registered because it decides when CRA obligations apply to our solutions.
A10: TR1-009 | B10: BSI TR-03183-1 v1.0.0 | C10: 3.4 Timeline | D10: Products with digital elements that have been placed on the market before 11 December 2027 are only subject to the CRA, if those PwDEs have been subject to a substantial modification after 11 December 2027 (Article 69(2) CRA). | E10: Applicability rule (no modal verb) | F10: CRA timeline - substantial modification | G10: High | H10: Every change to a legacy installation must be screened for substantial modification; security updates and bug fixes usually are not, changes of type or purpose can be. | I10: Vulnerability handling / PSIRT procedures, service management | J10: Embed 'products placed on the market before 11 Dec 2027 fall under the CRA only after a substantial modification after that date' in the PSIRT / vulnerability-handling procedure and service-management tooling. | K10: Procedure document; tickets/records proving execution; periodic review record | L10: PSIRT Lead / Service Delivery Manager | M10: Needs SBOM and release data from 3. Integration/Build; feeds 4. Deployment (patch roll-out) | N10: M | O10: Applicability rule without a modal verb; registered because it decides when CRA obligations apply to our solutions.
A11: TR1-010 | B11: BSI TR-03183-1 v1.0.0 | C11: 3.4 Timeline | D11: The above mentioned Obligations laid down in Article 14 form an exception and apply to all products with digital elements that fall within the scope of this Regulation that have been placed on the market before 11 December 2027 (Article 69(3) CRA). | E11: Applicability rule (no modal verb) | F11: CRA timeline - legacy products | G11: Medium | H11: Restates that reporting duties apply to the legacy installed base regardless of substantial modification. | I11: Vulnerability handling / PSIRT procedures, service management | J11: Embed 'Art. 14 obligations are the exception that applies to all products placed before 11 Dec 2027' in the PSIRT / vulnerability-handling procedure and service-management tooling. | K11: Procedure document; tickets/records proving execution; periodic review record | L11: PSIRT Lead / Service Delivery Manager | M11: Needs SBOM and release data from 3. Integration/Build; feeds 4. Deployment (patch roll-out) | N11: M | O11: Applicability rule without a modal verb; registered because it decides when CRA obligations apply to our solutions.
A12: TR1-011 | B12: BSI TR-03183-1 v1.0.0 | C12: 3.4 Timeline | D12: Based on the NLF [3] a substantial modification is given if the type and purpose of a PwDE is changed in a way which was not foreseen in the initial risk assessment. | E12: Applicability rule (definition) | F12: CRA timeline - substantial modification | G12: High | H12: Each change to an installed solution needs a documented check against the initial risk assessment to decide whether it is a substantial modification. | I12: Vulnerability handling / PSIRT procedures, service management | J12: Add a substantial-modification check (type/purpose change vs. initial risk assessment) to change management for all installed solutions. | K12: Change impact / substantial-modification decision record | L12: PSIRT Lead / Service Delivery Manager | M12: Needs SBOM and release data from 3. Integration/Build; feeds 4. Deployment (patch roll-out) | N12: M | O12: Applicability rule without a modal verb; registered because it decides when CRA obligations apply to our solutions. The European Commission is preparing definitive guidance on substantial modification.
A13: TR1-012 | B13: BSI TR-03183-1 v1.0.0 | C13: 3.4 Timeline | D13: As such typical maintenance of a PwDE with security updates and bug fixes is usually not considered a substantial modification. | E13: Applicability rule (definition) | F13: CRA timeline - substantial modification | G13: Medium | H13: Routine security updates and bug fixes can be shipped to legacy installations without triggering full CRA applicability - keep them separate from feature changes. | I13: Vulnerability handling / PSIRT procedures, service management | J13: Embed 'security updates and bug fixes are usually not a substantial modification' in the PSIRT / vulnerability-handling procedure and service-management tooling. | K13: Procedure document; tickets/records proving execution; periodic review record | L13: PSIRT Lead / Service Delivery Manager | M13: Needs SBOM and release data from 3. Integration/Build; feeds 4. Deployment (patch roll-out) | N13: M | O13: Applicability rule without a modal verb; registered because it decides when CRA obligations apply to our solutions.
A14: TR1-013 | B14: BSI TR-03183-1 v1.0.0 | C14: 3.5 Concepts - Security by Design and by Default | D14: The CRA mandates that manufacturers integrate cybersecurity into the planning, design, development, and maintenance of products with digital elements from the outset. | E14: MUST (equiv. 'mandates') | F14: Secure development lifecycle | G14: Medium | H14: The obligation continues after delivery for the whole support period (integrate cybersecurity into planning, design, development and maintenance from the outset). | I14: Post-market obligations | J14: Cover the obligation in the post-market process (monitoring, updates, reviews). | K14: Post-market records | L14: Product Security Officer / PSIRT Lead | M14: Inputs from 2. and 3. | N14: M
A15: TR1-014 | B15: BSI TR-03183-1 v1.0.0 | C15: 3.5 Concepts - Security by Design and by Default | D15: It also requires PwDEs to be secure by default, meaning users should not need to take extra steps to ensure secure use out-of-the-box. | E15: MUST (equiv. 'requires') | F15: Secure by default | G15: Low | H15: The property must be maintained through updates and re-assessed when new threats appear (products must be secure by default without extra user steps). | I15: Updates; post-market review | J15: Check in regression and post-market reviews that updates do not weaken the property. | K15: Regression/security test results for updates | L15: PSIRT Lead / QA Lead | M15: Updates from 2. Development and 3. Integration/Build | N15: S
A16: TR1-015 | B16: BSI TR-03183-1 v1.0.0 | C16: 3.5 Concepts - Risk-based approach | D16: The essential cybersecurity requirements have to be implemented based on a cybersecurity risk assessment taking into account the intended purpose and reasonably foreseeable use of a product with digital elements. | E16: MUST (equiv. 'have to') | F16: Risk assessment - general | G16: Low | H16: Post-market events (new vulnerabilities, threats, changes) must update the risk assessment (implement the essential requirements based on a risk assessment considering intended purpose and foreseeable use). | I16: Risk-assessment updates | J16: Trigger risk-assessment updates from PSIRT cases and threat intelligence. | K16: Updated risk-assessment versions | L16: Product Security Officer | M16: Analysis by 2. Development | N16: S
A17: TR1-016 | B17: BSI TR-03183-1 v1.0.0 | C17: 3.5 Concepts - Risk-based approach | D17: This approach ensures that all cybersecurity risks relevant to the PwDE have to be addressed ensuring an appropriate level of cybersecurity. | E17: MUST (equiv. 'have to') | F17: Risk assessment - general | G17: Low | H17: Post-market events (new vulnerabilities, threats, changes) must update the risk assessment (all relevant cybersecurity risks have to be addressed). | I17: Risk-assessment updates | J17: Trigger risk-assessment updates from PSIRT cases and threat intelligence. | K17: Updated risk-assessment versions | L17: Product Security Officer | M17: Analysis by 2. Development | N17: S
A18: TR1-017 | B18: BSI TR-03183-1 v1.0.0 | C18: 3.5 Concepts - Lifecycle Responsibility | D18: Manufacturers are responsible for cybersecurity throughout the entire lifecycle of their PwDEs, not just until the point of sale. | E18: Responsibility (equiv. 'are responsible') | F18: Lifecycle responsibility | G18: Medium | H18: Responsibility continues after acceptance: maintenance must handle cybersecurity for every installed release until its support period ends. | I18: Long-term maintenance of all supported release lines | J18: Plan PSIRT and engineering capacity per supported release line until its support end date. | K18: Support-period register per release; capacity plan | L18: Service Delivery Manager / PSIRT Lead | M18: Support periods from 1. Presale | N18: M
A19: TR1-018 | B19: BSI TR-03183-1 v1.0.0 | C19: 3.5 Concepts - Lifecycle Responsibility | D19: This entails handling of vulnerabilities, including providing timely security updates or other mitigating measures when necessary, during use for a determined support period so that it reflects the length of time during which the PwDE is expected to be in use, with a minimum of five years unless the PwDE is usually used less than five years. | E19: MUST (part of the responsibility; 'entails') | F19: Support period | G19: High | H19: Vulnerability handling and timely security updates must be delivered for every release for the whole (possibly 10+ year) support period; capacity and funding must match. | I19: Long-term maintenance of all supported release lines | J19: Plan PSIRT and engineering capacity per supported release line until its support end date. | K19: Support-period register per release; capacity plan | L19: Service Delivery Manager / PSIRT Lead | M19: Support periods from 1. Presale | N19: M
A20: TR1-019 | B20: BSI TR-03183-1 v1.0.0 | C20: 3.5 Concepts - Transparency and Information for Users | D20: The CRA emphasizes transparency, requiring manufacturers to provide clear and comprehensible information about the security features, contact information for vulnerability reporting and update policies of their PwDEs. | E20: MUST (equiv. 'requiring') | F20: Transparency & user information | G20: Medium | H20: The information must be kept current, e.g. contact point, support end date, update instructions (provide clear information on security features, vulnerability contact and update policies). | I20: Updates of user information | J20: Re-issue the user information when contacts, support dates or instructions change. | K20: Document revision history | L20: Service Delivery Manager | M20: Changes from 2./3. | N20: M
A21: TR1-020 | B21: BSI TR-03183-1 v1.0.0 | C21: 3.6 Obligations of the manufacturer - Pre-Market Obligations | D21: [The manufacturer has several obligations before placing a product with digital elements (PwDE) on the market:] Ensure that PwDEs meet the essential cybersecurity requirements outlined in Annex I, which includes designing, developing, and producing PwDEs to achieve an appropriate level of cybersecurity. The level of cybersecurity is based on a cybersecurity risk assessment for each PwDE as well as an appropriate treatment of potential risks to an acceptable level, considering the intended purpose, reasonably foreseeable use, operational environment, and expected period of use. | E21: MUST (obligation; imperative) | F21: Essential requirements - general | G21: Low | H21: The property must be maintained through updates and re-assessed when new threats appear (ensure products meet Annex I based on a per-product risk assessment and treatment). | I21: Updates; post-market review | J21: Check in regression and post-market reviews that updates do not weaken the property. | K21: Regression/security test results for updates | L21: PSIRT Lead / QA Lead | M21: Updates from 2. Development and 3. Integration/Build | N21: S
A22: TR1-021 | B22: BSI TR-03183-1 v1.0.0 | C22: 3.6 Obligations of the manufacturer - Pre-Market Obligations | D22: [The manufacturer has several obligations before placing a product with digital elements (PwDE) on the market:] Apply due diligence when integrating third-party components, including open source software, to make sure the component is suitable to be integrated in the PwDE and that arising vulnerabilities can be adequately addressed. | E22: MUST (obligation; imperative) | F22: Third-party component due diligence | G22: Medium | H22: Third-party components must be monitored for vulnerabilities and support status, and upstream maintainers informed (apply due diligence when integrating third-party components including open source). | I22: Supplier vulnerability information; upstream reporting | J22: Monitor supplier advisories and end-of-life dates; report found vulnerabilities upstream and track responses. | K22: Supplier advisory log; upstream reports | L22: PSIRT Lead | M22: SBOM from 3. Integration/Build | N22: M
A23: TR1-022-a | B23: BSI TR-03183-1 v1.0.0 | C23: 3.6 Obligations of the manufacturer - Pre-Market Obligations | D23: [The manufacturer has several obligations before placing a product with digital elements (PwDE) on the market:] Draw up the technical documentation (Article 31 CRA) containing at least the information set out in Annex VII that demonstrates compliance with the essential cybersecurity requirements. This documentation includes information about the PwDE, its intended purpose, its design and development. | E23: MUST (obligation; imperative) | F23: Technical documentation | G23: Medium | H23: The technical documentation must be kept up to date with updates and post-market findings (draw up the technical documentation (Art. 31, Annex VII) demonstrating compliance). | I23: Technical documentation maintenance | J23: Update the technical file with each security update and risk-assessment update. | K23: Technical file revision history | L23: CRA Compliance Manager | M23: Changes from 2., 3. and 5. | N23: M
A24: TR1-022-b | B24: BSI TR-03183-1 v1.0.0 | C24: 3.6 Obligations of the manufacturer - Pre-Market Obligations | D24: [The manufacturer has several obligations before placing a product with digital elements (PwDE) on the market:] It must also include a cybersecurity risk assessment that identifies potential threats and vulnerabilities, assesses their impact, and outlines the measures taken to mitigate these risks […] | E24: MUST (equiv. 'must') | F24: Technical documentation | G24: Low | H24: The technical documentation must be kept up to date with updates and post-market findings (the technical documentation must include the cybersecurity risk assessment). | I24: Technical documentation maintenance | J24: Update the technical file with each security update and risk-assessment update. | K24: Technical file revision history | L24: CRA Compliance Manager | M24: Changes from 2., 3. and 5. | N24: S
A25: TR1-022-c | B25: BSI TR-03183-1 v1.0.0 | C25: 3.6 Obligations of the manufacturer - Pre-Market Obligations | D25: [The manufacturer has several obligations before placing a product with digital elements (PwDE) on the market:] It must also include […] as well as a Software Bill of Material (SBOM). | E25: MUST (equiv. 'must') | F25: Technical documentation - SBOM | G25: Medium | H25: The technical documentation must be kept up to date with updates and post-market findings (the technical documentation must include an SBOM). | I25: Technical documentation maintenance | J25: Update the technical file with each security update and risk-assessment update. | K25: Technical file revision history | L25: CRA Compliance Manager | M25: Changes from 2., 3. and 5. | N25: M
... A32: TR1-027 | B32: BSI TR-03183-1 v1.0.0 | C32: 3.6 Obligations of the manufacturer - PwDE Monitoring and Post-Market Obligations | D32: This review includes updating the risk assessment as needed and addressing new risks appropriately. | E32: MUST (part of the review duty; 'includes') | F32: Post-market review | G32: High | H32: Post-market reviews must update the risk assessment and treat new risks; triggers and owners are needed. | I32: Post-market monitoring and vulnerability handling | J32: Operate SBOM-based continuous vulnerability monitoring, periodic security reviews and remediation for all supported releases. | K32: Monitoring records; review minutes; remediation tickets | L32: PSIRT Lead / Product Security Officer | M32: SBOMs from 3.; fixes from 2.; roll-out by 4. | N32: M
A33: TR1-028-a | B33: BSI TR-03183-1 v1.0.0 | C33: 3.6 Obligations of the manufacturer - PwDE Monitoring and Post-Market Obligations | D33: Additionally, the manufacturer ought to monitor the PwDE for vulnerabilities throughout its defined support period […] | E33: MUST (equiv. 'ought to') | F33: Vulnerability monitoring | G33: Critical | H33: Continuous vulnerability monitoring of every supported release (SBOM-based, incl. third-party components) for the full support period is a new capability and a CRA core duty. | I33: Post-market monitoring and vulnerability handling | J33: Operate SBOM-based continuous vulnerability monitoring, periodic security reviews and remediation for all supported releases. | K33: Monitoring records; review minutes; remediation tickets | L33: PSIRT Lead / Product Security Officer | M33: SBOMs from 3.; fixes from 2.; roll-out by 4. | N33: L | O33: The wording 'ought to' is advisory, but it restates the mandatory CRA duty to handle vulnerabilities during the support period.
A34: TR1-028-b | B34: BSI TR-03183-1 v1.0.0 | C34: 3.6 Obligations of the manufacturer - PwDE Monitoring and Post-Market Obligations | D34: […] and address found vulnerabilities appropriately, including by providing security updates […] | E34: MUST (equiv. 'ought to') | F34: Vulnerability remediation | G34: Critical | H34: Found vulnerabilities must be remediated with security updates for all supported releases - a remediation chain across engineering, build and field service. | I34: Post-market monitoring and vulnerability handling | J34: Operate SBOM-based continuous vulnerability monitoring, periodic security reviews and remediation for all supported releases. | K34: Monitoring records; review minutes; remediation tickets | L34: PSIRT Lead / Product Security Officer | M34: SBOMs from 3.; fixes from 2.; roll-out by 4. | N34: L | O34: The wording 'ought to' is advisory, but it restates the mandatory CRA duty to handle vulnerabilities during the support period.
A35: TR1-028-c | B35: BSI TR-03183-1 v1.0.0 | C35: 3.6 Obligations of the manufacturer - PwDE Monitoring and Post-Market Obligations | D35: […] generally free of charge unless otherwise agreed between a manufacturer and a business user in relation to a tailor-made product with digital elements. | E35: MUST (equiv. 'ought to') | F35: Security updates - free of charge | G35: High | H35: Security fixes must be delivered separately from paid feature upgrades so they can be provided free of charge. | I35: Post-market monitoring and vulnerability handling | J35: Operate SBOM-based continuous vulnerability monitoring, periodic security reviews and remediation for all supported releases. | K35: Monitoring records; review minutes; remediation tickets | L35: PSIRT Lead / Product Security Officer | M35: SBOMs from 3.; fixes from 2.; roll-out by 4. | N35: M | O35: The wording 'ought to' is advisory, but it restates the mandatory CRA duty to handle vulnerabilities during the support period. Assumption: many airport/government solutions are tailor-made for business users, so an explicit contractual agreement is possible but must be made deliberately.
A36: TR1-029 | B36: BSI TR-03183-1 v1.0.0 | C36: 3.6 Obligations of the manufacturer - PwDE Monitoring and Post-Market Obligations | D36: These post-market obligations have to be upheld during the support period of the PwDE determined by the manufacturer in accordance with the expected duration of use of the PwDE. | E36: MUST (equiv. 'have to') | F36: Support period | G36: High | H36: All post-market duties (monitoring, updates, reviews) must be upheld for the support period determined per solution. | I36: Long-term maintenance of all supported release lines | J36: Plan PSIRT and engineering capacity per supported release line until its support end date. | K36: Support-period register per release; capacity plan | L36: Service Delivery Manager / PSIRT Lead | M36: Support periods from 1. Presale | N36: M
A37: TR1-030 | B37: BSI TR-03183-1 v1.0.0 | C37: 3.6 Obligations of the manufacturer - PwDE Monitoring and Post-Market Obligations | D37: Generally, the support period is at least five years unless not appropriate for the type of PwDE and its foreseeable duration of use. | E37: Rule (equiv. 'is at least') | F37: Support period | G37: Medium | H37: the support period is generally at least five years - vulnerability handling and security updates must be resourced for the full support period of every delivered release. | I37: Long-term maintenance of all supported release lines | J37: Plan PSIRT and engineering capacity per supported release line until its support end date. | K37: Support-period register per release; capacity plan | L37: Service Delivery Manager / PSIRT Lead | M37: Support periods from 1. Presale | N37: M
A38: TR1-031-a | B38: BSI TR-03183-1 v1.0.0 | C38: 3.6 Obligations of the manufacturer - PwDE Monitoring and Post-Market Obligations | D38: In addition to that the manufacturer has to ensure that security updates […] are available for at least 10 years after the PwDE has been placed on the market or for the full support period, whichever is longer. | E38: MUST (equiv. 'has to') | F38: Availability of security updates | G38: High | H38: Security updates must stay available for at least 10 years after placing on the market (or the support period if longer) - a long-term update repository is needed. | I38: Long-term maintenance of all supported release lines | J38: Plan PSIRT and engineering capacity per supported release line until its support end date. | K38: Support-period register per release; capacity plan | L38: Service Delivery Manager / PSIRT Lead | M38: Support periods from 1. Presale | N38: M
A39: TR1-031-b | B39: BSI TR-03183-1 v1.0.0 | C39: 3.6 Obligations of the manufacturer - PwDE Monitoring and Post-Market Obligations | D39: In addition to that the manufacturer has to ensure that […] the technical documentation are available for at least 10 years after the PwDE has been placed on the market or for the full support period, whichever is longer. | E39: MUST (equiv. 'has to') | F39: Records retention | G39: Low | H39: The technical documentation must be kept up to date with updates and post-market findings (keep technical documentation available for at least 10 years (or the support period if longer)). | I39: Technical documentation maintenance | J39: Update the technical file with each security update and risk-assessment update. | K39: Technical file revision history | L39: CRA Compliance Manager | M39: Changes from 2., 3. and 5. | N39: S
A40: TR1-032-a | B40: BSI TR-03183-1 v1.0.0 | C40: 3.6 Obligations of the manufacturer - Reporting obligations | D40: Manufacturers have to report actively exploited vulnerabilities of the PwDE […] upon becoming aware of them. | E40: MUST (equiv. 'have to') | F40: CRA Art. 14 reporting - vulnerabilities | G40: Critical | H40: Reporting actively exploited vulnerabilities to CSIRT/ENISA is mandatory since 11 Sep 2026, also for solutions already installed at airports and government sites; it needs a 24/7-capable detection-to-notification procedure. | I40: CRA Art. 14 reporting procedure (ENISA single reporting platform, CSIRT) | J40: Implement the reporting procedure: awareness criteria, 24h / 72h / 14-day (vulnerability) and 24h / 72h / one-month (incident) timelines, platform accounts, templates, approvals and 24/7 escalation; rehearse it. | K40: Reporting procedure; platform registration; submitted reports; exercise records | L40: PSIRT Lead / Compliance Officer | M40: Facts from 2. Development; installed base from 4. Deployment | N40: L | O40: Reporting obligations apply since 11 Sep 2026 (today: 18 Oct 2026) and cover products placed on the market before 11 Dec 2027.
A41: TR1-032-b | B41: BSI TR-03183-1 v1.0.0 | C41: 3.6 Obligations of the manufacturer - Reporting obligations | D41: Manufacturers have to report […] severe cybersecurity incidents negatively affecting the security of products with digital elements upon becoming aware of them. | E41: MUST (equiv. 'have to') | F41: CRA Art. 14 reporting - incidents | G41: Critical | H41: Severe incidents affecting the security of our solutions (incl. remote data processing we operate) must be reported since 11 Sep 2026; needs incident classification criteria and the reporting procedure. | I41: CRA Art. 14 reporting procedure (ENISA single reporting platform, CSIRT) | J41: Implement the reporting procedure: awareness criteria, 24h / 72h / 14-day (vulnerability) and 24h / 72h / one-month (incident) timelines, platform accounts, templates, approvals and 24/7 escalation; rehearse it. | K41: Reporting procedure; platform registration; submitted reports; exercise records | L41: PSIRT Lead / Compliance Officer | M41: Facts from 2. Development; installed base from 4. Deployment | N41: L | O41: Reporting obligations apply since 11 Sep 2026 (today: 18 Oct 2026) and cover products placed on the market before 11 Dec 2027.
A42: TR1-033 | B42: BSI TR-03183-1 v1.0.0 | C42: 3.6 Obligations of the manufacturer - Reporting obligations | D42: Notifications must be made simultaneously to the CSIRT (Computer Security Incident Response Team) designated as coordinator and ENISA (European Union Agency for Cybersecurity) via the single reporting platform to be established under CRA Article 16. | E42: MUST | F42: CRA Art. 14 reporting - channel | G42: Critical | H42: Notifications go simultaneously to the coordinating CSIRT and ENISA via the single reporting platform - registration, accounts, roles and templates must be ready. | I42: CRA Art. 14 reporting procedure (ENISA single reporting platform, CSIRT) | J42: Implement the reporting procedure: awareness criteria, 24h / 72h / 14-day (vulnerability) and 24h / 72h / one-month (incident) timelines, platform accounts, templates, approvals and 24/7 escalation; rehearse it. | K42: Reporting procedure; platform registration; submitted reports; exercise records | L42: PSIRT Lead / Compliance Officer | M42: Facts from 2. Development; installed base from 4. Deployment | N42: L | O42: Reporting obligations apply since 11 Sep 2026 (today: 18 Oct 2026) and cover products placed on the market before 11 Dec 2027.
A43: TR1-034-a | B43: BSI TR-03183-1 v1.0.0 | C43: 3.6 Obligations of the manufacturer - Reporting obligations | D43: [The following notification timelines and content are given for actively exploited vulnerabilities:] Early Warning Notification: Must be submitted without undue delay and in any case within 24 hours of becoming aware of an actively exploited vulnerability […] | E43: MUST | F43: CRA Art. 14 reporting - vulnerabilities | G43: Critical | H43: An early warning within 24 hours of awareness needs on-call staff, pre-approved templates and a decision path that works on weekends. | I43: CRA Art. 14 reporting procedure (ENISA single reporting platform, CSIRT) | J43: Implement the reporting procedure: awareness criteria, 24h / 72h / 14-day (vulnerability) and 24h / 72h / one-month (incident) timelines, platform accounts, templates, approvals and 24/7 escalation; rehearse it. | K43: Reporting procedure; platform registration; submitted reports; exercise records | L43: PSIRT Lead / Compliance Officer | M43: Facts from 2. Development; installed base from 4. Deployment | N43: L | O43: Reporting obligations apply since 11 Sep 2026 (today: 18 Oct 2026) and cover products placed on the market before 11 Dec 2027.
A44: TR1-034-b | B44: BSI TR-03183-1 v1.0.0 | C44: 3.6 Obligations of the manufacturer - Reporting obligations | D44: [The following notification timelines and content are given for actively exploited vulnerabilities:] […] and should indicate, where applicable, the Member States where the PwDE has been made available of which the manufacturer is aware. | E44: SHOULD (equiv. 'should') | F44: CRA Art. 14 reporting - vulnerabilities | G44: High | H44: Early warnings should name the Member States where the solution is available - installed-base data must be retrievable on demand. | I44: CRA Art. 14 reporting procedure (ENISA single reporting platform, CSIRT) | J44: Implement the reporting procedure: awareness criteria, 24h / 72h / 14-day (vulnerability) and 24h / 72h / one-month (incident) timelines, platform accounts, templates, approvals and 24/7 escalation; rehearse it. | K44: Reporting procedure; platform registration; submitted reports; exercise records | L44: PSIRT Lead / Compliance Officer | M44: Facts from 2. Development; installed base from 4. Deployment | N44: M | O44: Reporting obligations apply since 11 Sep 2026 (today: 18 Oct 2026) and cover products placed on the market before 11 Dec 2027.
A45: TR1-035 | B45: BSI TR-03183-1 v1.0.0 | C45: 3.6 Obligations of the manufacturer - Reporting obligations | D45: [The following notification timelines and content are given for actively exploited vulnerabilities:] Vulnerability Notification: If not already provided, a more detailed notification must be submitted within 72 hours after becoming aware of an actively exploited vulnerability. | E45: MUST | F45: CRA Art. 14 reporting - vulnerabilities | G45: Critical | H45: A detailed vulnerability notification within 72 hours requires fast technical analysis and approval. | I45: CRA Art. 14 reporting procedure (ENISA single reporting platform, CSIRT) | J45: Implement the reporting procedure: awareness criteria, 24h / 72h / 14-day (vulnerability) and 24h / 72h / one-month (incident) timelines, platform accounts, templates, approvals and 24/7 escalation; rehearse it. | K45: Reporting procedure; platform registration; submitted reports; exercise records | L45: PSIRT Lead / Compliance Officer | M45: Facts from 2. Development; installed base from 4. Deployment | N45: L | O45: Reporting obligations apply since 11 Sep 2026 (today: 18 Oct 2026) and cover products placed on the market before 11 Dec 2027.
A46: TR1-036 | B46: BSI TR-03183-1 v1.0.0 | C46: 3.6 Obligations of the manufacturer - Reporting obligations | D46: [The following notification timelines and content are given for actively exploited vulnerabilities:] This should include general information about the PwDE, as available, the general nature of the exploit and vulnerability, corrective or mitigating actions taken, and guidance for users. | E46: SHOULD (equiv. 'should') | F46: CRA Art. 14 reporting - vulnerabilities | G46: High | H46: The 72-hour notification content (product information, nature of the exploit, mitigations, user guidance) needs templates and engineering input. | I46: CRA Art. 14 reporting procedure (ENISA single reporting platform, CSIRT) | J46: Implement the reporting procedure: awareness criteria, 24h / 72h / 14-day (vulnerability) and 24h / 72h / one-month (incident) timelines, platform accounts, templates, approvals and 24/7 escalation; rehearse it. | K46: Reporting procedure; platform registration; submitted reports; exercise records | L46: PSIRT Lead / Compliance Officer | M46: Facts from 2. Development; installed base from 4. Deployment | N46: M | O46: Reporting obligations apply since 11 Sep 2026 (today: 18 Oct 2026) and cover products placed on the market before 11 Dec 2027.
A47: TR1-037 | B47: BSI TR-03183-1 v1.0.0 | C47: 3.6 Obligations of the manufacturer - Reporting obligations | D47: [The following notification timelines and content are given for actively exploited vulnerabilities:] It should also indicate the sensitivity of the information, if relevant. | E47: SHOULD (equiv. 'should') | F47: CRA Art. 14 reporting - vulnerabilities | G47: Medium | H47: Classify the sensitivity of notified information (e.g. critical-infrastructure context of airports and government). | I47: CRA Art. 14 reporting procedure (ENISA single reporting platform, CSIRT) | J47: Implement the reporting procedure: awareness criteria, 24h / 72h / 14-day (vulnerability) and 24h / 72h / one-month (incident) timelines, platform accounts, templates, approvals and 24/7 escalation; rehearse it. | K47: Reporting procedure; platform registration; submitted reports; exercise records | L47: PSIRT Lead / Compliance Officer | M47: Facts from 2. Development; installed base from 4. Deployment | N47: M | O47: Reporting obligations apply since 11 Sep 2026 (today: 18 Oct 2026) and cover products placed on the market before 11 Dec 2027.
A48: TR1-038 | B48: BSI TR-03183-1 v1.0.0 | C48: 3.6 Obligations of the manufacturer - Reporting obligations | D48: [The following notification timelines and content are given for actively exploited vulnerabilities:] Final Report: If not already provided, a final report must be submitted within 14 days after a corrective or mitigating measure for the vulnerability is available, including a description of the vulnerability, including its severity and impact, and the details about the corrective measure made available to remedy the vulnerability. | E48: MUST | F48: CRA Art. 14 reporting - vulnerabilities | G48: Critical | H48: A final report within 14 days after a fix or mitigation is available requires tracking fix availability per case. | I48: CRA Art. 14 reporting procedure (ENISA single reporting platform, CSIRT) | J48: Implement the reporting procedure: awareness criteria, 24h / 72h / 14-day (vulnerability) and 24h / 72h / one-month (incident) timelines, platform accounts, templates, approvals and 24/7 escalation; rehearse it. | K48: Reporting procedure; platform registration; submitted reports; exercise records | L48: PSIRT Lead / Compliance Officer | M48: Facts from 2. Development; installed base from 4. Deployment | N48: L | O48: Reporting obligations apply since 11 Sep 2026 (today: 18 Oct 2026) and cover products placed on the market before 11 Dec 2027.
A49: TR1-039 | B49: BSI TR-03183-1 v1.0.0 | C49: 3.6 Obligations of the manufacturer - Reporting obligations | D49: [The following notification timelines and content are given for actively exploited vulnerabilities:] If available, this report also includes information concerning any malicious actor that has exploited or that is exploiting the vulnerability. | E49: Content rule (part of the final report 'must') | F49: CRA Art. 14 reporting - vulnerabilities | G49: Medium | H49: Threat-actor information, where available, must be included in the final report. | I49: CRA Art. 14 reporting procedure (ENISA single reporting platform, CSIRT) | J49: Implement the reporting procedure: awareness criteria, 24h / 72h / 14-day (vulnerability) and 24h / 72h / one-month (incident) timelines, platform accounts, templates, approvals and 24/7 escalation; rehearse it. | K49: Reporting procedure; platform registration; submitted reports; exercise records | L49: PSIRT Lead / Compliance Officer | M49: Facts from 2. Development; installed base from 4. Deployment | N49: M | O49: Reporting obligations apply since 11 Sep 2026 (today: 18 Oct 2026) and cover products placed on the market before 11 Dec 2027.
A50: TR1-040 | B50: BSI TR-03183-1 v1.0.0 | C50: 3.6 Obligations of the manufacturer - Reporting obligations | D50: [For severe incidents:] Early Warning Notification: Must be submitted without undue delay and in any case within 24 hours after becoming aware of the severe incident. | E50: MUST | F50: CRA Art. 14 reporting - incidents | G50: Critical | H50: Severe incidents need an early warning within 24 hours of awareness - same 24/7 capability as for exploited vulnerabilities. | I50: CRA Art. 14 reporting procedure (ENISA single reporting platform, CSIRT) | J50: Implement the reporting procedure: awareness criteria, 24h / 72h / 14-day (vulnerability) and 24h / 72h / one-month (incident) timelines, platform accounts, templates, approvals and 24/7 escalation; rehearse it. | K50: Reporting procedure; platform registration; submitted reports; exercise records | L50: PSIRT Lead / Compliance Officer | M50: Facts from 2. Development; installed base from 4. Deployment | N50: L | O50: Reporting obligations apply since 11 Sep 2026 (today: 18 Oct 2026) and cover products placed on the market before 11 Dec 2027.
A51: TR1-041-a | B51: BSI TR-03183-1 v1.0.0 | C51: 3.6 Obligations of the manufacturer - Reporting obligations | D51: [For severe incidents:] Includes at least whether the incident is suspected of being caused by unlawful or malicious acts […] | E51: MUST (equiv. 'includes at least') | F51: CRA Art. 14 reporting - incidents | G51: High | H51: The early warning must state whether unlawful or malicious acts are suspected - incident triage criteria are needed. | I51: CRA Art. 14 reporting procedure (ENISA single reporting platform, CSIRT) | J51: Implement the reporting procedure: awareness criteria, 24h / 72h / 14-day (vulnerability) and 24h / 72h / one-month (incident) timelines, platform accounts, templates, approvals and 24/7 escalation; rehearse it. | K51: Reporting procedure; platform registration; submitted reports; exercise records | L51: PSIRT Lead / Compliance Officer | M51: Facts from 2. Development; installed base from 4. Deployment | N51: M | O51: Reporting obligations apply since 11 Sep 2026 (today: 18 Oct 2026) and cover products placed on the market before 11 Dec 2027.
... A58: TR1-047 | B58: BSI TR-03183-1 v1.0.0 | C58: 3.6 Obligations of the manufacturer - Reporting obligations | D58: Besides the mandatory reports manufacturers and other parties may voluntarily report any vulnerability or cyber threat that could affect the risk profile of the PwDE as well as any incident or near-miss impacting the PwDE's security, according to CRA Article 15. | E58: MAY (equiv. 'may') | F58: CRA Art. 15 voluntary reporting | G58: Low | H58: Voluntary reporting of threats or near misses is optional; decide a policy. | I58: CRA Art. 14 reporting procedure (ENISA single reporting platform, CSIRT) | J58: Implement the reporting procedure: awareness criteria, 24h / 72h / 14-day (vulnerability) and 24h / 72h / one-month (incident) timelines, platform accounts, templates, approvals and 24/7 escalation; rehearse it. | K58: Reporting procedure; platform registration; submitted reports; exercise records | L58: PSIRT Lead / Compliance Officer | M58: Facts from 2. Development; installed base from 4. Deployment | N58: S | O58: Reporting obligations apply since 11 Sep 2026 (today: 18 Oct 2026) and cover products placed on the market before 11 Dec 2027.
A59: TR1-048 | B59: BSI TR-03183-1 v1.0.0 | C59: 3.6 Obligations of the manufacturer - Reporting obligations | D59: CSIRTs and ENISA must ensure confidentiality and appropriate protection of the information provided. | E59: MUST (addressed to CSIRTs/ENISA) | F59: Authority obligations | G59: Low | H59: Awareness: authorities must protect reported information, which supports sharing sensitive details about airport/government installations. | I59: Reporting procedure (background) | J59: Note the authority behaviour in the reporting procedure. | K59: Procedure note | L59: PSIRT Lead | M59: - | N59: S
A60: TR1-049 | B60: BSI TR-03183-1 v1.0.0 | C60: 3.6 Obligations of the manufacturer - Reporting obligations | D60: If a party other than the manufacturer notifies a vulnerability or severe incident, the CSIRT must inform the manufacturer without undue delay. | E60: MUST (addressed to CSIRTs) | F60: Authority obligations | G60: Low | H60: The CSIRT will forward third-party notifications about our solutions; intake must accept and act on them (they may start our own reporting clock). | I60: Reporting procedure (background) | J60: Note the authority behaviour in the reporting procedure. | K60: Procedure note | L60: PSIRT Lead | M60: - | N60: S
A61: TR1-050 | B61: BSI TR-03183-1 v1.0.0 | C61: 3.6 Obligations of the manufacturer - Reporting obligations | D61: The CSIRT may prioritize mandatory notifications over voluntary ones and will process all notifications according to the procedures in Article 16 of the CRA. | E61: MAY (addressed to CSIRTs) | F61: Authority obligations | G61: Nil | H61: Nil - addressed to the CSIRT (prioritisation of notifications); no manufacturer action in any process. | I61: None for this process | J61: No action in this process. | K61: n/a | L61: n/a | M61: Handled in 5. Solution Maintenance (RUN) | N61: n/a
A62: TR1-051 | B62: BSI TR-03183-1 v1.0.0 | C62: 3.6 Obligations of the manufacturer - Additional obligations for third-party components | D62: The manufacturer has to report vulnerabilities found in third-party components to the person or entity manufacturing or maintaining the component. | E62: MUST (equiv. 'has to') | F62: Upstream vulnerability reporting | G62: High | H62: Vulnerabilities found in third-party components must be reported to their maintainers - an upstream reporting procedure with supplier security contacts is needed. | I62: Supplier vulnerability information; upstream reporting | J62: Monitor supplier advisories and end-of-life dates; report found vulnerabilities upstream and track responses. | K62: Supplier advisory log; upstream reports | L62: PSIRT Lead | M62: SBOM from 3. Integration/Build | N62: M
A63: TR1-052 | B63: BSI TR-03183-1 v1.0.0 | C63: 3.6 Obligations of the manufacturer - Additional obligations for third-party components | D63: If the manufacturer develops a software or hardware modification of the third-party component that addresses the found vulnerability in that component, it has to share that relevant code or documentation with the person or entity manufacturing or maintaining the component where appropriate in a machine-readable format. | E63: MUST (equiv. 'has to') | F63: Upstream vulnerability reporting | G63: Medium | H63: Third-party components must be monitored for vulnerabilities and support status, and upstream maintainers informed (share own fixes for third-party components with their maintainer, machine-readable where appropriate). | I63: Supplier vulnerability information; upstream reporting | J63: Monitor supplier advisories and end-of-life dates; report found vulnerabilities upstream and track responses. | K63: Supplier advisory log; upstream reports | L63: PSIRT Lead | M63: SBOM from 3. Integration/Build | N63: M
A64: TR1-053 | B64: BSI TR-03183-1 v1.0.0 | C64: 3.7 Conformity assessment and Presumption of Conformity | D64: If a requested hEN can not be delivered or not be delivered in time, the European Commission may adopt implementing acts establishing common specifications covering technical requirements that provide a means to comply with the essential cybersecurity requirements set out in Annex I. | E64: MAY (addressed to the European Commission) | F64: Presumption of conformity | G64: Nil | H64: Nil - no change needed in 5. Solution Maintenance (RUN). Addressed to authorities (CSIRT/ENISA/European Commission/standardisation), not to the manufacturer. Handled in 3. Solution Integration / Build (CRA Compliance Manager). | I64: None for this process | J64: No action in this process. | K64: n/a | L64: n/a | M64: Handled in 3. Solution Integration / Build | N64: n/a
A65: TR1-054 | B65: BSI TR-03183-1 v1.0.0 | C65: 3.7 Conformity assessment and Presumption of Conformity | D65: The European Commission may also adopt specific European cybersecurity certification schemes under the Cyber Security Act (CSA) that can be used to demonstrate conformity of products with digital elements with the essential cybersecurity requirements or parts thereof as set out in Annex I. | E65: MAY (addressed to the European Commission) | F65: Presumption of conformity | G65: Nil | H65: Nil - no change needed in 5. Solution Maintenance (RUN). Addressed to authorities (CSIRT/ENISA/European Commission/standardisation), not to the manufacturer. Handled in 3. Solution Integration / Build (CRA Compliance Manager). | I65: None for this process | J65: No action in this process. | K65: n/a | L65: n/a | M65: Handled in 3. Solution Integration / Build | N65: n/a
A66: TR1-055 | B66: BSI TR-03183-1 v1.0.0 | C66: 3.7 Conformity assessment and Presumption of Conformity | D66: Harmonised European standards, common specifications as well as European cybersecurity certification schemes have to satisfy the essential cybersecurity requirements or part thereof for their given context. | E66: MUST (addressed to standards/schemes) | F66: Presumption of conformity | G66: Nil | H66: Nil - no change needed in 5. Solution Maintenance (RUN). Addressed to authorities (CSIRT/ENISA/European Commission/standardisation), not to the manufacturer. Handled in 3. Solution Integration / Build (CRA Compliance Manager). | I66: None for this process | J66: No action in this process. | K66: n/a | L66: n/a | M66: Handled in 3. Solution Integration / Build | N66: n/a
A67: TR1-056 | B67: BSI TR-03183-1 v1.0.0 | C67: 3.7 Conformity assessment and Presumption of Conformity | D67: To use the certificate for producing compliant PwDEs, the manufacturer must then ensure that the production of the PwDE ensures conformity with the approved type described in the certificate. | E67: MUST (equiv. 'must'; Module B+C only) | F67: Conformity assessment | G67: Nil | H67: Nil - applies only to conformity via Module B+C; default-category solutions use internal control (Module A). It would sit in 3. Integration/Build if Module B+C were chosen voluntarily. | I67: None for this process | J67: No action in this process. | K67: n/a | L67: n/a | M67: Handled in 3. Solution Integration / Build | N67: n/a | O67: Assumption: Module A self-assessment for all solutions (default category).
A68: TR1-057 | B68: BSI TR-03183-1 v1.0.0 | C68: 3.8.1 Default Category | D68: Self-assessment by the manufacturer based on the essential cybersecurity requirements of Annex I CRA is sufficient for this category (Article 32 (1) CRA). | E68: MAY (equiv. 'is sufficient') | F68: Conformity assessment | G68: Nil | H68: Nil - no change needed in 5. Solution Maintenance (RUN). Handled in 3. Solution Integration / Build (CRA Compliance Manager (management signatory)). | I68: None for this process | J68: No action in this process. | K68: n/a | L68: n/a | M68: Handled in 3. Solution Integration / Build | N68: n/a | O68: Assumption: all solutions are default category, as stated by the user.
A69: TR1-058 | B69: BSI TR-03183-1 v1.0.0 | C69: 3.8.1 Default Category | D69: This kind of conformity assessment based on internal control is under the sole responsibility of the manufacturer and does not require a third party. | E69: Responsibility (equiv. 'under the sole responsibility') | F69: Conformity assessment | G69: Nil | H69: Nil - no change needed in 5. Solution Maintenance (RUN). Handled in 3. Solution Integration / Build (CRA Compliance Manager (management signatory)). | I69: None for this process | J69: No action in this process. | K69: n/a | L69: n/a | M69: Handled in 3. Solution Integration / Build | N69: n/a
A70: TR1-059 | B70: BSI TR-03183-1 v1.0.0 | C70: 3.8.1 Default Category | D70: Alternatively a third-party assessment by a notified body based on module B+C or H (see next section) can be used on a voluntary basis as well as presumption of conformity via a European cybersecurity certification scheme. | E70: MAY (equiv. 'can be used on a voluntary basis') | F70: Conformity assessment | G70: Nil | H70: Nil - no change needed in 5. Solution Maintenance (RUN). Handled in 3. Solution Integration / Build (CRA Compliance Manager (management signatory)). | I70: None for this process | J70: No action in this process. | K70: n/a | L70: n/a | M70: Handled in 3. Solution Integration / Build | N70: n/a
A71: TR1-060 | B71: BSI TR-03183-1 v1.0.0 | C71: 3.8.3 Important PwDEs Class II | D71: Class II does not allow self-assessment of the manufacturer (Article 32(3) CRA). | E71: MUST NOT (equiv. 'does not allow') | F71: Product classification | G71: Nil | H71: Nil - no change needed in 5. Solution Maintenance (RUN). Not applicable to default-category products, which use Module A self-assessment. Handled in 1. Presale (Bid Manager / CRA Compliance Manager). | I71: None for this process | J71: No action in this process. | K71: n/a | L71: n/a | M71: Handled in 1. Presale | N71: n/a
A72: TR1-061 | B72: BSI TR-03183-1 v1.0.0 | C72: 3.8.4 Critical PwDEs | D72: Critical PwDEs require a certification following an European cybersecurity certification scheme (Article 32(4) CRA), if available. | E72: MUST (equiv. 'require') | F72: Product classification | G72: Nil | H72: Nil - no change needed in 5. Solution Maintenance (RUN). Not applicable to default-category products, which use Module A self-assessment. Handled in 1. Presale (Bid Manager / CRA Compliance Manager). | I72: None for this process | J72: No action in this process. | K72: n/a | L72: n/a | M72: Handled in 1. Presale | N72: n/a
A73: TR1-062 | B73: BSI TR-03183-1 v1.0.0 | C73: 3.8.4 Critical PwDEs | D73: If no such scheme exists the conformity has to be demonstrated following the procedures for important class II. | E73: MUST (equiv. 'has to') | F73: Product classification | G73: Nil | H73: Nil - no change needed in 5. Solution Maintenance (RUN). Not applicable to default-category products, which use Module A self-assessment. Handled in 1. Presale (Bid Manager / CRA Compliance Manager). | I73: None for this process | J73: No action in this process. | K73: n/a | L73: n/a | M73: Handled in 1. Presale | N73: n/a
A74: TR1-063-a | B74: BSI TR-03183-1 v1.0.0 | C74: 3.9 The Essential Requirements | D74: PwDEs and manufacturers have to comply […] to the essential cybersecurity requirements of the CRA. | E74: MUST (equiv. 'have to') | F74: CRA conformity - general | G74: Low | H74: The obligation continues after delivery for the whole support period (products and manufacturers have to comply with the essential requirements). | I74: Post-market obligations | J74: Cover the obligation in the post-market process (monitoring, updates, reviews). | K74: Post-market records | L74: Product Security Officer / PSIRT Lead | M74: Inputs from 2. and 3. | N74: S
A75: TR1-063-b | B75: BSI TR-03183-1 v1.0.0 | C75: 3.9 The Essential Requirements | D75: PwDEs and manufacturers have to […] demonstrate conformity to the essential cybersecurity requirements of the CRA. | E75: MUST (equiv. 'have to') | F75: Conformity assessment | G75: Nil | H75: Nil - no change needed in 5. Solution Maintenance (RUN). Handled in 3. Solution Integration / Build (CRA Compliance Manager (management signatory)). | I75: None for this process | J75: No action in this process. | K75: n/a | L75: n/a | M75: Handled in 3. Solution Integration / Build | N75: n/a
A76: TR1-064 | B76: BSI TR-03183-1 v1.0.0 | C76: 3.9 The Essential Requirements | D76: Only PwDEs meeting the requirements of Part I may be placed on the European market. | E76: MUST NOT (equiv. 'only ... may be placed') | F76: Conformity assessment | G76: Low | H76: Conformity must be maintained across updates; a substantial modification requires a new assessment (only products meeting Part I may be placed on the market). | I76: Change impact assessment of updates | J76: Assess each update for substantial modification and update the DoC where needed. | K76: Change impact assessment record | L76: CRA Compliance Manager | M76: Changes from 2./3. | N76: S
A77: TR1-065 | B77: BSI TR-03183-1 v1.0.0 | C77: 3.9 The Essential Requirements | D77: This has to be demonstrated by the manufacturer beforehand. | E77: MUST (equiv. 'has to') | F77: Conformity assessment | G77: Nil | H77: Nil - no change needed in 5. Solution Maintenance (RUN). Handled in 3. Solution Integration / Build (CRA Compliance Manager (management signatory)). | I77: None for this process | J77: No action in this process. | K77: n/a | L77: n/a | M77: Handled in 3. Solution Integration / Build | N77: n/a
A78: TR1-066 | B78: BSI TR-03183-1 v1.0.0 | C78: 3.9 The Essential Requirements | D78: Part II requirements are to be fulfilled by the manufacturer from the moment the PwDE is placed on the market and for the entire support period of the PwDE. | E78: MUST (equiv. 'are to be fulfilled') | F78: Lifecycle responsibility | G78: High | H78: Vulnerability-handling requirements (Part II) apply from placing on the market for the whole support period of each solution. | I78: Long-term maintenance of all supported release lines | J78: Plan PSIRT and engineering capacity per supported release line until its support end date. | K78: Support-period register per release; capacity plan | L78: Service Delivery Manager / PSIRT Lead | M78: Support periods from 1. Presale | N78: M
A79: TR1-067 | B79: BSI TR-03183-1 v1.0.0 | C79: 3.9 The Essential Requirements | D79: Nevertheless both parts are not independent of each other as Part I (2) Point (a) requires the PwDE to be free of known exploitable vulnerabilities and thus requires the manufacturer to have a vulnerability handling process in place to mitigate known exploitable vulnerabilities even before placing a PwDE on the market. | E79: MUST (equiv. 'requires') | F79: Vulnerability handling (Annex I Part II) | G79: High | H79: Vulnerability handling must already work before release: known exploitable vulnerabilities must be found and fixed before a version is placed on the market. | I79: Vulnerability handling (Annex I Part II) | J79: Implement, document and operate: a vulnerability handling process must be in place before placing on the market to avoid known exploitable vulnerabilities. | K79: Vulnerability-handling procedure; case records | L79: PSIRT Lead | M79: 2. Development (fixes), 3. Integration/Build (packages), 4. Deployment (roll-out) | N79: M
A80: TR1-068 | B80: BSI TR-03183-1 v1.0.0 | C80: 3.9 The Essential Requirements | D80: Part II requires the manufacturer to identify, address and remediate vulnerabilities. | E80: MUST (equiv. 'requires') | F80: Vulnerability handling (Annex I Part II) | G80: High | H80: Restates Part II: identify, address and remediate vulnerabilities during the support period (detailed in VH.1-VH.8a). | I80: Vulnerability handling (Annex I Part II) | J80: Implement, document and operate: Part II requires identifying, addressing and remediating vulnerabilities. | K80: Vulnerability-handling procedure; case records | L80: PSIRT Lead | M80: 2. Development (fixes), 3. Integration/Build (packages), 4. Deployment (roll-out) | N80: M
... A132: TR1-117-a | B132: BSI TR-03183-1 v1.0.0 | C132: 5.7.1 Intended purpose and reasonable foreseeable use | D132: Based on Article 13(1) products with digital elements shall be made available on the market only where they meet the essential cybersecurity requirements set out in Annex I Part I, provided that they are properly installed, maintained, used for their intended purpose or under conditions which can reasonably be foreseen, and, where applicable, the necessary security updates have been installed; […] | E132: SHALL (CRA Art. 13(1) restated) | F132: Essential requirements - general | G132: Medium | H132: Customers must be enabled to install the necessary security updates. | I132: Updates; post-market review | J132: Check in regression and post-market reviews that updates do not weaken the property. | K132: Regression/security test results for updates | L132: PSIRT Lead / QA Lead | M132: Updates from 2. Development and 3. Integration/Build | N132: M
A133: TR1-117-b | B133: BSI TR-03183-1 v1.0.0 | C133: 5.7.1 Intended purpose and reasonable foreseeable use | D133: […] and the processes put in place by the manufacturer comply with the essential cybersecurity requirements set out in Annex I Part I. | E133: SHALL (CRA Art. 13(1) restated) | F133: Vulnerability handling (Annex I Part II) | G133: High | H133: The manufacturer's processes (vulnerability handling) must comply with the essential requirements. | I133: Vulnerability handling (Annex I Part II) | J133: Implement, document and operate: the manufacturer's processes must comply with the essential requirements. | K133: Vulnerability-handling procedure; case records | L133: PSIRT Lead | M133: 2. Development (fixes), 3. Integration/Build (packages), 4. Deployment (roll-out) | N133: M | O133: TR-1 says 'Annex I Part I' for the processes; the CRA refers to the Part II (vulnerability handling) requirements here. Assessed as Part II processes - probable editorial error in TR-1.
A134: TR1-118 | B134: BSI TR-03183-1 v1.0.0 | C134: 5.7.1 Intended purpose and reasonable foreseeable use | D134: The CRA also addresses reasonably foreseeable misuse, which is in general not part of the risk assessment but has to be documented according Annex II CRA when posing a significant security risk. | E134: MUST (equiv. 'has to') | F134: User information (Annex II) | G134: Nil | H134: Nil - no change needed in 5. Solution Maintenance (RUN). Handled in 4. Solution Deployment (Deployment Manager). | I134: None for this process | J134: No action in this process. | K134: n/a | L134: n/a | M134: Handled in 4. Solution Deployment | N134: n/a
A135: TR1-119 | B135: BSI TR-03183-1 v1.0.0 | C135: 5.7.2 PwDE architecture | D135: Besides the intended purpose and foreseeable use a PwDE architecture is also necessary to perform an effective risk assessment. | E135: MUST (equiv. 'is also necessary') | F135: Risk assessment - context | G135: Nil | H135: Nil - no change needed in 5. Solution Maintenance (RUN). Handled in 2. Solution Development (Security Architect). | I135: None for this process | J135: No action in this process. | K135: n/a | L135: n/a | M135: Handled in 2. Solution Development | N135: n/a
A136: TR1-120 | B136: BSI TR-03183-1 v1.0.0 | C136: 5.7.2 PwDE architecture | D136: [The architecture is a high level technical description of the PwDE and should include:] The connective capabilities of the PwDE (WAN, Bluetooth, WLAN or other ) | E136: SHOULD (equiv. 'should include') | F136: Risk assessment - context | G136: Nil | H136: Nil - no change needed in 5. Solution Maintenance (RUN). Handled in 2. Solution Development (Security Architect). | I136: None for this process | J136: No action in this process. | K136: n/a | L136: n/a | M136: Handled in 2. Solution Development | N136: n/a
A137: TR1-121 | B137: BSI TR-03183-1 v1.0.0 | C137: 5.7.2 PwDE architecture | D137: [The architecture is a high level technical description of the PwDE and should include:] The (potential) relation and communication of the PwDE's components with its remote data processing solutions | E137: SHOULD (equiv. 'should include') | F137: Risk assessment - context | G137: Nil | H137: Nil - no change needed in 5. Solution Maintenance (RUN). Handled in 2. Solution Development (Security Architect). | I137: None for this process | J137: No action in this process. | K137: n/a | L137: n/a | M137: Handled in 2. Solution Development | N137: n/a
A138: TR1-122 | B138: BSI TR-03183-1 v1.0.0 | C138: 5.7.2 PwDE architecture | D138: [The architecture is a high level technical description of the PwDE and should include:] The (potential) relation and communication to other PwDE or PwDE components | E138: SHOULD (equiv. 'should include') | F138: Risk assessment - context | G138: Nil | H138: Nil - no change needed in 5. Solution Maintenance (RUN). Handled in 2. Solution Development (Security Architect). | I138: None for this process | J138: No action in this process. | K138: n/a | L138: n/a | M138: Handled in 2. Solution Development | N138: n/a
A139: TR1-123 | B139: BSI TR-03183-1 v1.0.0 | C139: 5.7.2 PwDE architecture | D139: [The architecture is a high level technical description of the PwDE and should include:] The boundaries of the PwDE | E139: SHOULD (equiv. 'should include') | F139: Risk assessment - context | G139: Nil | H139: Nil - no change needed in 5. Solution Maintenance (RUN). Handled in 2. Solution Development (Security Architect). | I139: None for this process | J139: No action in this process. | K139: n/a | L139: n/a | M139: Handled in 2. Solution Development | N139: n/a
A140: TR1-124 | B140: BSI TR-03183-1 v1.0.0 | C140: 5.7.2 PwDE architecture | D140: This is generally no problem for components in scope of the CRA as they are required to be designed, developed and produced in such a way that they ensure an appropriate level of cybersecurity based on the risks for the intended purpose. | E140: MUST (equiv. 'are required to'; other manufacturers) | F140: Third-party component due diligence | G140: Nil | H140: Nil - no change needed in 5. Solution Maintenance (RUN). Handled in 2. Solution Development (Software Architect / Open Source Program Office). | I140: None for this process | J140: No action in this process. | K140: n/a | L140: n/a | M140: Handled in 2. Solution Development | N140: n/a
A141: TR1-125-a | B141: BSI TR-03183-1 v1.0.0 | C141: 5.7.2 PwDE architecture | D141: The manufacturer is generally responsible for third-party components integrated by the manufacturer itself […] | E141: Responsibility (equiv. 'is responsible') | F141: Third-party component due diligence | G141: Low | H141: Third-party components must be monitored for vulnerabilities and support status, and upstream maintainers informed (the manufacturer is responsible for third-party components it integrates). | I141: Supplier vulnerability information; upstream reporting | J141: Monitor supplier advisories and end-of-life dates; report found vulnerabilities upstream and track responses. | K141: Supplier advisory log; upstream reports | L141: PSIRT Lead | M141: SBOM from 3. Integration/Build | N141: S
A142: TR1-125-b | B142: BSI TR-03183-1 v1.0.0 | C142: 5.7.2 PwDE architecture | D142: […] and has to exercise due diligence according to CRA Article 13 (5). | E142: MUST (equiv. 'has to') | F142: Third-party component due diligence | G142: Low | H142: Third-party components must be monitored for vulnerabilities and support status, and upstream maintainers informed (exercise due diligence for integrated third-party components (Art. 13(5))). | I142: Supplier vulnerability information; upstream reporting | J142: Monitor supplier advisories and end-of-life dates; report found vulnerabilities upstream and track responses. | K142: Supplier advisory log; upstream reports | L142: PSIRT Lead | M142: SBOM from 3. Integration/Build | N142: S
A143: TR1-126 | B143: BSI TR-03183-1 v1.0.0 | C143: 5.7.3 Decision Criteria | D143: To establish a comprehensible and consistent assessment the factors and criteria used for decision making have to be established as part of the risk context. | E143: MUST (equiv. 'have to') | F143: Risk decision criteria | G143: Nil | H143: Nil - no change needed in 5. Solution Maintenance (RUN). Handled in 2. Solution Development (Security Architect / Product Security Officer). | I143: None for this process | J143: No action in this process. | K143: n/a | L143: n/a | M143: Handled in 2. Solution Development | N143: n/a
A144: TR1-127 | B144: BSI TR-03183-1 v1.0.0 | C144: 5.7.3 Decision Criteria | D144: It is generally advisable to use existing specific standards based on existing sectorial knowledge and best practices. | E144: SHOULD (equiv. 'is generally advisable') | F144: Risk decision criteria | G144: Nil | H144: Nil - no change needed in 5. Solution Maintenance (RUN). Handled in 2. Solution Development (Security Architect). | I144: None for this process | J144: No action in this process. | K144: n/a | L144: n/a | M144: Handled in 2. Solution Development | N144: n/a
A145: TR1-128 | B145: BSI TR-03183-1 v1.0.0 | C145: 5.7.3 Decision Criteria | D145: A strategy on using these decision criteria as well as an initial set of criteria will be provided at the end of this chapter and can be tailored by the manufacturer for his specific use case based on its specific processes. | E145: MAY (equiv. 'can be tailored') | F145: Risk decision criteria | G145: Nil | H145: Nil - no change needed in 5. Solution Maintenance (RUN). Handled in 2. Solution Development (Security Architect / Product Security Officer). | I145: None for this process | J145: No action in this process. | K145: n/a | L145: n/a | M145: Handled in 2. Solution Development | N145: n/a
... A155: TR1-136 | B155: BSI TR-03183-1 v1.0.0 | C155: 5.9.1 Risk Analysis - General | D155: If the impact or likelihood of an identified risk can not be assessed, because it depends on additional parameters, e.g. attacker potential, duration of the incident, number of affected PwDEs, the identified risk should be split into multiple risks depending on the parameters. | E155: SHOULD (equiv. 'should') | F155: Risk assessment - analysis | G155: Nil | H155: Nil - no change needed in 5. Solution Maintenance (RUN). Handled in 2. Solution Development (Security Architect). | I155: None for this process | J155: No action in this process. | K155: n/a | L155: n/a | M155: Handled in 2. Solution Development | N155: n/a
A156: TR1-137 | B156: BSI TR-03183-1 v1.0.0 | C156: 5.9.1 Risk Analysis - General (NOTE) | D156: It is generally advisable to use sectorial appropriate methods for the risk analysis, fitting for the specific use case. | E156: SHOULD (equiv. 'is generally advisable') | F156: Risk assessment - method | G156: Nil | H156: Nil - no change needed in 5. Solution Maintenance (RUN). Handled in 2. Solution Development (Security Architect). | I156: None for this process | J156: No action in this process. | K156: n/a | L156: n/a | M156: Handled in 2. Solution Development | N156: n/a | O156: Text taken from the official BSI PDF of TR-03183-1 v1.0.0: the Markdown conversion garbled or dropped this passage.
A157: TR1-138 | B157: BSI TR-03183-1 v1.0.0 | C157: 5.9.1 Risk Analysis - General (NOTE) | D157: As it's generally not possible to completely, precisely and objectively assess the likelihood and impact of risks, the effort used for the risk analysis should be put into perspective to the effort of treating a potential risk. | E157: SHOULD (equiv. 'should') | F157: Risk assessment - method | G157: Nil | H157: Nil - no change needed in 5. Solution Maintenance (RUN). Handled in 2. Solution Development (Security Architect). | I157: None for this process | J157: No action in this process. | K157: n/a | L157: n/a | M157: Handled in 2. Solution Development | N157: n/a | O157: Text taken from the official BSI PDF of TR-03183-1 v1.0.0: the Markdown conversion garbled or dropped this passage.
A158: RH_RA.1.2 | B158: BSI TR-03183-1 v1.0.0 | C158: 5.9.3 Control - RH_RA.1.2 Risk Analysis (Activity) | D158: The manufacturer MUST analyse the risks of the PwDE in regard to their likelihood and potential impact. [Output: List of (analysed) risks including impact and likelihood] | E158: MUST | F158: Risk assessment - analysis | G158: Medium | H158: Post-market events (new vulnerabilities, threats, changes) must update the risk assessment (analyse the risks for likelihood and potential impact). | I158: Risk-assessment updates | J158: Trigger risk-assessment updates from PSIRT cases and threat intelligence. | K158: Updated risk-assessment versions | L158: Product Security Officer | M158: Analysis by 2. Development | N158: M
A159: TR1-139 | B159: BSI TR-03183-1 v1.0.0 | C159: 5.10.1 Risk Evaluation - General | D159: After the risks have been analysed, the manufacturer needs to evaluate if the analysed risks have to be treated or can be accepted. | E159: MUST (equiv. 'needs to') | F159: Risk assessment - evaluation | G159: Low | H159: Post-market events (new vulnerabilities, threats, changes) must update the risk assessment (evaluate whether analysed risks must be treated or can be accepted). | I159: Risk-assessment updates | J159: Trigger risk-assessment updates from PSIRT cases and threat intelligence. | K159: Updated risk-assessment versions | L159: Product Security Officer | M159: Analysis by 2. Development | N159: S
A160: RH_RA.1.3 | B160: BSI TR-03183-1 v1.0.0 | C160: 5.10.3 Control - RH_RA.1.3 Risk Evaluation (Activity) | D160: The manufacturer MUST evaluate whether the analysed risks of the PwDE can be accepted or not. [Output: List of (evaluated risks), which have to be treated or have been accepted] | E160: MUST | F160: Risk assessment - evaluation | G160: Medium | H160: Post-market events (new vulnerabilities, threats, changes) must update the risk assessment (evaluate whether the analysed risks can be accepted). | I160: Risk-assessment updates | J160: Trigger risk-assessment updates from PSIRT cases and threat intelligence. | K160: Updated risk-assessment versions | L160: Product Security Officer | M160: Analysis by 2. Development | N160: M
A161: TR1-140 | B161: BSI TR-03183-1 v1.0.0 | C161: 5.11 RH_RT.1 Risk Treatment | D161: Risks which a not accepted have to be treated. | E161: MUST (equiv. 'have to') | F161: Risk treatment | G161: Low | H161: New risks found after release must be treated in the same way (risks that are not accepted have to be treated). | I161: Post-market risk treatment | J161: Treat post-market risks via fixes, mitigations or documented acceptance. | K161: Treatment records | L161: Product Security Officer | M161: 2. Development | N161: S
A162: TR1-141 | B162: BSI TR-03183-1 v1.0.0 | C162: 5.11 RH_RT.1 Risk Treatment | D162: This entails that an appropriate risk treatment based on the risk is a required part of the PwDE design. | E162: MUST (equiv. 'is a required part') | F162: Risk treatment | G162: Nil | H162: Nil - no change needed in 5. Solution Maintenance (RUN). Handled in 2. Solution Development (Security Architect). | I162: None for this process | J162: No action in this process. | K162: n/a | L162: n/a | M162: Handled in 2. Solution Development | N162: n/a
A163: TR1-142 | B163: BSI TR-03183-1 v1.0.0 | C163: 5.11.1.1 Select appropriate controls - General | D163: The manufacturer has to meet the requirement Annex I Part I (1) by designing, developing and producing PwDEs in such a way that they ensure an appropriate level of cybersecurity based on the risks. | E163: MUST (equiv. 'has to') | F163: Risk treatment | G163: Nil | H163: Nil - no change needed in 5. Solution Maintenance (RUN). Handled in 2. Solution Development (Security Architect). | I163: None for this process | J163: No action in this process. | K163: n/a | L163: n/a | M163: Handled in 2. Solution Development | N163: n/a
A164: TR1-143 | B164: BSI TR-03183-1 v1.0.0 | C164: 5.11.1.1 Select appropriate controls - General | D164: This requires an initial selection of appropriate controls based on the risks to be treated. | E164: MUST (equiv. 'requires') | F164: Risk treatment | G164: Nil | H164: Nil - no change needed in 5. Solution Maintenance (RUN). Handled in 2. Solution Development (Security Architect). | I164: None for this process | J164: No action in this process. | K164: n/a | L164: n/a | M164: Handled in 2. Solution Development | N164: n/a
A165: TR1-144 | B165: BSI TR-03183-1 v1.0.0 | C165: 5.11.1.1 Select appropriate controls - General | D165: If a risk can not be effectively treated by the manufacturer on his own, risk sharing can be used. | E165: MAY (equiv. 'can be used') | F165: Risk sharing | G165: Nil | H165: Nil - no change needed in 5. Solution Maintenance (RUN). Handled in 2. Solution Development (Security Architect). | I165: None for this process | J165: No action in this process. | K165: n/a | L165: n/a | M165: Handled in 2. Solution Development | N165: n/a
A166: RH_RT.1.1.1-a | B166: BSI TR-03183-1 v1.0.0 | C166: 5.11.1.3 Control - RH_RT.1.1.1 Select appropriate controls (Activity) | D166: The manufacturer MUST select appropriate controls to treat the evaluated risks and to reduce them to an acceptable level […] | E166: MUST | F166: Risk treatment | G166: Medium | H166: New risks found after release must be treated in the same way (select controls that reduce evaluated risks to an acceptable level). | I166: Post-market risk treatment | J166: Treat post-market risks via fixes, mitigations or documented acceptance. | K166: Treatment records | L166: Product Security Officer | M166: 2. Development | N166: M
A167: RH_RT.1.1.1-b | B167: BSI TR-03183-1 v1.0.0 | C167: 5.11.1.3 Control - RH_RT.1.1.1 Select appropriate controls (Activity) | D167: […] and include the selected controls in the design of the PwDE. [Output: List of selected controls and associated risks to be included in the design of the PwDE] | E167: MUST | F167: Risk treatment | G167: Nil | H167: Nil - no change needed in 5. Solution Maintenance (RUN). Handled in 2. Solution Development (Security Architect). | I167: None for this process | J167: No action in this process. | K167: n/a | L167: n/a | M167: Handled in 2. Solution Development | N167: n/a
A168: TR1-145-a | B168: BSI TR-03183-1 v1.0.0 | C168: 5.11.2.1 Select Applicable Essential Cybersecurity Requirements - General | D168: The manufacturer also has to meet […] the applicable requirements of Annex I Part I (2) on the basis of the cybersecurity risk assessment. | E168: MUST (equiv. 'has to') | F168: Essential requirements - applicability | G168: Nil | H168: Nil - no change needed in 5. Solution Maintenance (RUN). Handled in 2. Solution Development (Security Architect). | I168: None for this process | J168: No action in this process. | K168: n/a | L168: n/a | M168: Handled in 2. Solution Development | N168: n/a
A169: TR1-145-b | B169: BSI TR-03183-1 v1.0.0 | C169: 5.11.2.1 Select Applicable Essential Cybersecurity Requirements - General | D169: The manufacturer also has to […] document the applicable requirements of Annex I Part I (2) on the basis of the cybersecurity risk assessment. | E169: MUST (equiv. 'has to') | F169: Essential requirements - applicability | G169: Nil | H169: Nil - no change needed in 5. Solution Maintenance (RUN). Handled in 3. Solution Integration / Build (CRA Compliance Manager / Technical Documentation Lead). | I169: None for this process | J169: No action in this process. | K169: n/a | L169: n/a | M169: Handled in 3. Solution Integration / Build | N169: n/a
... A203: TR1-166 | B203: BSI TR-03183-1 v1.0.0 | C203: 5.14.3 Acceptance Criteria | D203: [This guideline will use the following criteria for acceptance of risks:] The risk for a high or higher impact of a network attack is not acceptable, if the network restrictions do not prevent network access to a known limited group potentially malicious actors with the capability to perform high complexity attacks. | E203: MUST NOT (equiv. 'is not acceptable') | F203: Risk acceptance criteria | G203: Nil | H203: Nil - no change needed in 5. Solution Maintenance (RUN). Handled in 2. Solution Development (Security Architect / Product Security Officer). | I203: None for this process | J203: No action in this process. | K203: n/a | L203: n/a | M203: Handled in 2. Solution Development | N203: n/a
A204: TR1-167 | B204: BSI TR-03183-1 v1.0.0 | C204: 5.14.3 Acceptance Criteria | D204: [This guideline will use the following criteria for acceptance of risks:] The risk for a moderate or higher impact based on an initial misconfiguration of the PwDE is not acceptable, if the user is a layman. | E204: MUST NOT (equiv. 'is not acceptable') | F204: Risk acceptance criteria | G204: Nil | H204: Nil - no change needed in 5. Solution Maintenance (RUN). Handled in 2. Solution Development (Security Architect / Product Security Officer). | I204: None for this process | J204: No action in this process. | K204: n/a | L204: n/a | M204: Handled in 2. Solution Development | N204: n/a | O204: Assumption: customer operators are skilled IT/OT professionals.
A205: TR1-168 | B205: BSI TR-03183-1 v1.0.0 | C205: 5.14.3 Acceptance Criteria | D205: [This guideline will use the following criteria for acceptance of risks:] The risk for a high or very high impact based on an initial misconfiguration of the PwDE is not acceptable, if the user is an instructed tradesmen but not a skilled expert. | E205: MUST NOT (equiv. 'is not acceptable') | F205: Risk acceptance criteria | G205: Nil | H205: Nil - no change needed in 5. Solution Maintenance (RUN). Handled in 2. Solution Development (Security Architect / Product Security Officer). | I205: None for this process | J205: No action in this process. | K205: n/a | L205: n/a | M205: Handled in 2. Solution Development | N205: n/a
...

Sheet Summary
A1: CRA / BSI TR-03183 impact summary - 5. Solution Maintenance (RUN) | X1: helper: listed row | Y1: helper: Critical rows | Z1: helper: High rows
A2: Role: solution provider acting as CRA manufacturer; default-category solutions for governments and airports. Assessment date 18 Oct 2026. | Y2: =IF(Assessment!$G2="Critical",ROW(Assessment!$G2),"") | Z2: =IF(Assessment!$G2="High",ROW(Assessment!$G2),"")
A3: All counts are COUNTIF / COUNTIFS formulas on the Assessment sheet and update when a rating is changed there. | Y3: =IF(Assessment!$G3="Critical",ROW(Assessment!$G3),"") | Z3: =IF(Assessment!$G3="High",ROW(Assessment!$G3),"")
Y4: =IF(Assessment!$G4="Critical",ROW(Assessment!$G4),"") | Z4: =IF(Assessment!$G4="High",ROW(Assessment!$G4),"")
A5: Impact rating | B5: All documents | C5: BSI TR-03183-1 v1.0.0 | D5: BSI TR-03183-2 v2.1.0 | E5: BSI TR-03183-3 v1.0.0 | F5: Share of all requirements | Y5: =IF(Assessment!$G5="Critical",ROW(Assessment!$G5),"") | Z5: =IF(Assessment!$G5="High",ROW(Assessment!$G5),"")
A6: Critical | B6: =COUNTIF(Assessment!$G:$G,$A6) -> 26 | C6: =COUNTIFS(Assessment!$B:$B,C$5,Assessment!$G:$G,$A6) -> 20 | D6: =COUNTIFS(Assessment!$B:$B,D$5,Assessment!$G:$G,$A6) -> 1 | E6: =COUNTIFS(Assessment!$B:$B,E$5,Assessment!$G:$G,$A6) -> 5 | F6: =IF($B$11=0,0,B6/$B$11) -> 0.043918919 | Y6: =IF(Assessment!$G6="Critical",ROW(Assessment!$G6),"") -> 6 | Z6: =IF(Assessment!$G6="High",ROW(Assessment!$G6),"")
A7: High | B7: =COUNTIF(Assessment!$G:$G,$A7) -> 63 | C7: =COUNTIFS(Assessment!$B:$B,C$5,Assessment!$G:$G,$A7) -> 34 | D7: =COUNTIFS(Assessment!$B:$B,D$5,Assessment!$G:$G,$A7) -> 6 | E7: =COUNTIFS(Assessment!$B:$B,E$5,Assessment!$G:$G,$A7) -> 23 | F7: =IF($B$11=0,0,B7/$B$11) -> 0.10641892 | Y7: =IF(Assessment!$G7="Critical",ROW(Assessment!$G7),"") -> 7 | Z7: =IF(Assessment!$G7="High",ROW(Assessment!$G7),"")
A8: Medium | B8: =COUNTIF(Assessment!$G:$G,$A8) -> 119 | C8: =COUNTIFS(Assessment!$B:$B,C$5,Assessment!$G:$G,$A8) -> 51 | D8: =COUNTIFS(Assessment!$B:$B,D$5,Assessment!$G:$G,$A8) -> 14 | E8: =COUNTIFS(Assessment!$B:$B,E$5,Assessment!$G:$G,$A8) -> 54 | F8: =IF($B$11=0,0,B8/$B$11) -> 0.20101351 | Y8: =IF(Assessment!$G8="Critical",ROW(Assessment!$G8),"") | Z8: =IF(Assessment!$G8="High",ROW(Assessment!$G8),"")
A9: Low | B9: =COUNTIF(Assessment!$G:$G,$A9) -> 169 | C9: =COUNTIFS(Assessment!$B:$B,C$5,Assessment!$G:$G,$A9) -> 49 | D9: =COUNTIFS(Assessment!$B:$B,D$5,Assessment!$G:$G,$A9) -> 20 | E9: =COUNTIFS(Assessment!$B:$B,E$5,Assessment!$G:$G,$A9) -> 100 | F9: =IF($B$11=0,0,B9/$B$11) -> 0.28547297 | Y9: =IF(Assessment!$G9="Critical",ROW(Assessment!$G9),"") | Z9: =IF(Assessment!$G9="High",ROW(Assessment!$G9),"") -> 9
A10: Nil | B10: =COUNTIF(Assessment!$G:$G,$A10) -> 215 | C10: =COUNTIFS(Assessment!$B:$B,C$5,Assessment!$G:$G,$A10) -> 128 | D10: =COUNTIFS(Assessment!$B:$B,D$5,Assessment!$G:$G,$A10) -> 87 | E10: =COUNTIFS(Assessment!$B:$B,E$5,Assessment!$G:$G,$A10) -> 0 | F10: =IF($B$11=0,0,B10/$B$11) -> 0.36317568 | Y10: =IF(Assessment!$G10="Critical",ROW(Assessment!$G10),"") | Z10: =IF(Assessment!$G10="High",ROW(Assessment!$G10),"") -> 10
A11: Total | B11: =SUM(B6:B10) -> 592 | C11: =SUM(C6:C10) -> 282 | D11: =SUM(D6:D10) -> 128 | E11: =SUM(E6:E10) -> 182 | Y11: =IF(Assessment!$G11="Critical",ROW(Assessment!$G11),"") | Z11: =IF(Assessment!$G11="High",ROW(Assessment!$G11),"")
A12: Requirements in register | B12: =COUNTA(Assessment!$A:$A)-1 -> 592 | C12: =COUNTIF(Assessment!$B:$B,C$5) -> 282 | D12: =COUNTIF(Assessment!$B:$B,D$5) -> 128 | E12: =COUNTIF(Assessment!$B:$B,E$5) -> 182 | Y12: =IF(Assessment!$G12="Critical",ROW(Assessment!$G12),"") | Z12: =IF(Assessment!$G12="High",ROW(Assessment!$G12),"") -> 12
A13: Check: total = register | B13: =IF(B11=B12,"OK","CHECK") -> OK | C13: =IF(C11=C12,"OK","CHECK") -> OK | D13: =IF(D11=D12,"OK","CHECK") -> OK | E13: =IF(E11=E12,"OK","CHECK") -> OK | Y13: =IF(Assessment!$G13="Critical",ROW(Assessment!$G13),"") | Z13: =IF(Assessment!$G13="High",ROW(Assessment!$G13),"")
Y14: =IF(Assessment!$G14="Critical",ROW(Assessment!$G14),"") | Z14: =IF(Assessment!$G14="High",ROW(Assessment!$G14),"")
A15: Critical and High items (formula-driven: Critical first, then High, each in register order) | Y15: =IF(Assessment!$G15="Critical",ROW(Assessment!$G15),"") | Z15: =IF(Assessment!$G15="High",ROW(Assessment!$G15),"")
A16: # | B16: Req ID | C16: Source document | D16: Section | E16: Topic | F16: Impact rating | G16: Required changes / actions | H16: Owner role | I16: Effort (S/M/L) | Y16: =IF(Assessment!$G16="Critical",ROW(Assessment!$G16),"") | Z16: =IF(Assessment!$G16="High",ROW(Assessment!$G16),"")
A17: =IF($X17="","",1) -> 1 | B17: =IF($X17="","",INDEX(Assessment!$A:$A,$X17)) -> TR1-005 | C17: =IF($X17="","",INDEX(Assessment!$B:$B,$X17)) -> BSI TR-03183-1 v1.0.0 | D17: =IF($X17="","",INDEX(Assessment!$C:$C,$X17)) -> 3.4 Timeline | E17: =IF($X17="","",INDEX(Assessment!$F:$F,$X17)) -> CRA timeline - reporting obligations | F17: =IF($X17="","",INDEX(Assessment!$G:$G,$X17)) -> Critical | G17: =IF($X17="","",INDEX(Assessment!$J:$J,$X17)) -> Set up an interim reporting capability immediately: name reporters and deputies, register on the single reporting platform, prepare templates, define awareness criteria and a 24/7 escalation path; rehearse once. | H17: =IF($X17="","",INDEX(Assessment!$L:$L,$X17)) -> PSIRT Lead / Service Delivery Manager | I17: =IF($X17="","",INDEX(Assessment!$N:$N,$X17)) -> L | X17: =IF(1<=$B$6,SMALL($Y$2:$Y$593,1),IF(1<=$B$6+$B$7,SMALL($Z$2:$Z$593,1-$B$6),"")) -> 6 | Y17: =IF(Assessment!$G17="Critical",ROW(Assessment!$G17),"") | Z17: =IF(Assessment!$G17="High",ROW(Assessment!$G17),"")
A18: =IF($X18="","",2) -> 2 | B18: =IF($X18="","",INDEX(Assessment!$A:$A,$X18)) -> TR1-006 | C18: =IF($X18="","",INDEX(Assessment!$B:$B,$X18)) -> BSI TR-03183-1 v1.0.0 | D18: =IF($X18="","",INDEX(Assessment!$C:$C,$X18)) -> 3.4 Timeline | E18: =IF($X18="","",INDEX(Assessment!$F:$F,$X18)) -> CRA timeline - reporting obligations | F18: =IF($X18="","",INDEX(Assessment!$G:$G,$X18)) -> Critical | G18: =IF($X18="","",INDEX(Assessment!$J:$J,$X18)) -> Build or complete the installed-base register for all delivered solutions still in operation and link it to the PSIRT reporting procedure. | H18: =IF($X18="","",INDEX(Assessment!$L:$L,$X18)) -> PSIRT Lead / Service Delivery Manager | I18: =IF($X18="","",INDEX(Assessment!$N:$N,$X18)) -> L | X18: =IF(2<=$B$6,SMALL($Y$2:$Y$593,2),IF(2<=$B$6+$B$7,SMALL($Z$2:$Z$593,2-$B$6),"")) -> 7 | Y18: =IF(Assessment!$G18="Critical",ROW(Assessment!$G18),"") | Z18: =IF(Assessment!$G18="High",ROW(Assessment!$G18),"")
A19: =IF($X19="","",3) -> 3 | B19: =IF($X19="","",INDEX(Assessment!$A:$A,$X19)) -> TR1-028-a | C19: =IF($X19="","",INDEX(Assessment!$B:$B,$X19)) -> BSI TR-03183-1 v1.0.0 | D19: =IF($X19="","",INDEX(Assessment!$C:$C,$X19)) -> 3.6 Obligations of the manufacturer - PwDE Monitoring and Post-Market Obligations | E19: =IF($X19="","",INDEX(Assessment!$F:$F,$X19)) -> Vulnerability monitoring | F19: =IF($X19="","",INDEX(Assessment!$G:$G,$X19)) -> Critical | G19: =IF($X19="","",INDEX(Assessment!$J:$J,$X19)) -> Operate SBOM-based continuous vulnerability monitoring, periodic security reviews and remediation for all supported releases. | H19: =IF($X19="","",INDEX(Assessment!$L:$L,$X19)) -> PSIRT Lead / Product Security Officer | I19: =IF($X19="","",INDEX(Assessment!$N:$N,$X19)) -> L | X19: =IF(3<=$B$6,SMALL($Y$2:$Y$593,3),IF(3<=$B$6+$B$7,SMALL($Z$2:$Z$593,3-$B$6),"")) -> 33 | Y19: =IF(Assessment!$G19="Critical",ROW(Assessment!$G19),"") | Z19: =IF(Assessment!$G19="High",ROW(Assessment!$G19),"") -> 19
A20: =IF($X20="","",4) -> 4 | B20: =IF($X20="","",INDEX(Assessment!$A:$A,$X20)) -> TR1-028-b | C20: =IF($X20="","",INDEX(Assessment!$B:$B,$X20)) -> BSI TR-03183-1 v1.0.0 | D20: =IF($X20="","",INDEX(Assessment!$C:$C,$X20)) -> 3.6 Obligations of the manufacturer - PwDE Monitoring and Post-Market Obligations | E20: =IF($X20="","",INDEX(Assessment!$F:$F,$X20)) -> Vulnerability remediation | F20: =IF($X20="","",INDEX(Assessment!$G:$G,$X20)) -> Critical | G20: =IF($X20="","",INDEX(Assessment!$J:$J,$X20)) -> Operate SBOM-based continuous vulnerability monitoring, periodic security reviews and remediation for all supported releases. | H20: =IF($X20="","",INDEX(Assessment!$L:$L,$X20)) -> PSIRT Lead / Product Security Officer | I20: =IF($X20="","",INDEX(Assessment!$N:$N,$X20)) -> L | X20: =IF(4<=$B$6,SMALL($Y$2:$Y$593,4),IF(4<=$B$6+$B$7,SMALL($Z$2:$Z$593,4-$B$6),"")) -> 34 | Y20: =IF(Assessment!$G20="Critical",ROW(Assessment!$G20),"") | Z20: =IF(Assessment!$G20="High",ROW(Assessment!$G20),"")
A21: =IF($X21="","",5) -> 5 | B21: =IF($X21="","",INDEX(Assessment!$A:$A,$X21)) -> TR1-032-a | C21: =IF($X21="","",INDEX(Assessment!$B:$B,$X21)) -> BSI TR-03183-1 v1.0.0 | D21: =IF($X21="","",INDEX(Assessment!$C:$C,$X21)) -> 3.6 Obligations of the manufacturer - Reporting obligations | E21: =IF($X21="","",INDEX(Assessment!$F:$F,$X21)) -> CRA Art. 14 reporting - vulnerabilities | F21: =IF($X21="","",INDEX(Assessment!$G:$G,$X21)) -> Critical | G21: =IF($X21="","",INDEX(Assessment!$J:$J,$X21)) -> Implement the reporting procedure: awareness criteria, 24h / 72h / 14-day (vulnerability) and 24h / 72h / one-month (incident) timelines, platform accounts, templates, approvals and 24/7 escalation; rehearse it. | H21: =IF($X21="","",INDEX(Assessment!$L:$L,$X21)) -> PSIRT Lead / Compliance Officer | I21: =IF($X21="","",INDEX(Assessment!$N:$N,$X21)) -> L | X21: =IF(5<=$B$6,SMALL($Y$2:$Y$593,5),IF(5<=$B$6+$B$7,SMALL($Z$2:$Z$593,5-$B$6),"")) -> 40 | Y21: =IF(Assessment!$G21="Critical",ROW(Assessment!$G21),"") | Z21: =IF(Assessment!$G21="High",ROW(Assessment!$G21),"")
A22: =IF($X22="","",6) -> 6 | B22: =IF($X22="","",INDEX(Assessment!$A:$A,$X22)) -> TR1-032-b | C22: =IF($X22="","",INDEX(Assessment!$B:$B,$X22)) -> BSI TR-03183-1 v1.0.0 | D22: =IF($X22="","",INDEX(Assessment!$C:$C,$X22)) -> 3.6 Obligations of the manufacturer - Reporting obligations | E22: =IF($X22="","",INDEX(Assessment!$F:$F,$X22)) -> CRA Art. 14 reporting - incidents | F22: =IF($X22="","",INDEX(Assessment!$G:$G,$X22)) -> Critical | G22: =IF($X22="","",INDEX(Assessment!$J:$J,$X22)) -> Implement the reporting procedure: awareness criteria, 24h / 72h / 14-day (vulnerability) and 24h / 72h / one-month (incident) timelines, platform accounts, templates, approvals and 24/7 escalation; rehearse it. | H22: =IF($X22="","",INDEX(Assessment!$L:$L,$X22)) -> PSIRT Lead / Compliance Officer | I22: =IF($X22="","",INDEX(Assessment!$N:$N,$X22)) -> L | X22: =IF(6<=$B$6,SMALL($Y$2:$Y$593,6),IF(6<=$B$6+$B$7,SMALL($Z$2:$Z$593,6-$B$6),"")) -> 41 | Y22: =IF(Assessment!$G22="Critical",ROW(Assessment!$G22),"") | Z22: =IF(Assessment!$G22="High",ROW(Assessment!$G22),"")
A23: =IF($X23="","",7) -> 7 | B23: =IF($X23="","",INDEX(Assessment!$A:$A,$X23)) -> TR1-033 | C23: =IF($X23="","",INDEX(Assessment!$B:$B,$X23)) -> BSI TR-03183-1 v1.0.0 | D23: =IF($X23="","",INDEX(Assessment!$C:$C,$X23)) -> 3.6 Obligations of the manufacturer - Reporting obligations | E23: =IF($X23="","",INDEX(Assessment!$F:$F,$X23)) -> CRA Art. 14 reporting - channel | F23: =IF($X23="","",INDEX(Assessment!$G:$G,$X23)) -> Critical | G23: =IF($X23="","",INDEX(Assessment!$J:$J,$X23)) -> Implement the reporting procedure: awareness criteria, 24h / 72h / 14-day (vulnerability) and 24h / 72h / one-month (incident) timelines, platform accounts, templates, approvals and 24/7 escalation; rehearse it. | H23: =IF($X23="","",INDEX(Assessment!$L:$L,$X23)) -> PSIRT Lead / Compliance Officer | I23: =IF($X23="","",INDEX(Assessment!$N:$N,$X23)) -> L | X23: =IF(7<=$B$6,SMALL($Y$2:$Y$593,7),IF(7<=$B$6+$B$7,SMALL($Z$2:$Z$593,7-$B$6),"")) -> 42 | Y23: =IF(Assessment!$G23="Critical",ROW(Assessment!$G23),"") | Z23: =IF(Assessment!$G23="High",ROW(Assessment!$G23),"")
A24: =IF($X24="","",8) -> 8 | B24: =IF($X24="","",INDEX(Assessment!$A:$A,$X24)) -> TR1-034-a | C24: =IF($X24="","",INDEX(Assessment!$B:$B,$X24)) -> BSI TR-03183-1 v1.0.0 | D24: =IF($X24="","",INDEX(Assessment!$C:$C,$X24)) -> 3.6 Obligations of the manufacturer - Reporting obligations | E24: =IF($X24="","",INDEX(Assessment!$F:$F,$X24)) -> CRA Art. 14 reporting - vulnerabilities | F24: =IF($X24="","",INDEX(Assessment!$G:$G,$X24)) -> Critical | G24: =IF($X24="","",INDEX(Assessment!$J:$J,$X24)) -> Implement the reporting procedure: awareness criteria, 24h / 72h / 14-day (vulnerability) and 24h / 72h / one-month (incident) timelines, platform accounts, templates, approvals and 24/7 escalation; rehearse it. | H24: =IF($X24="","",INDEX(Assessment!$L:$L,$X24)) -> PSIRT Lead / Compliance Officer | I24: =IF($X24="","",INDEX(Assessment!$N:$N,$X24)) -> L | X24: =IF(8<=$B$6,SMALL($Y$2:$Y$593,8),IF(8<=$B$6+$B$7,SMALL($Z$2:$Z$593,8-$B$6),"")) -> 43 | Y24: =IF(Assessment!$G24="Critical",ROW(Assessment!$G24),"") | Z24: =IF(Assessment!$G24="High",ROW(Assessment!$G24),"")
A25: =IF($X25="","",9) -> 9 | B25: =IF($X25="","",INDEX(Assessment!$A:$A,$X25)) -> TR1-035 | C25: =IF($X25="","",INDEX(Assessment!$B:$B,$X25)) -> BSI TR-03183-1 v1.0.0 | D25: =IF($X25="","",INDEX(Assessment!$C:$C,$X25)) -> 3.6 Obligations of the manufacturer - Reporting obligations | E25: =IF($X25="","",INDEX(Assessment!$F:$F,$X25)) -> CRA Art. 14 reporting - vulnerabilities | F25: =IF($X25="","",INDEX(Assessment!$G:$G,$X25)) -> Critical | G25: =IF($X25="","",INDEX(Assessment!$J:$J,$X25)) -> Implement the reporting procedure: awareness criteria, 24h / 72h / 14-day (vulnerability) and 24h / 72h / one-month (incident) timelines, platform accounts, templates, approvals and 24/7 escalation; rehearse it. | H25: =IF($X25="","",INDEX(Assessment!$L:$L,$X25)) -> PSIRT Lead / Compliance Officer | I25: =IF($X25="","",INDEX(Assessment!$N:$N,$X25)) -> L | X25: =IF(9<=$B$6,SMALL($Y$2:$Y$593,9),IF(9<=$B$6+$B$7,SMALL($Z$2:$Z$593,9-$B$6),"")) -> 45 | Y25: =IF(Assessment!$G25="Critical",ROW(Assessment!$G25),"") | Z25: =IF(Assessment!$G25="High",ROW(Assessment!$G25),"")
A26: =IF($X26="","",10) -> 10 | B26: =IF($X26="","",INDEX(Assessment!$A:$A,$X26)) -> TR1-038 | C26: =IF($X26="","",INDEX(Assessment!$B:$B,$X26)) -> BSI TR-03183-1 v1.0.0 | D26: =IF($X26="","",INDEX(Assessment!$C:$C,$X26)) -> 3.6 Obligations of the manufacturer - Reporting obligations | E26: =IF($X26="","",INDEX(Assessment!$F:$F,$X26)) -> CRA Art. 14 reporting - vulnerabilities | F26: =IF($X26="","",INDEX(Assessment!$G:$G,$X26)) -> Critical | G26: =IF($X26="","",INDEX(Assessment!$J:$J,$X26)) -> Implement the reporting procedure: awareness criteria, 24h / 72h / 14-day (vulnerability) and 24h / 72h / one-month (incident) timelines, platform accounts, templates, approvals and 24/7 escalation; rehearse it. | H26: =IF($X26="","",INDEX(Assessment!$L:$L,$X26)) -> PSIRT Lead / Compliance Officer | I26: =IF($X26="","",INDEX(Assessment!$N:$N,$X26)) -> L | X26: =IF(10<=$B$6,SMALL($Y$2:$Y$593,10),IF(10<=$B$6+$B$7,SMALL($Z$2:$Z$593,10-$B$6),"")) -> 48 | Y26: =IF(Assessment!$G26="Critical",ROW(Assessment!$G26),"") | Z26: =IF(Assessment!$G26="High",ROW(Assessment!$G26),"")
A27: =IF($X27="","",11) -> 11 | B27: =IF($X27="","",INDEX(Assessment!$A:$A,$X27)) -> TR1-040 | C27: =IF($X27="","",INDEX(Assessment!$B:$B,$X27)) -> BSI TR-03183-1 v1.0.0 | D27: =IF($X27="","",INDEX(Assessment!$C:$C,$X27)) -> 3.6 Obligations of the manufacturer - Reporting obligations | E27: =IF($X27="","",INDEX(Assessment!$F:$F,$X27)) -> CRA Art. 14 reporting - incidents | F27: =IF($X27="","",INDEX(Assessment!$G:$G,$X27)) -> Critical | G27: =IF($X27="","",INDEX(Assessment!$J:$J,$X27)) -> Implement the reporting procedure: awareness criteria, 24h / 72h / 14-day (vulnerability) and 24h / 72h / one-month (incident) timelines, platform accounts, templates, approvals and 24/7 escalation; rehearse it. | H27: =IF($X27="","",INDEX(Assessment!$L:$L,$X27)) -> PSIRT Lead / Compliance Officer | I27: =IF($X27="","",INDEX(Assessment!$N:$N,$X27)) -> L | X27: =IF(11<=$B$6,SMALL($Y$2:$Y$593,11),IF(11<=$B$6+$B$7,SMALL($Z$2:$Z$593,11-$B$6),"")) -> 50 | Y27: =IF(Assessment!$G27="Critical",ROW(Assessment!$G27),"") | Z27: =IF(Assessment!$G27="High",ROW(Assessment!$G27),"")
A28: =IF($X28="","",12) -> 12 | B28: =IF($X28="","",INDEX(Assessment!$A:$A,$X28)) -> TR1-042 | C28: =IF($X28="","",INDEX(Assessment!$B:$B,$X28)) -> BSI TR-03183-1 v1.0.0 | D28: =IF($X28="","",INDEX(Assessment!$C:$C,$X28)) -> 3.6 Obligations of the manufacturer - Reporting obligations | E28: =IF($X28="","",INDEX(Assessment!$F:$F,$X28)) -> CRA Art. 14 reporting - incidents | F28: =IF($X28="","",INDEX(Assessment!$G:$G,$X28)) -> Critical | G28: =IF($X28="","",INDEX(Assessment!$J:$J,$X28)) -> Implement the reporting procedure: awareness criteria, 24h / 72h / 14-day (vulnerability) and 24h / 72h / one-month (incident) timelines, platform accounts, templates, approvals and 24/7 escalation; rehearse it. | H28: =IF($X28="","",INDEX(Assessment!$L:$L,$X28)) -> PSIRT Lead / Compliance Officer | I28: =IF($X28="","",INDEX(Assessment!$N:$N,$X28)) -> L | X28: =IF(12<=$B$6,SMALL($Y$2:$Y$593,12),IF(12<=$B$6+$B$7,SMALL($Z$2:$Z$593,12-$B$6),"")) -> 53 | Y28: =IF(Assessment!$G28="Critical",ROW(Assessment!$G28),"") | Z28: =IF(Assessment!$G28="High",ROW(Assessment!$G28),"")
A29: =IF($X29="","",13) -> 13 | B29: =IF($X29="","",INDEX(Assessment!$A:$A,$X29)) -> TR1-045 | C29: =IF($X29="","",INDEX(Assessment!$B:$B,$X29)) -> BSI TR-03183-1 v1.0.0 | D29: =IF($X29="","",INDEX(Assessment!$C:$C,$X29)) -> 3.6 Obligations of the manufacturer - Reporting obligations | E29: =IF($X29="","",INDEX(Assessment!$F:$F,$X29)) -> CRA Art. 14 reporting - incidents | F29: =IF($X29="","",INDEX(Assessment!$G:$G,$X29)) -> Critical | G29: =IF($X29="","",INDEX(Assessment!$J:$J,$X29)) -> Implement the reporting procedure: awareness criteria, 24h / 72h / 14-day (vulnerability) and 24h / 72h / one-month (incident) timelines, platform accounts, templates, approvals and 24/7 escalation; rehearse it. | H29: =IF($X29="","",INDEX(Assessment!$L:$L,$X29)) -> PSIRT Lead / Compliance Officer | I29: =IF($X29="","",INDEX(Assessment!$N:$N,$X29)) -> L | X29: =IF(13<=$B$6,SMALL($Y$2:$Y$593,13),IF(13<=$B$6+$B$7,SMALL($Z$2:$Z$593,13-$B$6),"")) -> 56 | Y29: =IF(Assessment!$G29="Critical",ROW(Assessment!$G29),"") | Z29: =IF(Assessment!$G29="High",ROW(Assessment!$G29),"")
A30: =IF($X30="","",14) -> 14 | B30: =IF($X30="","",INDEX(Assessment!$A:$A,$X30)) -> VH.1 | C30: =IF($X30="","",INDEX(Assessment!$B:$B,$X30)) -> BSI TR-03183-1 v1.0.0 | D30: =IF($X30="","",INDEX(Assessment!$C:$C,$X30)) -> Annex B Table 10 (CRA Annex I Part II (1)); text also in 3.9 | E30: =IF($X30="","",INDEX(Assessment!$F:$F,$X30)) -> Vulnerability handling - identification | F30: =IF($X30="","",INDEX(Assessment!$G:$G,$X30)) -> Critical | G30: =IF($X30="","",INDEX(Assessment!$J:$J,$X30)) -> Implement, document and operate: identify and document vulnerabilities and components contained in products. | H30: =IF($X30="","",INDEX(Assessment!$L:$L,$X30)) -> PSIRT Lead | I30: =IF($X30="","",INDEX(Assessment!$N:$N,$X30)) -> L | X30: =IF(14<=$B$6,SMALL($Y$2:$Y$593,14),IF(14<=$B$6+$B$7,SMALL($Z$2:$Z$593,14-$B$6),"")) -> 257 | Y30: =IF(Assessment!$G30="Critical",ROW(Assessment!$G30),"") | Z30: =IF(Assessment!$G30="High",ROW(Assessment!$G30),"")
A31: =IF($X31="","",15) -> 15 | B31: =IF($X31="","",INDEX(Assessment!$A:$A,$X31)) -> VH.2a-a | C31: =IF($X31="","",INDEX(Assessment!$B:$B,$X31)) -> BSI TR-03183-1 v1.0.0 | D31: =IF($X31="","",INDEX(Assessment!$C:$C,$X31)) -> Annex B Table 10 (CRA Annex I Part II (2)); text also in 3.9 | E31: =IF($X31="","",INDEX(Assessment!$F:$F,$X31)) -> Vulnerability handling - remediation | F31: =IF($X31="","",INDEX(Assessment!$G:$G,$X31)) -> Critical | G31: =IF($X31="","",INDEX(Assessment!$J:$J,$X31)) -> Implement, document and operate: address and remediate vulnerabilities without delay, incl. security updates. | H31: =IF($X31="","",INDEX(Assessment!$L:$L,$X31)) -> PSIRT Lead | I31: =IF($X31="","",INDEX(Assessment!$N:$N,$X31)) -> L | X31: =IF(15<=$B$6,SMALL($Y$2:$Y$593,15),IF(15<=$B$6+$B$7,SMALL($Z$2:$Z$593,15-$B$6),"")) -> 259 | Y31: =IF(Assessment!$G31="Critical",ROW(Assessment!$G31),"") | Z31: =IF(Assessment!$G31="High",ROW(Assessment!$G31),"") -> 31
A32: =IF($X32="","",16) -> 16 | B32: =IF($X32="","",INDEX(Assessment!$A:$A,$X32)) -> VH.4-a | C32: =IF($X32="","",INDEX(Assessment!$B:$B,$X32)) -> BSI TR-03183-1 v1.0.0 | D32: =IF($X32="","",INDEX(Assessment!$C:$C,$X32)) -> Annex B Table 10 (CRA Annex I Part II (4)); text also in 3.9 | E32: =IF($X32="","",INDEX(Assessment!$F:$F,$X32)) -> Vulnerability disclosure | F32: =IF($X32="","",INDEX(Assessment!$G:$G,$X32)) -> Critical | G32: =IF($X32="","",INDEX(Assessment!$J:$J,$X32)) -> Implement, document and operate: once a security update is available, publicly disclose information about fixed vulnerabilities. | H32: =IF($X32="","",INDEX(Assessment!$L:$L,$X32)) -> PSIRT Lead | I32: =IF($X32="","",INDEX(Assessment!$N:$N,$X32)) -> L | X32: =IF(16<=$B$6,SMALL($Y$2:$Y$593,16),IF(16<=$B$6+$B$7,SMALL($Z$2:$Z$593,16-$B$6),"")) -> 262 | Y32: =IF(Assessment!$G32="Critical",ROW(Assessment!$G32),"") | Z32: =IF(Assessment!$G32="High",ROW(Assessment!$G32),"") -> 32
A33: =IF($X33="","",17) -> 17 | B33: =IF($X33="","",INDEX(Assessment!$A:$A,$X33)) -> VH.5 | C33: =IF($X33="","",INDEX(Assessment!$B:$B,$X33)) -> BSI TR-03183-1 v1.0.0 | D33: =IF($X33="","",INDEX(Assessment!$C:$C,$X33)) -> Annex B Table 10 (CRA Annex I Part II (5)); text also in 3.9 | E33: =IF($X33="","",INDEX(Assessment!$F:$F,$X33)) -> CVD policy | F33: =IF($X33="","",INDEX(Assessment!$G:$G,$X33)) -> Critical | G33: =IF($X33="","",INDEX(Assessment!$J:$J,$X33)) -> Implement, document and operate: put in place and enforce a coordinated vulnerability disclosure policy. | H33: =IF($X33="","",INDEX(Assessment!$L:$L,$X33)) -> PSIRT Lead | I33: =IF($X33="","",INDEX(Assessment!$N:$N,$X33)) -> L | X33: =IF(17<=$B$6,SMALL($Y$2:$Y$593,17),IF(17<=$B$6+$B$7,SMALL($Z$2:$Z$593,17-$B$6),"")) -> 264 | Y33: =IF(Assessment!$G33="Critical",ROW(Assessment!$G33),"") -> 33 | Z33: =IF(Assessment!$G33="High",ROW(Assessment!$G33),"")
A34: =IF($X34="","",18) -> 18 | B34: =IF($X34="","",INDEX(Assessment!$A:$A,$X34)) -> VH.6a | C34: =IF($X34="","",INDEX(Assessment!$B:$B,$X34)) -> BSI TR-03183-1 v1.0.0 | D34: =IF($X34="","",INDEX(Assessment!$C:$C,$X34)) -> Annex B Table 10 (CRA Annex I Part II (6)); text also in 3.9 | E34: =IF($X34="","",INDEX(Assessment!$F:$F,$X34)) -> Vulnerability contact | F34: =IF($X34="","",INDEX(Assessment!$G:$G,$X34)) -> Critical | G34: =IF($X34="","",INDEX(Assessment!$J:$J,$X34)) -> Implement, document and operate: provide a contact address for reporting vulnerabilities. | H34: =IF($X34="","",INDEX(Assessment!$L:$L,$X34)) -> PSIRT Lead | I34: =IF($X34="","",INDEX(Assessment!$N:$N,$X34)) -> L | X34: =IF(18<=$B$6,SMALL($Y$2:$Y$593,18),IF(18<=$B$6+$B$7,SMALL($Z$2:$Z$593,18-$B$6),"")) -> 266 | Y34: =IF(Assessment!$G34="Critical",ROW(Assessment!$G34),"") -> 34 | Z34: =IF(Assessment!$G34="High",ROW(Assessment!$G34),"")
A35: =IF($X35="","",19) -> 19 | B35: =IF($X35="","",INDEX(Assessment!$A:$A,$X35)) -> VH.7 | C35: =IF($X35="","",INDEX(Assessment!$B:$B,$X35)) -> BSI TR-03183-1 v1.0.0 | D35: =IF($X35="","",INDEX(Assessment!$C:$C,$X35)) -> Annex B Table 10 (CRA Annex I Part II (7)); text also in 3.9 | E35: =IF($X35="","",INDEX(Assessment!$F:$F,$X35)) -> Secure update distribution | F35: =IF($X35="","",INDEX(Assessment!$G:$G,$X35)) -> Critical | G35: =IF($X35="","",INDEX(Assessment!$J:$J,$X35)) -> Operate update distribution and track installation status per site. | H35: =IF($X35="","",INDEX(Assessment!$L:$L,$X35)) -> Service Delivery Manager | I35: =IF($X35="","",INDEX(Assessment!$N:$N,$X35)) -> L | X35: =IF(19<=$B$6,SMALL($Y$2:$Y$593,19),IF(19<=$B$6+$B$7,SMALL($Z$2:$Z$593,19-$B$6),"")) -> 267 | Y35: =IF(Assessment!$G35="Critical",ROW(Assessment!$G35),"") | Z35: =IF(Assessment!$G35="High",ROW(Assessment!$G35),"") -> 35
A36: =IF($X36="","",20) -> 20 | B36: =IF($X36="","",INDEX(Assessment!$A:$A,$X36)) -> VH.8 | C36: =IF($X36="","",INDEX(Assessment!$B:$B,$X36)) -> BSI TR-03183-1 v1.0.0 | D36: =IF($X36="","",INDEX(Assessment!$C:$C,$X36)) -> Annex B Table 10 (CRA Annex I Part II (8)); text also in 3.9 | E36: =IF($X36="","",INDEX(Assessment!$F:$F,$X36)) -> Security updates - dissemination | F36: =IF($X36="","",INDEX(Assessment!$G:$G,$X36)) -> Critical | G36: =IF($X36="","",INDEX(Assessment!$J:$J,$X36)) -> Implement, document and operate: disseminate available security updates without delay. | H36: =IF($X36="","",INDEX(Assessment!$L:$L,$X36)) -> PSIRT Lead | I36: =IF($X36="","",INDEX(Assessment!$N:$N,$X36)) -> L | X36: =IF(20<=$B$6,SMALL($Y$2:$Y$593,20),IF(20<=$B$6+$B$7,SMALL($Z$2:$Z$593,20-$B$6),"")) -> 269 | Y36: =IF(Assessment!$G36="Critical",ROW(Assessment!$G36),"") | Z36: =IF(Assessment!$G36="High",ROW(Assessment!$G36),"") -> 36
A37: =IF($X37="","",21) -> 21 | B37: =IF($X37="","",INDEX(Assessment!$A:$A,$X37)) -> TR2-004 | C37: =IF($X37="","",INDEX(Assessment!$B:$B,$X37)) -> BSI TR-03183-2 v2.1.0 | D37: =IF($X37="","",INDEX(Assessment!$C:$C,$X37)) -> 1 Introduction | E37: =IF($X37="","",INDEX(Assessment!$F:$F,$X37)) -> Vulnerability handling - impact analysis | F37: =IF($X37="","",INDEX(Assessment!$G:$G,$X37)) -> Critical | G37: =IF($X37="","",INDEX(Assessment!$J:$J,$X37)) -> Triage every SBOM-based match, record the exploitability decision, and publish product status as CSAF/VEX linked to SBOM component identifiers. | H37: =IF($X37="","",INDEX(Assessment!$L:$L,$X37)) -> PSIRT Lead | I37: =IF($X37="","",INDEX(Assessment!$N:$N,$X37)) -> L | X37: =IF(21<=$B$6,SMALL($Y$2:$Y$593,21),IF(21<=$B$6+$B$7,SMALL($Z$2:$Z$593,21-$B$6),"")) -> 287 | Y37: =IF(Assessment!$G37="Critical",ROW(Assessment!$G37),"") | Z37: =IF(Assessment!$G37="High",ROW(Assessment!$G37),"")
A38: =IF($X38="","",22) -> 22 | B38: =IF($X38="","",INDEX(Assessment!$A:$A,$X38)) -> TR3-007 | C38: =IF($X38="","",INDEX(Assessment!$B:$B,$X38)) -> BSI TR-03183-3 v1.0.0 | D38: =IF($X38="","",INDEX(Assessment!$C:$C,$X38)) -> 3.1.7 Corresponding national CSIRT | E38: =IF($X38="","",INDEX(Assessment!$F:$F,$X38)) -> CVD - national CSIRT coordination | F38: =IF($X38="","",INDEX(Assessment!$G:$G,$X38)) -> Critical | G38: =IF($X38="","",INDEX(Assessment!$J:$J,$X38)) -> select the corresponding national CSIRT among those designated as CVD coordinator in the Member State - document it in the PSIRT notification procedure and keep a case log. | H38: =IF($X38="","",INDEX(Assessment!$L:$L,$X38)) -> PSIRT Lead / Compliance Officer | I38: =IF($X38="","",INDEX(Assessment!$N:$N,$X38)) -> S | X38: =IF(22<=$B$6,SMALL($Y$2:$Y$593,22),IF(22<=$B$6+$B$7,SMALL($Z$2:$Z$593,22-$B$6),"")) -> 420 | Y38: =IF(Assessment!$G38="Critical",ROW(Assessment!$G38),"") | Z38: =IF(Assessment!$G38="High",ROW(Assessment!$G38),"") -> 38
A39: =IF($X39="","",23) -> 23 | B39: =IF($X39="","",INDEX(Assessment!$A:$A,$X39)) -> TR3-4.3.1a | C39: =IF($X39="","",INDEX(Assessment!$B:$B,$X39)) -> BSI TR-03183-3 v1.0.0 | D39: =IF($X39="","",INDEX(Assessment!$C:$C,$X39)) -> 4.3.1 Roles of responsible cybersecurity contacts | E39: =IF($X39="","",INDEX(Assessment!$F:$F,$X39)) -> PSIRT / CSIRT organisation | F39: =IF($X39="","",INDEX(Assessment!$G:$G,$X39)) -> Critical | G39: =IF($X39="","",INDEX(Assessment!$J:$J,$X39)) -> Establish PSIRT (products, incl. RDPS) and CSIRT (corporate infrastructure) with charter, named members, deputies and management mandate. | H39: =IF($X39="","",INDEX(Assessment!$L:$L,$X39)) -> CISO / PSIRT Lead | I39: =IF($X39="","",INDEX(Assessment!$N:$N,$X39)) -> L | X39: =IF(23<=$B$6,SMALL($Y$2:$Y$593,23),IF(23<=$B$6+$B$7,SMALL($Z$2:$Z$593,23-$B$6),"")) -> 479 | Y39: =IF(Assessment!$G39="Critical",ROW(Assessment!$G39),"") | Z39: =IF(Assessment!$G39="High",ROW(Assessment!$G39),"")
A40: =IF($X40="","",24) -> 24 | B40: =IF($X40="","",INDEX(Assessment!$A:$A,$X40)) -> TR3-4.3.4a | C40: =IF($X40="","",INDEX(Assessment!$B:$B,$X40)) -> BSI TR-03183-3 v1.0.0 | D40: =IF($X40="","",INDEX(Assessment!$C:$C,$X40)) -> 4.3.4 Web page for incoming vulnerability reports | E40: =IF($X40="","",INDEX(Assessment!$F:$F,$X40)) -> Vulnerability reporting web page | F40: =IF($X40="","",INDEX(Assessment!$G:$G,$X40)) -> Critical | G40: =IF($X40="","",INDEX(Assessment!$J:$J,$X40)) -> Publish the central vulnerability reporting page (contacts, keys, web form, CVD policy link) and link it from the home page. | H40: =IF($X40="","",INDEX(Assessment!$L:$L,$X40)) -> PSIRT Lead with Web/IT team | I40: =IF($X40="","",INDEX(Assessment!$N:$N,$X40)) -> M | X40: =IF(24<=$B$6,SMALL($Y$2:$Y$593,24),IF(24<=$B$6+$B$7,SMALL($Z$2:$Z$593,24-$B$6),"")) -> 514 | Y40: =IF(Assessment!$G40="Critical",ROW(Assessment!$G40),"") -> 40 | Z40: =IF(Assessment!$G40="High",ROW(Assessment!$G40),"")
A41: =IF($X41="","",25) -> 25 | B41: =IF($X41="","",INDEX(Assessment!$A:$A,$X41)) -> TR3-022 | C41: =IF($X41="","",INDEX(Assessment!$B:$B,$X41)) -> BSI TR-03183-3 v1.0.0 | D41: =IF($X41="","",INDEX(Assessment!$C:$C,$X41)) -> 4.4 CVD policy | E41: =IF($X41="","",INDEX(Assessment!$F:$F,$X41)) -> CVD policy - content | F41: =IF($X41="","",INDEX(Assessment!$G:$G,$X41)) -> Critical | G41: =IF($X41="","",INDEX(Assessment!$J:$J,$X41)) -> Draft, approve (Legal, management) and publish the CVD policy covering every 4.4.x item; assign an owner and review cycle. | H41: =IF($X41="","",INDEX(Assessment!$L:$L,$X41)) -> PSIRT Lead (Legal reviews policy wording) | I41: =IF($X41="","",INDEX(Assessment!$N:$N,$X41)) -> L | X41: =IF(25<=$B$6,SMALL($Y$2:$Y$593,25),IF(25<=$B$6+$B$7,SMALL($Z$2:$Z$593,25-$B$6),"")) -> 515 | Y41: =IF(Assessment!$G41="Critical",ROW(Assessment!$G41),"") -> 41 | Z41: =IF(Assessment!$G41="High",ROW(Assessment!$G41),"")
A42: =IF($X42="","",26) -> 26 | B42: =IF($X42="","",INDEX(Assessment!$A:$A,$X42)) -> TR3-4.4.2a | C42: =IF($X42="","",INDEX(Assessment!$B:$B,$X42)) -> BSI TR-03183-3 v1.0.0 | D42: =IF($X42="","",INDEX(Assessment!$C:$C,$X42)) -> 4.4.2 Corresponding national CSIRT | E42: =IF($X42="","",INDEX(Assessment!$F:$F,$X42)) -> Incident & vulnerability reporting (CSIRT) | F42: =IF($X42="","",INDEX(Assessment!$G:$G,$X42)) -> Critical | G42: =IF($X42="","",INDEX(Assessment!$J:$J,$X42)) -> Implement the actively-exploited-vulnerability notification procedure (awareness criteria, 24h/72h/14-day timeline, single reporting platform account, CSIRT contact, approvals) and rehearse it. | H42: =IF($X42="","",INDEX(Assessment!$L:$L,$X42)) -> PSIRT Lead / Compliance Officer | I42: =IF($X42="","",INDEX(Assessment!$N:$N,$X42)) -> L | X42: =IF(26<=$B$6,SMALL($Y$2:$Y$593,26),IF(26<=$B$6+$B$7,SMALL($Z$2:$Z$593,26-$B$6),"")) -> 520 | Y42: =IF(Assessment!$G42="Critical",ROW(Assessment!$G42),"") -> 42 | Z42: =IF(Assessment!$G42="High",ROW(Assessment!$G42),"")
A43: =IF($X43="","",27) -> 27 | B43: =IF($X43="","",INDEX(Assessment!$A:$A,$X43)) -> TR1-008 | C43: =IF($X43="","",INDEX(Assessment!$B:$B,$X43)) -> BSI TR-03183-1 v1.0.0 | D43: =IF($X43="","",INDEX(Assessment!$C:$C,$X43)) -> 3.4 Timeline | E43: =IF($X43="","",INDEX(Assessment!$F:$F,$X43)) -> CRA timeline - legacy products | F43: =IF($X43="","",INDEX(Assessment!$G:$G,$X43)) -> High | G43: =IF($X43="","",INDEX(Assessment!$J:$J,$X43)) -> Embed 'Art. 14 obligations apply to all in-scope products placed on the market before 11 Dec 2027' in the PSIRT / vulnerability-handling procedure and service-management tooling. | H43: =IF($X43="","",INDEX(Assessment!$L:$L,$X43)) -> PSIRT Lead / Service Delivery Manager | I43: =IF($X43="","",INDEX(Assessment!$N:$N,$X43)) -> M | X43: =IF(27<=$B$6,SMALL($Y$2:$Y$593,27),IF(27<=$B$6+$B$7,SMALL($Z$2:$Z$593,27-$B$6),"")) -> 9 | Y43: =IF(Assessment!$G43="Critical",ROW(Assessment!$G43),"") -> 43 | Z43: =IF(Assessment!$G43="High",ROW(Assessment!$G43),"")
A44: =IF($X44="","",28) -> 28 | B44: =IF($X44="","",INDEX(Assessment!$A:$A,$X44)) -> TR1-009 | C44: =IF($X44="","",INDEX(Assessment!$B:$B,$X44)) -> BSI TR-03183-1 v1.0.0 | D44: =IF($X44="","",INDEX(Assessment!$C:$C,$X44)) -> 3.4 Timeline | E44: =IF($X44="","",INDEX(Assessment!$F:$F,$X44)) -> CRA timeline - substantial modification | F44: =IF($X44="","",INDEX(Assessment!$G:$G,$X44)) -> High | G44: =IF($X44="","",INDEX(Assessment!$J:$J,$X44)) -> Embed 'products placed on the market before 11 Dec 2027 fall under the CRA only after a substantial modification after that date' in the PSIRT / vulnerability-handling procedure and service-management tooling. | H44: =IF($X44="","",INDEX(Assessment!$L:$L,$X44)) -> PSIRT Lead / Service Delivery Manager | I44: =IF($X44="","",INDEX(Assessment!$N:$N,$X44)) -> M | X44: =IF(28<=$B$6,SMALL($Y$2:$Y$593,28),IF(28<=$B$6+$B$7,SMALL($Z$2:$Z$593,28-$B$6),"")) -> 10 | Y44: =IF(Assessment!$G44="Critical",ROW(Assessment!$G44),"") | Z44: =IF(Assessment!$G44="High",ROW(Assessment!$G44),"") -> 44
A45: =IF($X45="","",29) -> 29 | B45: =IF($X45="","",INDEX(Assessment!$A:$A,$X45)) -> TR1-011 | C45: =IF($X45="","",INDEX(Assessment!$B:$B,$X45)) -> BSI TR-03183-1 v1.0.0 | D45: =IF($X45="","",INDEX(Assessment!$C:$C,$X45)) -> 3.4 Timeline | E45: =IF($X45="","",INDEX(Assessment!$F:$F,$X45)) -> CRA timeline - substantial modification | F45: =IF($X45="","",INDEX(Assessment!$G:$G,$X45)) -> High | G45: =IF($X45="","",INDEX(Assessment!$J:$J,$X45)) -> Add a substantial-modification check (type/purpose change vs. initial risk assessment) to change management for all installed solutions. | H45: =IF($X45="","",INDEX(Assessment!$L:$L,$X45)) -> PSIRT Lead / Service Delivery Manager | I45: =IF($X45="","",INDEX(Assessment!$N:$N,$X45)) -> M | X45: =IF(29<=$B$6,SMALL($Y$2:$Y$593,29),IF(29<=$B$6+$B$7,SMALL($Z$2:$Z$593,29-$B$6),"")) -> 12 | Y45: =IF(Assessment!$G45="Critical",ROW(Assessment!$G45),"") -> 45 | Z45: =IF(Assessment!$G45="High",ROW(Assessment!$G45),"")
A46: =IF($X46="","",30) -> 30 | B46: =IF($X46="","",INDEX(Assessment!$A:$A,$X46)) -> TR1-018 | C46: =IF($X46="","",INDEX(Assessment!$B:$B,$X46)) -> BSI TR-03183-1 v1.0.0 | D46: =IF($X46="","",INDEX(Assessment!$C:$C,$X46)) -> 3.5 Concepts - Lifecycle Responsibility | E46: =IF($X46="","",INDEX(Assessment!$F:$F,$X46)) -> Support period | F46: =IF($X46="","",INDEX(Assessment!$G:$G,$X46)) -> High | G46: =IF($X46="","",INDEX(Assessment!$J:$J,$X46)) -> Plan PSIRT and engineering capacity per supported release line until its support end date. | H46: =IF($X46="","",INDEX(Assessment!$L:$L,$X46)) -> Service Delivery Manager / PSIRT Lead | I46: =IF($X46="","",INDEX(Assessment!$N:$N,$X46)) -> M | X46: =IF(30<=$B$6,SMALL($Y$2:$Y$593,30),IF(30<=$B$6+$B$7,SMALL($Z$2:$Z$593,30-$B$6),"")) -> 19 | Y46: =IF(Assessment!$G46="Critical",ROW(Assessment!$G46),"") | Z46: =IF(Assessment!$G46="High",ROW(Assessment!$G46),"") -> 46
A47: =IF($X47="","",31) -> 31 | B47: =IF($X47="","",INDEX(Assessment!$A:$A,$X47)) -> TR1-026 | C47: =IF($X47="","",INDEX(Assessment!$B:$B,$X47)) -> BSI TR-03183-1 v1.0.0 | D47: =IF($X47="","",INDEX(Assessment!$C:$C,$X47)) -> 3.6 Obligations of the manufacturer - PwDE Monitoring and Post-Market Obligations | E47: =IF($X47="","",INDEX(Assessment!$F:$F,$X47)) -> Post-market review | F47: =IF($X47="","",INDEX(Assessment!$G:$G,$X47)) -> High | G47: =IF($X47="","",INDEX(Assessment!$J:$J,$X47)) -> Operate SBOM-based continuous vulnerability monitoring, periodic security reviews and remediation for all supported releases. | H47: =IF($X47="","",INDEX(Assessment!$L:$L,$X47)) -> PSIRT Lead / Product Security Officer | I47: =IF($X47="","",INDEX(Assessment!$N:$N,$X47)) -> M | X47: =IF(31<=$B$6,SMALL($Y$2:$Y$593,31),IF(31<=$B$6+$B$7,SMALL($Z$2:$Z$593,31-$B$6),"")) -> 31 | Y47: =IF(Assessment!$G47="Critical",ROW(Assessment!$G47),"") | Z47: =IF(Assessment!$G47="High",ROW(Assessment!$G47),"")
A48: =IF($X48="","",32) -> 32 | B48: =IF($X48="","",INDEX(Assessment!$A:$A,$X48)) -> TR1-027 | C48: =IF($X48="","",INDEX(Assessment!$B:$B,$X48)) -> BSI TR-03183-1 v1.0.0 | D48: =IF($X48="","",INDEX(Assessment!$C:$C,$X48)) -> 3.6 Obligations of the manufacturer - PwDE Monitoring and Post-Market Obligations | E48: =IF($X48="","",INDEX(Assessment!$F:$F,$X48)) -> Post-market review | F48: =IF($X48="","",INDEX(Assessment!$G:$G,$X48)) -> High | G48: =IF($X48="","",INDEX(Assessment!$J:$J,$X48)) -> Operate SBOM-based continuous vulnerability monitoring, periodic security reviews and remediation for all supported releases. | H48: =IF($X48="","",INDEX(Assessment!$L:$L,$X48)) -> PSIRT Lead / Product Security Officer | I48: =IF($X48="","",INDEX(Assessment!$N:$N,$X48)) -> M | X48: =IF(32<=$B$6,SMALL($Y$2:$Y$593,32),IF(32<=$B$6+$B$7,SMALL($Z$2:$Z$593,32-$B$6),"")) -> 32 | Y48: =IF(Assessment!$G48="Critical",ROW(Assessment!$G48),"") -> 48 | Z48: =IF(Assessment!$G48="High",ROW(Assessment!$G48),"")
A49: =IF($X49="","",33) -> 33 | B49: =IF($X49="","",INDEX(Assessment!$A:$A,$X49)) -> TR1-028-c | C49: =IF($X49="","",INDEX(Assessment!$B:$B,$X49)) -> BSI TR-03183-1 v1.0.0 | D49: =IF($X49="","",INDEX(Assessment!$C:$C,$X49)) -> 3.6 Obligations of the manufacturer - PwDE Monitoring and Post-Market Obligations | E49: =IF($X49="","",INDEX(Assessment!$F:$F,$X49)) -> Security updates - free of charge | F49: =IF($X49="","",INDEX(Assessment!$G:$G,$X49)) -> High | G49: =IF($X49="","",INDEX(Assessment!$J:$J,$X49)) -> Operate SBOM-based continuous vulnerability monitoring, periodic security reviews and remediation for all supported releases. | H49: =IF($X49="","",INDEX(Assessment!$L:$L,$X49)) -> PSIRT Lead / Product Security Officer | I49: =IF($X49="","",INDEX(Assessment!$N:$N,$X49)) -> M | X49: =IF(33<=$B$6,SMALL($Y$2:$Y$593,33),IF(33<=$B$6+$B$7,SMALL($Z$2:$Z$593,33-$B$6),"")) -> 35 | Y49: =IF(Assessment!$G49="Critical",ROW(Assessment!$G49),"") | Z49: =IF(Assessment!$G49="High",ROW(Assessment!$G49),"")
A50: =IF($X50="","",34) -> 34 | B50: =IF($X50="","",INDEX(Assessment!$A:$A,$X50)) -> TR1-029 | C50: =IF($X50="","",INDEX(Assessment!$B:$B,$X50)) -> BSI TR-03183-1 v1.0.0 | D50: =IF($X50="","",INDEX(Assessment!$C:$C,$X50)) -> 3.6 Obligations of the manufacturer - PwDE Monitoring and Post-Market Obligations | E50: =IF($X50="","",INDEX(Assessment!$F:$F,$X50)) -> Support period | F50: =IF($X50="","",INDEX(Assessment!$G:$G,$X50)) -> High | G50: =IF($X50="","",INDEX(Assessment!$J:$J,$X50)) -> Plan PSIRT and engineering capacity per supported release line until its support end date. | H50: =IF($X50="","",INDEX(Assessment!$L:$L,$X50)) -> Service Delivery Manager / PSIRT Lead | I50: =IF($X50="","",INDEX(Assessment!$N:$N,$X50)) -> M | X50: =IF(34<=$B$6,SMALL($Y$2:$Y$593,34),IF(34<=$B$6+$B$7,SMALL($Z$2:$Z$593,34-$B$6),"")) -> 36 | Y50: =IF(Assessment!$G50="Critical",ROW(Assessment!$G50),"") -> 50 | Z50: =IF(Assessment!$G50="High",ROW(Assessment!$G50),"")
A51: =IF($X51="","",35) -> 35 | B51: =IF($X51="","",INDEX(Assessment!$A:$A,$X51)) -> TR1-031-a | C51: =IF($X51="","",INDEX(Assessment!$B:$B,$X51)) -> BSI TR-03183-1 v1.0.0 | D51: =IF($X51="","",INDEX(Assessment!$C:$C,$X51)) -> 3.6 Obligations of the manufacturer - PwDE Monitoring and Post-Market Obligations | E51: =IF($X51="","",INDEX(Assessment!$F:$F,$X51)) -> Availability of security updates | F51: =IF($X51="","",INDEX(Assessment!$G:$G,$X51)) -> High | G51: =IF($X51="","",INDEX(Assessment!$J:$J,$X51)) -> Plan PSIRT and engineering capacity per supported release line until its support end date. | H51: =IF($X51="","",INDEX(Assessment!$L:$L,$X51)) -> Service Delivery Manager / PSIRT Lead | I51: =IF($X51="","",INDEX(Assessment!$N:$N,$X51)) -> M | X51: =IF(35<=$B$6,SMALL($Y$2:$Y$593,35),IF(35<=$B$6+$B$7,SMALL($Z$2:$Z$593,35-$B$6),"")) -> 38 | Y51: =IF(Assessment!$G51="Critical",ROW(Assessment!$G51),"") | Z51: =IF(Assessment!$G51="High",ROW(Assessment!$G51),"") -> 51
A52: =IF($X52="","",36) -> 36 | B52: =IF($X52="","",INDEX(Assessment!$A:$A,$X52)) -> TR1-034-b | C52: =IF($X52="","",INDEX(Assessment!$B:$B,$X52)) -> BSI TR-03183-1 v1.0.0 | D52: =IF($X52="","",INDEX(Assessment!$C:$C,$X52)) -> 3.6 Obligations of the manufacturer - Reporting obligations | E52: =IF($X52="","",INDEX(Assessment!$F:$F,$X52)) -> CRA Art. 14 reporting - vulnerabilities | F52: =IF($X52="","",INDEX(Assessment!$G:$G,$X52)) -> High | G52: =IF($X52="","",INDEX(Assessment!$J:$J,$X52)) -> Implement the reporting procedure: awareness criteria, 24h / 72h / 14-day (vulnerability) and 24h / 72h / one-month (incident) timelines, platform accounts, templates, approvals and 24/7 escalation; rehearse it. | H52: =IF($X52="","",INDEX(Assessment!$L:$L,$X52)) -> PSIRT Lead / Compliance Officer | I52: =IF($X52="","",INDEX(Assessment!$N:$N,$X52)) -> M | X52: =IF(36<=$B$6,SMALL($Y$2:$Y$593,36),IF(36<=$B$6+$B$7,SMALL($Z$2:$Z$593,36-$B$6),"")) -> 44 | Y52: =IF(Assessment!$G52="Critical",ROW(Assessment!$G52),"") | Z52: =IF(Assessment!$G52="High",ROW(Assessment!$G52),"") -> 52
A53: =IF($X53="","",37) -> 37 | B53: =IF($X53="","",INDEX(Assessment!$A:$A,$X53)) -> TR1-036 | C53: =IF($X53="","",INDEX(Assessment!$B:$B,$X53)) -> BSI TR-03183-1 v1.0.0 | D53: =IF($X53="","",INDEX(Assessment!$C:$C,$X53)) -> 3.6 Obligations of the manufacturer - Reporting obligations | E53: =IF($X53="","",INDEX(Assessment!$F:$F,$X53)) -> CRA Art. 14 reporting - vulnerabilities | F53: =IF($X53="","",INDEX(Assessment!$G:$G,$X53)) -> High | G53: =IF($X53="","",INDEX(Assessment!$J:$J,$X53)) -> Implement the reporting procedure: awareness criteria, 24h / 72h / 14-day (vulnerability) and 24h / 72h / one-month (incident) timelines, platform accounts, templates, approvals and 24/7 escalation; rehearse it. | H53: =IF($X53="","",INDEX(Assessment!$L:$L,$X53)) -> PSIRT Lead / Compliance Officer | I53: =IF($X53="","",INDEX(Assessment!$N:$N,$X53)) -> M | X53: =IF(37<=$B$6,SMALL($Y$2:$Y$593,37),IF(37<=$B$6+$B$7,SMALL($Z$2:$Z$593,37-$B$6),"")) -> 46 | Y53: =IF(Assessment!$G53="Critical",ROW(Assessment!$G53),"") -> 53 | Z53: =IF(Assessment!$G53="High",ROW(Assessment!$G53),"")
A54: =IF($X54="","",38) -> 38 | B54: =IF($X54="","",INDEX(Assessment!$A:$A,$X54)) -> TR1-041-a | C54: =IF($X54="","",INDEX(Assessment!$B:$B,$X54)) -> BSI TR-03183-1 v1.0.0 | D54: =IF($X54="","",INDEX(Assessment!$C:$C,$X54)) -> 3.6 Obligations of the manufacturer - Reporting obligations | E54: =IF($X54="","",INDEX(Assessment!$F:$F,$X54)) -> CRA Art. 14 reporting - incidents | F54: =IF($X54="","",INDEX(Assessment!$G:$G,$X54)) -> High | G54: =IF($X54="","",INDEX(Assessment!$J:$J,$X54)) -> Implement the reporting procedure: awareness criteria, 24h / 72h / 14-day (vulnerability) and 24h / 72h / one-month (incident) timelines, platform accounts, templates, approvals and 24/7 escalation; rehearse it. | H54: =IF($X54="","",INDEX(Assessment!$L:$L,$X54)) -> PSIRT Lead / Compliance Officer | I54: =IF($X54="","",INDEX(Assessment!$N:$N,$X54)) -> M | X54: =IF(38<=$B$6,SMALL($Y$2:$Y$593,38),IF(38<=$B$6+$B$7,SMALL($Z$2:$Z$593,38-$B$6),"")) -> 51 | Y54: =IF(Assessment!$G54="Critical",ROW(Assessment!$G54),"") | Z54: =IF(Assessment!$G54="High",ROW(Assessment!$G54),"") -> 54
A55: =IF($X55="","",39) -> 39 | B55: =IF($X55="","",INDEX(Assessment!$A:$A,$X55)) -> TR1-041-b | C55: =IF($X55="","",INDEX(Assessment!$B:$B,$X55)) -> BSI TR-03183-1 v1.0.0 | D55: =IF($X55="","",INDEX(Assessment!$C:$C,$X55)) -> 3.6 Obligations of the manufacturer - Reporting obligations | E55: =IF($X55="","",INDEX(Assessment!$F:$F,$X55)) -> CRA Art. 14 reporting - incidents | F55: =IF($X55="","",INDEX(Assessment!$G:$G,$X55)) -> High | G55: =IF($X55="","",INDEX(Assessment!$J:$J,$X55)) -> Implement the reporting procedure: awareness criteria, 24h / 72h / 14-day (vulnerability) and 24h / 72h / one-month (incident) timelines, platform accounts, templates, approvals and 24/7 escalation; rehearse it. | H55: =IF($X55="","",INDEX(Assessment!$L:$L,$X55)) -> PSIRT Lead / Compliance Officer | I55: =IF($X55="","",INDEX(Assessment!$N:$N,$X55)) -> M | X55: =IF(39<=$B$6,SMALL($Y$2:$Y$593,39),IF(39<=$B$6+$B$7,SMALL($Z$2:$Z$593,39-$B$6),"")) -> 52 | Y55: =IF(Assessment!$G55="Critical",ROW(Assessment!$G55),"") | Z55: =IF(Assessment!$G55="High",ROW(Assessment!$G55),"")
A56: =IF($X56="","",40) -> 40 | B56: =IF($X56="","",INDEX(Assessment!$A:$A,$X56)) -> TR1-043 | C56: =IF($X56="","",INDEX(Assessment!$B:$B,$X56)) -> BSI TR-03183-1 v1.0.0 | D56: =IF($X56="","",INDEX(Assessment!$C:$C,$X56)) -> 3.6 Obligations of the manufacturer - Reporting obligations | E56: =IF($X56="","",INDEX(Assessment!$F:$F,$X56)) -> CRA Art. 14 reporting - incidents | F56: =IF($X56="","",INDEX(Assessment!$G:$G,$X56)) -> High | G56: =IF($X56="","",INDEX(Assessment!$J:$J,$X56)) -> Implement the reporting procedure: awareness criteria, 24h / 72h / 14-day (vulnerability) and 24h / 72h / one-month (incident) timelines, platform accounts, templates, approvals and 24/7 escalation; rehearse it. | H56: =IF($X56="","",INDEX(Assessment!$L:$L,$X56)) -> PSIRT Lead / Compliance Officer | I56: =IF($X56="","",INDEX(Assessment!$N:$N,$X56)) -> M | X56: =IF(40<=$B$6,SMALL($Y$2:$Y$593,40),IF(40<=$B$6+$B$7,SMALL($Z$2:$Z$593,40-$B$6),"")) -> 54 | Y56: =IF(Assessment!$G56="Critical",ROW(Assessment!$G56),"") -> 56 | Z56: =IF(Assessment!$G56="High",ROW(Assessment!$G56),"")
A57: =IF($X57="","",41) -> 41 | B57: =IF($X57="","",INDEX(Assessment!$A:$A,$X57)) -> TR1-046 | C57: =IF($X57="","",INDEX(Assessment!$B:$B,$X57)) -> BSI TR-03183-1 v1.0.0 | D57: =IF($X57="","",INDEX(Assessment!$C:$C,$X57)) -> 3.6 Obligations of the manufacturer - Reporting obligations | E57: =IF($X57="","",INDEX(Assessment!$F:$F,$X57)) -> CRA Art. 14 reporting - awareness | F57: =IF($X57="","",INDEX(Assessment!$G:$G,$X57)) -> High | G57: =IF($X57="","",INDEX(Assessment!$J:$J,$X57)) -> Implement the reporting procedure: awareness criteria, 24h / 72h / 14-day (vulnerability) and 24h / 72h / one-month (incident) timelines, platform accounts, templates, approvals and 24/7 escalation; rehearse it. | H57: =IF($X57="","",INDEX(Assessment!$L:$L,$X57)) -> PSIRT Lead / Compliance Officer | I57: =IF($X57="","",INDEX(Assessment!$N:$N,$X57)) -> M | X57: =IF(41<=$B$6,SMALL($Y$2:$Y$593,41),IF(41<=$B$6+$B$7,SMALL($Z$2:$Z$593,41-$B$6),"")) -> 57 | Y57: =IF(Assessment!$G57="Critical",ROW(Assessment!$G57),"") | Z57: =IF(Assessment!$G57="High",ROW(Assessment!$G57),"") -> 57
A58: =IF($X58="","",42) -> 42 | B58: =IF($X58="","",INDEX(Assessment!$A:$A,$X58)) -> TR1-051 | C58: =IF($X58="","",INDEX(Assessment!$B:$B,$X58)) -> BSI TR-03183-1 v1.0.0 | D58: =IF($X58="","",INDEX(Assessment!$C:$C,$X58)) -> 3.6 Obligations of the manufacturer - Additional obligations for third-party components | E58: =IF($X58="","",INDEX(Assessment!$F:$F,$X58)) -> Upstream vulnerability reporting | F58: =IF($X58="","",INDEX(Assessment!$G:$G,$X58)) -> High | G58: =IF($X58="","",INDEX(Assessment!$J:$J,$X58)) -> Monitor supplier advisories and end-of-life dates; report found vulnerabilities upstream and track responses. | H58: =IF($X58="","",INDEX(Assessment!$L:$L,$X58)) -> PSIRT Lead | I58: =IF($X58="","",INDEX(Assessment!$N:$N,$X58)) -> M | X58: =IF(42<=$B$6,SMALL($Y$2:$Y$593,42),IF(42<=$B$6+$B$7,SMALL($Z$2:$Z$593,42-$B$6),"")) -> 62 | Y58: =IF(Assessment!$G58="Critical",ROW(Assessment!$G58),"") | Z58: =IF(Assessment!$G58="High",ROW(Assessment!$G58),"")
A59: =IF($X59="","",43) -> 43 | B59: =IF($X59="","",INDEX(Assessment!$A:$A,$X59)) -> TR1-066 | C59: =IF($X59="","",INDEX(Assessment!$B:$B,$X59)) -> BSI TR-03183-1 v1.0.0 | D59: =IF($X59="","",INDEX(Assessment!$C:$C,$X59)) -> 3.9 The Essential Requirements | E59: =IF($X59="","",INDEX(Assessment!$F:$F,$X59)) -> Lifecycle responsibility | F59: =IF($X59="","",INDEX(Assessment!$G:$G,$X59)) -> High | G59: =IF($X59="","",INDEX(Assessment!$J:$J,$X59)) -> Plan PSIRT and engineering capacity per supported release line until its support end date. | H59: =IF($X59="","",INDEX(Assessment!$L:$L,$X59)) -> Service Delivery Manager / PSIRT Lead | I59: =IF($X59="","",INDEX(Assessment!$N:$N,$X59)) -> M | X59: =IF(43<=$B$6,SMALL($Y$2:$Y$593,43),IF(43<=$B$6+$B$7,SMALL($Z$2:$Z$593,43-$B$6),"")) -> 78 | Y59: =IF(Assessment!$G59="Critical",ROW(Assessment!$G59),"") | Z59: =IF(Assessment!$G59="High",ROW(Assessment!$G59),"")
A60: =IF($X60="","",44) -> 44 | B60: =IF($X60="","",INDEX(Assessment!$A:$A,$X60)) -> TR1-067 | C60: =IF($X60="","",INDEX(Assessment!$B:$B,$X60)) -> BSI TR-03183-1 v1.0.0 | D60: =IF($X60="","",INDEX(Assessment!$C:$C,$X60)) -> 3.9 The Essential Requirements | E60: =IF($X60="","",INDEX(Assessment!$F:$F,$X60)) -> Vulnerability handling (Annex I Part II) | F60: =IF($X60="","",INDEX(Assessment!$G:$G,$X60)) -> High | G60: =IF($X60="","",INDEX(Assessment!$J:$J,$X60)) -> Implement, document and operate: a vulnerability handling process must be in place before placing on the market to avoid known exploitable vulnerabilities. | H60: =IF($X60="","",INDEX(Assessment!$L:$L,$X60)) -> PSIRT Lead | I60: =IF($X60="","",INDEX(Assessment!$N:$N,$X60)) -> M | X60: =IF(44<=$B$6,SMALL($Y$2:$Y$593,44),IF(44<=$B$6+$B$7,SMALL($Z$2:$Z$593,44-$B$6),"")) -> 79 | Y60: =IF(Assessment!$G60="Critical",ROW(Assessment!$G60),"") | Z60: =IF(Assessment!$G60="High",ROW(Assessment!$G60),"")
A61: =IF($X61="","",45) -> 45 | B61: =IF($X61="","",INDEX(Assessment!$A:$A,$X61)) -> TR1-068 | C61: =IF($X61="","",INDEX(Assessment!$B:$B,$X61)) -> BSI TR-03183-1 v1.0.0 | D61: =IF($X61="","",INDEX(Assessment!$C:$C,$X61)) -> 3.9 The Essential Requirements | E61: =IF($X61="","",INDEX(Assessment!$F:$F,$X61)) -> Vulnerability handling (Annex I Part II) | F61: =IF($X61="","",INDEX(Assessment!$G:$G,$X61)) -> High | G61: =IF($X61="","",INDEX(Assessment!$J:$J,$X61)) -> Implement, document and operate: Part II requires identifying, addressing and remediating vulnerabilities. | H61: =IF($X61="","",INDEX(Assessment!$L:$L,$X61)) -> PSIRT Lead | I61: =IF($X61="","",INDEX(Assessment!$N:$N,$X61)) -> M | X61: =IF(45<=$B$6,SMALL($Y$2:$Y$593,45),IF(45<=$B$6+$B$7,SMALL($Z$2:$Z$593,45-$B$6),"")) -> 80 | Y61: =IF(Assessment!$G61="Critical",ROW(Assessment!$G61),"") | Z61: =IF(Assessment!$G61="High",ROW(Assessment!$G61),"")
A62: =IF($X62="","",46) -> 46 | B62: =IF($X62="","",INDEX(Assessment!$A:$A,$X62)) -> TR1-072 | C62: =IF($X62="","",INDEX(Assessment!$B:$B,$X62)) -> BSI TR-03183-1 v1.0.0 | D62: =IF($X62="","",INDEX(Assessment!$C:$C,$X62)) -> 3.10 Consequences of Non-Compliance | E62: =IF($X62="","",INDEX(Assessment!$F:$F,$X62)) -> Market surveillance cooperation | F62: =IF($X62="","",INDEX(Assessment!$G:$G,$X62)) -> High | G62: =IF($X62="","",INDEX(Assessment!$J:$J,$X62)) -> Define an authority-request and corrective-action procedure (single point of contact, escalation, recall decision). | H62: =IF($X62="","",INDEX(Assessment!$L:$L,$X62)) -> Compliance Officer / PSIRT Lead | I62: =IF($X62="","",INDEX(Assessment!$N:$N,$X62)) -> M | X62: =IF(46<=$B$6,SMALL($Y$2:$Y$593,46),IF(46<=$B$6+$B$7,SMALL($Z$2:$Z$593,46-$B$6),"")) -> 84 | Y62: =IF(Assessment!$G62="Critical",ROW(Assessment!$G62),"") | Z62: =IF(Assessment!$G62="High",ROW(Assessment!$G62),"") -> 62
A63: =IF($X63="","",47) -> 47 | B63: =IF($X63="","",INDEX(Assessment!$A:$A,$X63)) -> TR1-117-b | C63: =IF($X63="","",INDEX(Assessment!$B:$B,$X63)) -> BSI TR-03183-1 v1.0.0 | D63: =IF($X63="","",INDEX(Assessment!$C:$C,$X63)) -> 5.7.1 Intended purpose and reasonable foreseeable use | E63: =IF($X63="","",INDEX(Assessment!$F:$F,$X63)) -> Vulnerability handling (Annex I Part II) | F63: =IF($X63="","",INDEX(Assessment!$G:$G,$X63)) -> High | G63: =IF($X63="","",INDEX(Assessment!$J:$J,$X63)) -> Implement, document and operate: the manufacturer's processes must comply with the essential requirements. | H63: =IF($X63="","",INDEX(Assessment!$L:$L,$X63)) -> PSIRT Lead | I63: =IF($X63="","",INDEX(Assessment!$N:$N,$X63)) -> M | X63: =IF(47<=$B$6,SMALL($Y$2:$Y$593,47),IF(47<=$B$6+$B$7,SMALL($Z$2:$Z$593,47-$B$6),"")) -> 133 | Y63: =IF(Assessment!$G63="Critical",ROW(Assessment!$G63),"") | Z63: =IF(Assessment!$G63="High",ROW(Assessment!$G63),"")
A64: =IF($X64="","",48) -> 48 | B64: =IF($X64="","",INDEX(Assessment!$A:$A,$X64)) -> TR1-156 | C64: =IF($X64="","",INDEX(Assessment!$B:$B,$X64)) -> BSI TR-03183-1 v1.0.0 | D64: =IF($X64="","",INDEX(Assessment!$C:$C,$X64)) -> 5.13.1 Update Risk Assessment - General | E64: =IF($X64="","",INDEX(Assessment!$F:$F,$X64)) -> Risk assessment - update | F64: =IF($X64="","",INDEX(Assessment!$G:$G,$X64)) -> High | G64: =IF($X64="","",INDEX(Assessment!$J:$J,$X64)) -> Operate SBOM-based continuous vulnerability monitoring, periodic security reviews and remediation for all supported releases. | H64: =IF($X64="","",INDEX(Assessment!$L:$L,$X64)) -> PSIRT Lead / Product Security Officer | I64: =IF($X64="","",INDEX(Assessment!$N:$N,$X64)) -> M | X64: =IF(48<=$B$6,SMALL($Y$2:$Y$593,48),IF(48<=$B$6+$B$7,SMALL($Z$2:$Z$593,48-$B$6),"")) -> 191 | Y64: =IF(Assessment!$G64="Critical",ROW(Assessment!$G64),"") | Z64: =IF(Assessment!$G64="High",ROW(Assessment!$G64),"")
A65: =IF($X65="","",49) -> 49 | B65: =IF($X65="","",INDEX(Assessment!$A:$A,$X65)) -> TR1-158 | C65: =IF($X65="","",INDEX(Assessment!$B:$B,$X65)) -> BSI TR-03183-1 v1.0.0 | D65: =IF($X65="","",INDEX(Assessment!$C:$C,$X65)) -> 5.13.1 Update Risk Assessment - General (trigger) | E65: =IF($X65="","",INDEX(Assessment!$F:$F,$X65)) -> Risk assessment - update | F65: =IF($X65="","",INDEX(Assessment!$G:$G,$X65)) -> High | G65: =IF($X65="","",INDEX(Assessment!$J:$J,$X65)) -> Operate SBOM-based continuous vulnerability monitoring, periodic security reviews and remediation for all supported releases. | H65: =IF($X65="","",INDEX(Assessment!$L:$L,$X65)) -> PSIRT Lead / Product Security Officer | I65: =IF($X65="","",INDEX(Assessment!$N:$N,$X65)) -> M | X65: =IF(49<=$B$6,SMALL($Y$2:$Y$593,49),IF(49<=$B$6+$B$7,SMALL($Z$2:$Z$593,49-$B$6),"")) -> 193 | Y65: =IF(Assessment!$G65="Critical",ROW(Assessment!$G65),"") | Z65: =IF(Assessment!$G65="High",ROW(Assessment!$G65),"")
A66: =IF($X66="","",50) -> 50 | B66: =IF($X66="","",INDEX(Assessment!$A:$A,$X66)) -> RH_UPD.1-a | C66: =IF($X66="","",INDEX(Assessment!$B:$B,$X66)) -> BSI TR-03183-1 v1.0.0 | D66: =IF($X66="","",INDEX(Assessment!$C:$C,$X66)) -> 5.13.3 Control - RH_UPD.1 Update Risk Assessment (Activity) | E66: =IF($X66="","",INDEX(Assessment!$F:$F,$X66)) -> Risk assessment - update | F66: =IF($X66="","",INDEX(Assessment!$G:$G,$X66)) -> High | G66: =IF($X66="","",INDEX(Assessment!$J:$J,$X66)) -> Trigger risk-assessment updates from PSIRT cases and threat intelligence. | H66: =IF($X66="","",INDEX(Assessment!$L:$L,$X66)) -> Product Security Officer | I66: =IF($X66="","",INDEX(Assessment!$N:$N,$X66)) -> M | X66: =IF(50<=$B$6,SMALL($Y$2:$Y$593,50),IF(50<=$B$6+$B$7,SMALL($Z$2:$Z$593,50-$B$6),"")) -> 196 | Y66: =IF(Assessment!$G66="Critical",ROW(Assessment!$G66),"") | Z66: =IF(Assessment!$G66="High",ROW(Assessment!$G66),"")
A67: =IF($X67="","",51) -> 51 | B67: =IF($X67="","",INDEX(Assessment!$A:$A,$X67)) -> RH_UPD.1-b | C67: =IF($X67="","",INDEX(Assessment!$B:$B,$X67)) -> BSI TR-03183-1 v1.0.0 | D67: =IF($X67="","",INDEX(Assessment!$C:$C,$X67)) -> 5.13.3 Control - RH_UPD.1 Update Risk Assessment (Activity) | E67: =IF($X67="","",INDEX(Assessment!$F:$F,$X67)) -> Risk treatment | F67: =IF($X67="","",INDEX(Assessment!$G:$G,$X67)) -> High | G67: =IF($X67="","",INDEX(Assessment!$J:$J,$X67)) -> Treat post-market risks via fixes, mitigations or documented acceptance. | H67: =IF($X67="","",INDEX(Assessment!$L:$L,$X67)) -> Product Security Officer | I67: =IF($X67="","",INDEX(Assessment!$N:$N,$X67)) -> M | X67: =IF(51<=$B$6,SMALL($Y$2:$Y$593,51),IF(51<=$B$6+$B$7,SMALL($Z$2:$Z$593,51-$B$6),"")) -> 197 | Y67: =IF(Assessment!$G67="Critical",ROW(Assessment!$G67),"") | Z67: =IF(Assessment!$G67="High",ROW(Assessment!$G67),"")
A68: =IF($X68="","",52) -> 52 | B68: =IF($X68="","",INDEX(Assessment!$A:$A,$X68)) -> ER.1 | C68: =IF($X68="","",INDEX(Assessment!$B:$B,$X68)) -> BSI TR-03183-1 v1.0.0 | D68: =IF($X68="","",INDEX(Assessment!$C:$C,$X68)) -> Annex B Table 9 (CRA Annex I Part I (2)(a)); text also in 3.9 | E68: =IF($X68="","",INDEX(Assessment!$F:$F,$X68)) -> Essential requirements - no known exploitable vulnerabilities | F68: =IF($X68="","",INDEX(Assessment!$G:$G,$X68)) -> High | G68: =IF($X68="","",INDEX(Assessment!$J:$J,$X68)) -> Check in regression and post-market reviews that updates do not weaken the property. | H68: =IF($X68="","",INDEX(Assessment!$L:$L,$X68)) -> PSIRT Lead / QA Lead | I68: =IF($X68="","",INDEX(Assessment!$N:$N,$X68)) -> M | X68: =IF(52<=$B$6,SMALL($Y$2:$Y$593,52),IF(52<=$B$6+$B$7,SMALL($Z$2:$Z$593,52-$B$6),"")) -> 231 | Y68: =IF(Assessment!$G68="Critical",ROW(Assessment!$G68),"") | Z68: =IF(Assessment!$G68="High",ROW(Assessment!$G68),"")
A69: =IF($X69="","",53) -> 53 | B69: =IF($X69="","",INDEX(Assessment!$A:$A,$X69)) -> ER.4 | C69: =IF($X69="","",INDEX(Assessment!$B:$B,$X69)) -> BSI TR-03183-1 v1.0.0 | D69: =IF($X69="","",INDEX(Assessment!$C:$C,$X69)) -> Annex B Table 9 (CRA Annex I Part I (2)(c)); text also in 3.9 | E69: =IF($X69="","",INDEX(Assessment!$F:$F,$X69)) -> Essential requirements - security updates | F69: =IF($X69="","",INDEX(Assessment!$G:$G,$X69)) -> High | G69: =IF($X69="","",INDEX(Assessment!$J:$J,$X69)) -> Operate update distribution and track installation status per site. | H69: =IF($X69="","",INDEX(Assessment!$L:$L,$X69)) -> Service Delivery Manager | I69: =IF($X69="","",INDEX(Assessment!$N:$N,$X69)) -> M | X69: =IF(53<=$B$6,SMALL($Y$2:$Y$593,53),IF(53<=$B$6+$B$7,SMALL($Z$2:$Z$593,53-$B$6),"")) -> 234 | Y69: =IF(Assessment!$G69="Critical",ROW(Assessment!$G69),"") | Z69: =IF(Assessment!$G69="High",ROW(Assessment!$G69),"")
A70: =IF($X70="","",54) -> 54 | B70: =IF($X70="","",INDEX(Assessment!$A:$A,$X70)) -> ER.4c | C70: =IF($X70="","",INDEX(Assessment!$B:$B,$X70)) -> BSI TR-03183-1 v1.0.0 | D70: =IF($X70="","",INDEX(Assessment!$C:$C,$X70)) -> Annex B Table 9 (CRA Annex I Part I (2)(c)); text also in 3.9 | E70: =IF($X70="","",INDEX(Assessment!$F:$F,$X70)) -> Essential requirements - security updates | F70: =IF($X70="","",INDEX(Assessment!$G:$G,$X70)) -> High | G70: =IF($X70="","",INDEX(Assessment!$J:$J,$X70)) -> Operate update distribution and track installation status per site. | H70: =IF($X70="","",INDEX(Assessment!$L:$L,$X70)) -> Service Delivery Manager | I70: =IF($X70="","",INDEX(Assessment!$N:$N,$X70)) -> M | X70: =IF(54<=$B$6,SMALL($Y$2:$Y$593,54),IF(54<=$B$6+$B$7,SMALL($Z$2:$Z$593,54-$B$6),"")) -> 237 | Y70: =IF(Assessment!$G70="Critical",ROW(Assessment!$G70),"") | Z70: =IF(Assessment!$G70="High",ROW(Assessment!$G70),"")
A71: =IF($X71="","",55) -> 55 | B71: =IF($X71="","",INDEX(Assessment!$A:$A,$X71)) -> ER.9 | C71: =IF($X71="","",INDEX(Assessment!$B:$B,$X71)) -> BSI TR-03183-1 v1.0.0 | D71: =IF($X71="","",INDEX(Assessment!$C:$C,$X71)) -> Annex B Table 9 (CRA Annex I Part I (2)(h)); text also in 3.9 | E71: =IF($X71="","",INDEX(Assessment!$F:$F,$X71)) -> Essential requirements - availability & resilience | F71: =IF($X71="","",INDEX(Assessment!$G:$G,$X71)) -> High | G71: =IF($X71="","",INDEX(Assessment!$J:$J,$X71)) -> Check in regression and post-market reviews that updates do not weaken the property. | H71: =IF($X71="","",INDEX(Assessment!$L:$L,$X71)) -> PSIRT Lead / QA Lead | I71: =IF($X71="","",INDEX(Assessment!$N:$N,$X71)) -> M | X71: =IF(55<=$B$6,SMALL($Y$2:$Y$593,55),IF(55<=$B$6+$B$7,SMALL($Z$2:$Z$593,55-$B$6),"")) -> 246 | Y71: =IF(Assessment!$G71="Critical",ROW(Assessment!$G71),"") | Z71: =IF(Assessment!$G71="High",ROW(Assessment!$G71),"")
A72: =IF($X72="","",56) -> 56 | B72: =IF($X72="","",INDEX(Assessment!$A:$A,$X72)) -> VH.1a | C72: =IF($X72="","",INDEX(Assessment!$B:$B,$X72)) -> BSI TR-03183-1 v1.0.0 | D72: =IF($X72="","",INDEX(Assessment!$C:$C,$X72)) -> Annex B Table 10 (CRA Annex I Part II (1)); text also in 3.9 | E72: =IF($X72="","",INDEX(Assessment!$F:$F,$X72)) -> SBOM (CRA) | F72: =IF($X72="","",INDEX(Assessment!$G:$G,$X72)) -> High | G72: =IF($X72="","",INDEX(Assessment!$J:$J,$X72)) -> Implement, document and operate: draw up an SBOM in a commonly used machine-readable format covering at least top-level dependencies. | H72: =IF($X72="","",INDEX(Assessment!$L:$L,$X72)) -> PSIRT Lead | I72: =IF($X72="","",INDEX(Assessment!$N:$N,$X72)) -> M | X72: =IF(56<=$B$6,SMALL($Y$2:$Y$593,56),IF(56<=$B$6+$B$7,SMALL($Z$2:$Z$593,56-$B$6),"")) -> 258 | Y72: =IF(Assessment!$G72="Critical",ROW(Assessment!$G72),"") | Z72: =IF(Assessment!$G72="High",ROW(Assessment!$G72),"")
A73: =IF($X73="","",57) -> 57 | B73: =IF($X73="","",INDEX(Assessment!$A:$A,$X73)) -> VH.2a-b | C73: =IF($X73="","",INDEX(Assessment!$B:$B,$X73)) -> BSI TR-03183-1 v1.0.0 | D73: =IF($X73="","",INDEX(Assessment!$C:$C,$X73)) -> Annex B Table 10 (CRA Annex I Part II (2)); text also in 3.9 | E73: =IF($X73="","",INDEX(Assessment!$F:$F,$X73)) -> Vulnerability handling - separate security updates | F73: =IF($X73="","",INDEX(Assessment!$G:$G,$X73)) -> High | G73: =IF($X73="","",INDEX(Assessment!$J:$J,$X73)) -> Implement, document and operate: provide security updates separately from functionality updates where technically feasible. | H73: =IF($X73="","",INDEX(Assessment!$L:$L,$X73)) -> PSIRT Lead | I73: =IF($X73="","",INDEX(Assessment!$N:$N,$X73)) -> M | X73: =IF(57<=$B$6,SMALL($Y$2:$Y$593,57),IF(57<=$B$6+$B$7,SMALL($Z$2:$Z$593,57-$B$6),"")) -> 260 | Y73: =IF(Assessment!$G73="Critical",ROW(Assessment!$G73),"") | Z73: =IF(Assessment!$G73="High",ROW(Assessment!$G73),"")
A74: =IF($X74="","",58) -> 58 | B74: =IF($X74="","",INDEX(Assessment!$A:$A,$X74)) -> VH.6 | C74: =IF($X74="","",INDEX(Assessment!$B:$B,$X74)) -> BSI TR-03183-1 v1.0.0 | D74: =IF($X74="","",INDEX(Assessment!$C:$C,$X74)) -> Annex B Table 10 (CRA Annex I Part II (6)); text also in 3.9 | E74: =IF($X74="","",INDEX(Assessment!$F:$F,$X74)) -> Vulnerability information sharing | F74: =IF($X74="","",INDEX(Assessment!$G:$G,$X74)) -> High | G74: =IF($X74="","",INDEX(Assessment!$J:$J,$X74)) -> Implement, document and operate: facilitate sharing information about potential vulnerabilities in the product and its third-party components. | H74: =IF($X74="","",INDEX(Assessment!$L:$L,$X74)) -> PSIRT Lead | I74: =IF($X74="","",INDEX(Assessment!$N:$N,$X74)) -> M | X74: =IF(58<=$B$6,SMALL($Y$2:$Y$593,58),IF(58<=$B$6+$B$7,SMALL($Z$2:$Z$593,58-$B$6),"")) -> 265 | Y74: =IF(Assessment!$G74="Critical",ROW(Assessment!$G74),"") | Z74: =IF(Assessment!$G74="High",ROW(Assessment!$G74),"")
A75: =IF($X75="","",59) -> 59 | B75: =IF($X75="","",INDEX(Assessment!$A:$A,$X75)) -> VH.8a-a | C75: =IF($X75="","",INDEX(Assessment!$B:$B,$X75)) -> BSI TR-03183-1 v1.0.0 | D75: =IF($X75="","",INDEX(Assessment!$C:$C,$X75)) -> Annex B Table 10 (CRA Annex I Part II (8)); text also in 3.9 | E75: =IF($X75="","",INDEX(Assessment!$F:$F,$X75)) -> Security updates - free of charge | F75: =IF($X75="","",INDEX(Assessment!$G:$G,$X75)) -> High | G75: =IF($X75="","",INDEX(Assessment!$J:$J,$X75)) -> Implement, document and operate: security updates free of charge unless otherwise agreed for tailor-made business products. | H75: =IF($X75="","",INDEX(Assessment!$L:$L,$X75)) -> PSIRT Lead | I75: =IF($X75="","",INDEX(Assessment!$N:$N,$X75)) -> M | X75: =IF(59<=$B$6,SMALL($Y$2:$Y$593,59),IF(59<=$B$6+$B$7,SMALL($Z$2:$Z$593,59-$B$6),"")) -> 270 | Y75: =IF(Assessment!$G75="Critical",ROW(Assessment!$G75),"") | Z75: =IF(Assessment!$G75="High",ROW(Assessment!$G75),"")
A76: =IF($X76="","",60) -> 60 | B76: =IF($X76="","",INDEX(Assessment!$A:$A,$X76)) -> VH.8a-b | C76: =IF($X76="","",INDEX(Assessment!$B:$B,$X76)) -> BSI TR-03183-1 v1.0.0 | D76: =IF($X76="","",INDEX(Assessment!$C:$C,$X76)) -> Annex B Table 10 (CRA Annex I Part II (8)); text also in 3.9 | E76: =IF($X76="","",INDEX(Assessment!$F:$F,$X76)) -> Security advisories | F76: =IF($X76="","",INDEX(Assessment!$G:$G,$X76)) -> High | G76: =IF($X76="","",INDEX(Assessment!$J:$J,$X76)) -> Implement, document and operate: accompany security updates with advisory messages incl. actions to take. | H76: =IF($X76="","",INDEX(Assessment!$L:$L,$X76)) -> PSIRT Lead | I76: =IF($X76="","",INDEX(Assessment!$N:$N,$X76)) -> M | X76: =IF(60<=$B$6,SMALL($Y$2:$Y$593,60),IF(60<=$B$6+$B$7,SMALL($Z$2:$Z$593,60-$B$6),"")) -> 271 | Y76: =IF(Assessment!$G76="Critical",ROW(Assessment!$G76),"") | Z76: =IF(Assessment!$G76="High",ROW(Assessment!$G76),"")
A77: =IF($X77="","",61) -> 61 | B77: =IF($X77="","",INDEX(Assessment!$A:$A,$X77)) -> TR2-003 | C77: =IF($X77="","",INDEX(Assessment!$B:$B,$X77)) -> BSI TR-03183-2 v2.1.0 | D77: =IF($X77="","",INDEX(Assessment!$C:$C,$X77)) -> 1 Introduction | E77: =IF($X77="","",INDEX(Assessment!$F:$F,$X77)) -> SBOM - vulnerability information | F77: =IF($X77="","",INDEX(Assessment!$G:$G,$X77)) -> High | G77: =IF($X77="","",INDEX(Assessment!$J:$J,$X77)) -> Triage every SBOM-based match, record the exploitability decision, and publish product status as CSAF/VEX linked to SBOM component identifiers. | H77: =IF($X77="","",INDEX(Assessment!$L:$L,$X77)) -> PSIRT Lead | I77: =IF($X77="","",INDEX(Assessment!$N:$N,$X77)) -> M | X77: =IF(61<=$B$6,SMALL($Y$2:$Y$593,61),IF(61<=$B$6+$B$7,SMALL($Z$2:$Z$593,61-$B$6),"")) -> 286 | Y77: =IF(Assessment!$G77="Critical",ROW(Assessment!$G77),"") | Z77: =IF(Assessment!$G77="High",ROW(Assessment!$G77),"")
A78: =IF($X78="","",62) -> 62 | B78: =IF($X78="","",INDEX(Assessment!$A:$A,$X78)) -> TR2-005 | C78: =IF($X78="","",INDEX(Assessment!$B:$B,$X78)) -> BSI TR-03183-2 v2.1.0 | D78: =IF($X78="","",INDEX(Assessment!$C:$C,$X78)) -> 1 Introduction | E78: =IF($X78="","",INDEX(Assessment!$F:$F,$X78)) -> SBOM - general | F78: =IF($X78="","",INDEX(Assessment!$G:$G,$X78)) -> High | G78: =IF($X78="","",INDEX(Assessment!$J:$J,$X78)) -> Load every released SBOM into the vulnerability monitoring tool; publish updated/corrected SBOMs with patch releases. | H78: =IF($X78="","",INDEX(Assessment!$L:$L,$X78)) -> PSIRT Lead | I78: =IF($X78="","",INDEX(Assessment!$N:$N,$X78)) -> M | X78: =IF(62<=$B$6,SMALL($Y$2:$Y$593,62),IF(62<=$B$6+$B$7,SMALL($Z$2:$Z$593,62-$B$6),"")) -> 288 | Y78: =IF(Assessment!$G78="Critical",ROW(Assessment!$G78),"") | Z78: =IF(Assessment!$G78="High",ROW(Assessment!$G78),"") -> 78
A79: =IF($X79="","",63) -> 63 | B79: =IF($X79="","",INDEX(Assessment!$A:$A,$X79)) -> TR2-006-a | C79: =IF($X79="","",INDEX(Assessment!$B:$B,$X79)) -> BSI TR-03183-2 v2.1.0 | D79: =IF($X79="","",INDEX(Assessment!$C:$C,$X79)) -> 1 Introduction | E79: =IF($X79="","",INDEX(Assessment!$F:$F,$X79)) -> Vulnerability handling process | F79: =IF($X79="","",INDEX(Assessment!$G:$G,$X79)) -> High | G79: =IF($X79="","",INDEX(Assessment!$J:$J,$X79)) -> Establish and document the vulnerability handling chain: intake, triage, fix, release, secure distribution, installation tracking. | H79: =IF($X79="","",INDEX(Assessment!$L:$L,$X79)) -> PSIRT Lead | I79: =IF($X79="","",INDEX(Assessment!$N:$N,$X79)) -> M | X79: =IF(63<=$B$6,SMALL($Y$2:$Y$593,63),IF(63<=$B$6+$B$7,SMALL($Z$2:$Z$593,63-$B$6),"")) -> 289 | Y79: =IF(Assessment!$G79="Critical",ROW(Assessment!$G79),"") | Z79: =IF(Assessment!$G79="High",ROW(Assessment!$G79),"") -> 79
A80: =IF($X80="","",64) -> 64 | B80: =IF($X80="","",INDEX(Assessment!$A:$A,$X80)) -> TR2-011 | C80: =IF($X80="","",INDEX(Assessment!$B:$B,$X80)) -> BSI TR-03183-2 v2.1.0 | D80: =IF($X80="","",INDEX(Assessment!$C:$C,$X80)) -> 3.1 Definition of SBOM | E80: =IF($X80="","",INDEX(Assessment!$F:$F,$X80)) -> SBOM - per version | F80: =IF($X80="","",INDEX(Assessment!$G:$G,$X80)) -> High | G80: =IF($X80="","",INDEX(Assessment!$J:$J,$X80)) -> Load every released SBOM into the vulnerability monitoring tool; publish updated/corrected SBOMs with patch releases. | H80: =IF($X80="","",INDEX(Assessment!$L:$L,$X80)) -> PSIRT Lead | I80: =IF($X80="","",INDEX(Assessment!$N:$N,$X80)) -> M | X80: =IF(64<=$B$6,SMALL($Y$2:$Y$593,64),IF(64<=$B$6+$B$7,SMALL($Z$2:$Z$593,64-$B$6),"")) -> 295 | Y80: =IF(Assessment!$G80="Critical",ROW(Assessment!$G80),"") | Z80: =IF(Assessment!$G80="High",ROW(Assessment!$G80),"") -> 80
A81: =IF($X81="","",65) -> 65 | B81: =IF($X81="","",INDEX(Assessment!$A:$A,$X81)) -> TR2-066 | C81: =IF($X81="","",INDEX(Assessment!$B:$B,$X81)) -> BSI TR-03183-2 v2.1.0 | D81: =IF($X81="","",INDEX(Assessment!$C:$C,$X81)) -> 5.2.4 Additional data fields for each component (Table 5) | E81: =IF($X81="","",INDEX(Assessment!$F:$F,$X81)) -> SBOM - data fields (component) | F81: =IF($X81="","",INDEX(Assessment!$G:$G,$X81)) -> High | G81: =IF($X81="","",INDEX(Assessment!$J:$J,$X81)) -> Use the field in monitoring/matching rules; correct and re-issue SBOMs where the data is wrong. | H81: =IF($X81="","",INDEX(Assessment!$L:$L,$X81)) -> PSIRT Lead | I81: =IF($X81="","",INDEX(Assessment!$N:$N,$X81)) -> M | X81: =IF(65<=$B$6,SMALL($Y$2:$Y$593,65),IF(65<=$B$6+$B$7,SMALL($Z$2:$Z$593,65-$B$6),"")) -> 363 | Y81: =IF(Assessment!$G81="Critical",ROW(Assessment!$G81),"") | Z81: =IF(Assessment!$G81="High",ROW(Assessment!$G81),"")
A82: =IF($X82="","",66) -> 66 | B82: =IF($X82="","",INDEX(Assessment!$A:$A,$X82)) -> TR2-092 | C82: =IF($X82="","",INDEX(Assessment!$B:$B,$X82)) -> BSI TR-03183-2 v2.1.0 | D82: =IF($X82="","",INDEX(Assessment!$C:$C,$X82)) -> 8.1.14 Vulnerability information (appendix) | E82: =IF($X82="","",INDEX(Assessment!$F:$F,$X82)) -> SBOM - vulnerability information | F82: =IF($X82="","",INDEX(Assessment!$G:$G,$X82)) -> High | G82: =IF($X82="","",INDEX(Assessment!$J:$J,$X82)) -> Triage every SBOM-based match, record the exploitability decision, and publish product status as CSAF/VEX linked to SBOM component identifiers. | H82: =IF($X82="","",INDEX(Assessment!$L:$L,$X82)) -> PSIRT Lead | I82: =IF($X82="","",INDEX(Assessment!$N:$N,$X82)) -> M | X82: =IF(66<=$B$6,SMALL($Y$2:$Y$593,66),IF(66<=$B$6+$B$7,SMALL($Z$2:$Z$593,66-$B$6),"")) -> 395 | Y82: =IF(Assessment!$G82="Critical",ROW(Assessment!$G82),"") | Z82: =IF(Assessment!$G82="High",ROW(Assessment!$G82),"")
A83: =IF($X83="","",67) -> 67 | B83: =IF($X83="","",INDEX(Assessment!$A:$A,$X83)) -> TR3-001 | C83: =IF($X83="","",INDEX(Assessment!$B:$B,$X83)) -> BSI TR-03183-3 v1.0.0 | D83: =IF($X83="","",INDEX(Assessment!$C:$C,$X83)) -> 1 Introduction | E83: =IF($X83="","",INDEX(Assessment!$F:$F,$X83)) -> Vulnerability handling process | F83: =IF($X83="","",INDEX(Assessment!$G:$G,$X83)) -> High | G83: =IF($X83="","",INDEX(Assessment!$J:$J,$X83)) -> Establish and document the vulnerability handling chain: intake, triage, fix, release, secure distribution, installation tracking. | H83: =IF($X83="","",INDEX(Assessment!$L:$L,$X83)) -> PSIRT Lead | I83: =IF($X83="","",INDEX(Assessment!$N:$N,$X83)) -> M | X83: =IF(67<=$B$6,SMALL($Y$2:$Y$593,67),IF(67<=$B$6+$B$7,SMALL($Z$2:$Z$593,67-$B$6),"")) -> 412 | Y83: =IF(Assessment!$G83="Critical",ROW(Assessment!$G83),"") | Z83: =IF(Assessment!$G83="High",ROW(Assessment!$G83),"")
A84: =IF($X84="","",68) -> 68 | B84: =IF($X84="","",INDEX(Assessment!$A:$A,$X84)) -> TR3-003 | C84: =IF($X84="","",INDEX(Assessment!$B:$B,$X84)) -> BSI TR-03183-3 v1.0.0 | D84: =IF($X84="","",INDEX(Assessment!$C:$C,$X84)) -> 1 Introduction | E84: =IF($X84="","",INDEX(Assessment!$F:$F,$X84)) -> CVD - preparation | F84: =IF($X84="","",INDEX(Assessment!$G:$G,$X84)) -> High | G84: =IF($X84="","",INDEX(Assessment!$J:$J,$X84)) -> Write into the CVD policy / PSIRT procedure and apply in case handling: prepare holistic internal CVD processes across departments, contact options and channels. | H84: =IF($X84="","",INDEX(Assessment!$L:$L,$X84)) -> PSIRT Lead (Legal reviews policy wording) | I84: =IF($X84="","",INDEX(Assessment!$N:$N,$X84)) -> M | X84: =IF(68<=$B$6,SMALL($Y$2:$Y$593,68),IF(68<=$B$6+$B$7,SMALL($Z$2:$Z$593,68-$B$6),"")) -> 415 | Y84: =IF(Assessment!$G84="Critical",ROW(Assessment!$G84),"") | Z84: =IF(Assessment!$G84="High",ROW(Assessment!$G84),"") -> 84
A85: =IF($X85="","",69) -> 69 | B85: =IF($X85="","",INDEX(Assessment!$A:$A,$X85)) -> TR3-005 | C85: =IF($X85="","",INDEX(Assessment!$B:$B,$X85)) -> BSI TR-03183-3 v1.0.0 | D85: =IF($X85="","",INDEX(Assessment!$C:$C,$X85)) -> 1 Introduction | E85: =IF($X85="","",INDEX(Assessment!$F:$F,$X85)) -> CVD - preparation | F85: =IF($X85="","",INDEX(Assessment!$G:$G,$X85)) -> High | G85: =IF($X85="","",INDEX(Assessment!$J:$J,$X85)) -> Implement on the corporate website: publish the contact options and the CVD policy for external communication; include it in the quarterly security.txt/contact check. | H85: =IF($X85="","",INDEX(Assessment!$L:$L,$X85)) -> PSIRT Lead with Web/IT team | I85: =IF($X85="","",INDEX(Assessment!$N:$N,$X85)) -> M | X85: =IF(69<=$B$6,SMALL($Y$2:$Y$593,69),IF(69<=$B$6+$B$7,SMALL($Z$2:$Z$593,69-$B$6),"")) -> 418 | Y85: =IF(Assessment!$G85="Critical",ROW(Assessment!$G85),"") | Z85: =IF(Assessment!$G85="High",ROW(Assessment!$G85),"")
A86: =IF($X86="","",70) -> 70 | B86: =IF($X86="","",INDEX(Assessment!$A:$A,$X86)) -> TR3-006 | C86: =IF($X86="","",INDEX(Assessment!$B:$B,$X86)) -> BSI TR-03183-3 v1.0.0 | D86: =IF($X86="","",INDEX(Assessment!$C:$C,$X86)) -> 3.1.5 Security advisory | E86: =IF($X86="","",INDEX(Assessment!$F:$F,$X86)) -> Security advisories (CSAF) | F86: =IF($X86="","",INDEX(Assessment!$G:$G,$X86)) -> High | G86: =IF($X86="","",INDEX(Assessment!$J:$J,$X86)) -> publish security advisories on the manufacturer website in CSAF format - define the disclosure workflow, deadlines and approvals. | H86: =IF($X86="","",INDEX(Assessment!$L:$L,$X86)) -> PSIRT Lead | I86: =IF($X86="","",INDEX(Assessment!$N:$N,$X86)) -> M | X86: =IF(70<=$B$6,SMALL($Y$2:$Y$593,70),IF(70<=$B$6+$B$7,SMALL($Z$2:$Z$593,70-$B$6),"")) -> 419 | Y86: =IF(Assessment!$G86="Critical",ROW(Assessment!$G86),"") | Z86: =IF(Assessment!$G86="High",ROW(Assessment!$G86),"")
A87: =IF($X87="","",71) -> 71 | B87: =IF($X87="","",INDEX(Assessment!$A:$A,$X87)) -> TR3-008 | C87: =IF($X87="","",INDEX(Assessment!$B:$B,$X87)) -> BSI TR-03183-3 v1.0.0 | D87: =IF($X87="","",INDEX(Assessment!$C:$C,$X87)) -> 3.1.7 Corresponding national CSIRT | E87: =IF($X87="","",INDEX(Assessment!$F:$F,$X87)) -> CVD - national CSIRT coordination | F87: =IF($X87="","",INDEX(Assessment!$G:$G,$X87)) -> High | G87: =IF($X87="","",INDEX(Assessment!$J:$J,$X87)) -> determine the corresponding CSIRT according to CRA Art. 14(7) (main establishment) - document it in the PSIRT notification procedure and keep a case log. | H87: =IF($X87="","",INDEX(Assessment!$L:$L,$X87)) -> PSIRT Lead / Compliance Officer | I87: =IF($X87="","",INDEX(Assessment!$N:$N,$X87)) -> S | X87: =IF(71<=$B$6,SMALL($Y$2:$Y$593,71),IF(71<=$B$6+$B$7,SMALL($Z$2:$Z$593,71-$B$6),"")) -> 421 | Y87: =IF(Assessment!$G87="Critical",ROW(Assessment!$G87),"") | Z87: =IF(Assessment!$G87="High",ROW(Assessment!$G87),"")
A88: =IF($X88="","",72) -> 72 | B88: =IF($X88="","",INDEX(Assessment!$A:$A,$X88)) -> TR3-016 | C88: =IF($X88="","",INDEX(Assessment!$B:$B,$X88)) -> BSI TR-03183-3 v1.0.0 | D88: =IF($X88="","",INDEX(Assessment!$C:$C,$X88)) -> 4 Cybersecurity requirements for receiving vulnerability reports | E88: =IF($X88="","",INDEX(Assessment!$F:$F,$X88)) -> Vulnerability intake - records | F88: =IF($X88="","",INDEX(Assessment!$G:$G,$X88)) -> High | G88: =IF($X88="","",INDEX(Assessment!$J:$J,$X88)) -> Keep an evidence register: implemented measures, test procedures and test results for the reporting channels. | H88: =IF($X88="","",INDEX(Assessment!$L:$L,$X88)) -> PSIRT Lead | I88: =IF($X88="","",INDEX(Assessment!$N:$N,$X88)) -> M | X88: =IF(72<=$B$6,SMALL($Y$2:$Y$593,72),IF(72<=$B$6+$B$7,SMALL($Z$2:$Z$593,72-$B$6),"")) -> 429 | Y88: =IF(Assessment!$G88="Critical",ROW(Assessment!$G88),"") | Z88: =IF(Assessment!$G88="High",ROW(Assessment!$G88),"")
A89: =IF($X89="","",73) -> 73 | B89: =IF($X89="","",INDEX(Assessment!$A:$A,$X89)) -> TR3-019 | C89: =IF($X89="","",INDEX(Assessment!$B:$B,$X89)) -> BSI TR-03183-3 v1.0.0 | D89: =IF($X89="","",INDEX(Assessment!$C:$C,$X89)) -> 4.1 Website of the manufacturer | E89: =IF($X89="","",INDEX(Assessment!$F:$F,$X89)) -> Security information website | F89: =IF($X89="","",INDEX(Assessment!$G:$G,$X89)) -> High | G89: =IF($X89="","",INDEX(Assessment!$J:$J,$X89)) -> Implement on the corporate website: make security-related information easily accessible to the public; include it in the quarterly security.txt/contact check. | H89: =IF($X89="","",INDEX(Assessment!$L:$L,$X89)) -> PSIRT Lead with Web/IT team | I89: =IF($X89="","",INDEX(Assessment!$N:$N,$X89)) -> M | X89: =IF(73<=$B$6,SMALL($Y$2:$Y$593,73),IF(73<=$B$6+$B$7,SMALL($Z$2:$Z$593,73-$B$6),"")) -> 432 | Y89: =IF(Assessment!$G89="Critical",ROW(Assessment!$G89),"") | Z89: =IF(Assessment!$G89="High",ROW(Assessment!$G89),"")
A90: =IF($X90="","",74) -> 74 | B90: =IF($X90="","",INDEX(Assessment!$A:$A,$X90)) -> TR3-4.1.1a | C90: =IF($X90="","",INDEX(Assessment!$B:$B,$X90)) -> BSI TR-03183-3 v1.0.0 | D90: =IF($X90="","",INDEX(Assessment!$C:$C,$X90)) -> 4.1.1 General | E90: =IF($X90="","",INDEX(Assessment!$F:$F,$X90)) -> Security information website | F90: =IF($X90="","",INDEX(Assessment!$G:$G,$X90)) -> High | G90: =IF($X90="","",INDEX(Assessment!$J:$J,$X90)) -> Implement on the corporate website: operate a website that publicly provides security-related information about the manufacturer and its products; include it in the quarterly security.txt/contact check. | H90: =IF($X90="","",INDEX(Assessment!$L:$L,$X90)) -> PSIRT Lead with Web/IT team | I90: =IF($X90="","",INDEX(Assessment!$N:$N,$X90)) -> M | X90: =IF(74<=$B$6,SMALL($Y$2:$Y$593,74),IF(74<=$B$6+$B$7,SMALL($Z$2:$Z$593,74-$B$6),"")) -> 433 | Y90: =IF(Assessment!$G90="Critical",ROW(Assessment!$G90),"") | Z90: =IF(Assessment!$G90="High",ROW(Assessment!$G90),"")
A91: =IF($X91="","",75) -> 75 | B91: =IF($X91="","",INDEX(Assessment!$A:$A,$X91)) -> TR3-020 | C91: =IF($X91="","",INDEX(Assessment!$B:$B,$X91)) -> BSI TR-03183-3 v1.0.0 | D91: =IF($X91="","",INDEX(Assessment!$C:$C,$X91)) -> 4.2 Security.txt file in accordance with RFC 9116 | E91: =IF($X91="","",INDEX(Assessment!$F:$F,$X91)) -> security.txt (RFC 9116) | F91: =IF($X91="","",INDEX(Assessment!$G:$G,$X91)) -> High | G91: =IF($X91="","",INDEX(Assessment!$J:$J,$X91)) -> Implement on the corporate website: create a security.txt according to RFC 9116 and make it available on the website; include it in the quarterly security.txt/contact check. | H91: =IF($X91="","",INDEX(Assessment!$L:$L,$X91)) -> PSIRT Lead with Web/IT team | I91: =IF($X91="","",INDEX(Assessment!$N:$N,$X91)) -> M | X91: =IF(75<=$B$6,SMALL($Y$2:$Y$593,75),IF(75<=$B$6+$B$7,SMALL($Z$2:$Z$593,75-$B$6),"")) -> 436 | Y91: =IF(Assessment!$G91="Critical",ROW(Assessment!$G91),"") | Z91: =IF(Assessment!$G91="High",ROW(Assessment!$G91),"")
A92: =IF($X92="","",76) -> 76 | B92: =IF($X92="","",INDEX(Assessment!$A:$A,$X92)) -> TR3-021 | C92: =IF($X92="","",INDEX(Assessment!$B:$B,$X92)) -> BSI TR-03183-3 v1.0.0 | D92: =IF($X92="","",INDEX(Assessment!$C:$C,$X92)) -> 4.3 Preliminary measures for a CVD process | E92: =IF($X92="","",INDEX(Assessment!$F:$F,$X92)) -> PSIRT / CSIRT organisation | F92: =IF($X92="","",INDEX(Assessment!$G:$G,$X92)) -> High | G92: =IF($X92="","",INDEX(Assessment!$J:$J,$X92)) -> Set up and document: organise the response process for vulnerability reports in advance. | H92: =IF($X92="","",INDEX(Assessment!$L:$L,$X92)) -> CISO / PSIRT Lead | I92: =IF($X92="","",INDEX(Assessment!$N:$N,$X92)) -> M | X92: =IF(76<=$B$6,SMALL($Y$2:$Y$593,76),IF(76<=$B$6+$B$7,SMALL($Z$2:$Z$593,76-$B$6),"")) -> 478 | Y92: =IF(Assessment!$G92="Critical",ROW(Assessment!$G92),"") | Z92: =IF(Assessment!$G92="High",ROW(Assessment!$G92),"")
A93: =IF($X93="","",77) -> 77 | B93: =IF($X93="","",INDEX(Assessment!$A:$A,$X93)) -> TR3-4.3.1b | C93: =IF($X93="","",INDEX(Assessment!$B:$B,$X93)) -> BSI TR-03183-3 v1.0.0 | D93: =IF($X93="","",INDEX(Assessment!$C:$C,$X93)) -> 4.3.1 Roles of responsible cybersecurity contacts | E93: =IF($X93="","",INDEX(Assessment!$F:$F,$X93)) -> PSIRT / CSIRT organisation | F93: =IF($X93="","",INDEX(Assessment!$G:$G,$X93)) -> High | G93: =IF($X93="","",INDEX(Assessment!$J:$J,$X93)) -> Set up and document: PSIRT and CSIRT must not be one person; split across several individuals (unless microenterprise). | H93: =IF($X93="","",INDEX(Assessment!$L:$L,$X93)) -> CISO / PSIRT Lead | I93: =IF($X93="","",INDEX(Assessment!$N:$N,$X93)) -> M | X93: =IF(77<=$B$6,SMALL($Y$2:$Y$593,77),IF(77<=$B$6+$B$7,SMALL($Z$2:$Z$593,77-$B$6),"")) -> 480 | Y93: =IF(Assessment!$G93="Critical",ROW(Assessment!$G93),"") | Z93: =IF(Assessment!$G93="High",ROW(Assessment!$G93),"")
A94: =IF($X94="","",78) -> 78 | B94: =IF($X94="","",INDEX(Assessment!$A:$A,$X94)) -> TR3-4.3.1f | C94: =IF($X94="","",INDEX(Assessment!$B:$B,$X94)) -> BSI TR-03183-3 v1.0.0 | D94: =IF($X94="","",INDEX(Assessment!$C:$C,$X94)) -> 4.3.1 Roles of responsible cybersecurity contacts | E94: =IF($X94="","",INDEX(Assessment!$F:$F,$X94)) -> PSIRT / CSIRT organisation | F94: =IF($X94="","",INDEX(Assessment!$G:$G,$X94)) -> High | G94: =IF($X94="","",INDEX(Assessment!$J:$J,$X94)) -> Set up and document: PSIRT is the first contact and covers vulnerability handling of products and services. | H94: =IF($X94="","",INDEX(Assessment!$L:$L,$X94)) -> CISO / PSIRT Lead | I94: =IF($X94="","",INDEX(Assessment!$N:$N,$X94)) -> M | X94: =IF(78<=$B$6,SMALL($Y$2:$Y$593,78),IF(78<=$B$6+$B$7,SMALL($Z$2:$Z$593,78-$B$6),"")) -> 485 | Y94: =IF(Assessment!$G94="Critical",ROW(Assessment!$G94),"") | Z94: =IF(Assessment!$G94="High",ROW(Assessment!$G94),"")
A95: =IF($X95="","",79) -> 79 | B95: =IF($X95="","",INDEX(Assessment!$A:$A,$X95)) -> TR3-4.3.1m | C95: =IF($X95="","",INDEX(Assessment!$B:$B,$X95)) -> BSI TR-03183-3 v1.0.0 | D95: =IF($X95="","",INDEX(Assessment!$C:$C,$X95)) -> 4.3.1 Roles of responsible cybersecurity contacts | E95: =IF($X95="","",INDEX(Assessment!$F:$F,$X95)) -> PSIRT / CSIRT organisation | F95: =IF($X95="","",INDEX(Assessment!$G:$G,$X95)) -> High | G95: =IF($X95="","",INDEX(Assessment!$J:$J,$X95)) -> Set up and document: provide sufficient resources for absences and to guarantee CVD response times. | H95: =IF($X95="","",INDEX(Assessment!$L:$L,$X95)) -> CISO / PSIRT Lead | I95: =IF($X95="","",INDEX(Assessment!$N:$N,$X95)) -> M | X95: =IF(79<=$B$6,SMALL($Y$2:$Y$593,79),IF(79<=$B$6+$B$7,SMALL($Z$2:$Z$593,79-$B$6),"")) -> 495 | Y95: =IF(Assessment!$G95="Critical",ROW(Assessment!$G95),"") | Z95: =IF(Assessment!$G95="High",ROW(Assessment!$G95),"")
A96: =IF($X96="","",80) -> 80 | B96: =IF($X96="","",INDEX(Assessment!$A:$A,$X96)) -> TR3-4.3.3a-a | C96: =IF($X96="","",INDEX(Assessment!$B:$B,$X96)) -> BSI TR-03183-3 v1.0.0 | D96: =IF($X96="","",INDEX(Assessment!$C:$C,$X96)) -> 4.3.3 Web form for vulnerability reports | E96: =IF($X96="","",INDEX(Assessment!$F:$F,$X96)) -> Vulnerability report web form | F96: =IF($X96="","",INDEX(Assessment!$G:$G,$X96)) -> High | G96: =IF($X96="","",INDEX(Assessment!$J:$J,$X96)) -> Build the report web form with a secure back-end into PSIRT case tooling; no trackers; anonymous submission possible. | H96: =IF($X96="","",INDEX(Assessment!$L:$L,$X96)) -> PSIRT Lead with Web/IT team | I96: =IF($X96="","",INDEX(Assessment!$N:$N,$X96)) -> M | X96: =IF(80<=$B$6,SMALL($Y$2:$Y$593,80),IF(80<=$B$6+$B$7,SMALL($Z$2:$Z$593,80-$B$6),"")) -> 505 | Y96: =IF(Assessment!$G96="Critical",ROW(Assessment!$G96),"") | Z96: =IF(Assessment!$G96="High",ROW(Assessment!$G96),"")
A97: =IF($X97="","",81) -> 81 | B97: =IF($X97="","",INDEX(Assessment!$A:$A,$X97)) -> TR3-4.4.2b-a | C97: =IF($X97="","",INDEX(Assessment!$B:$B,$X97)) -> BSI TR-03183-3 v1.0.0 | D97: =IF($X97="","",INDEX(Assessment!$C:$C,$X97)) -> 4.4.2 Corresponding national CSIRT | E97: =IF($X97="","",INDEX(Assessment!$F:$F,$X97)) -> Incident & vulnerability reporting (CSIRT) | F97: =IF($X97="","",INDEX(Assessment!$G:$G,$X97)) -> High | G97: =IF($X97="","",INDEX(Assessment!$J:$J,$X97)) -> inform the CSIRT about all new information, mitigation measures and their schedules - document it in the PSIRT notification procedure and keep a case log. | H97: =IF($X97="","",INDEX(Assessment!$L:$L,$X97)) -> PSIRT Lead / Compliance Officer | I97: =IF($X97="","",INDEX(Assessment!$N:$N,$X97)) -> M | X97: =IF(81<=$B$6,SMALL($Y$2:$Y$593,81),IF(81<=$B$6+$B$7,SMALL($Z$2:$Z$593,81-$B$6),"")) -> 521 | Y97: =IF(Assessment!$G97="Critical",ROW(Assessment!$G97),"") | Z97: =IF(Assessment!$G97="High",ROW(Assessment!$G97),"")
A98: =IF($X98="","",82) -> 82 | B98: =IF($X98="","",INDEX(Assessment!$A:$A,$X98)) -> TR3-4.4.2b-b | C98: =IF($X98="","",INDEX(Assessment!$B:$B,$X98)) -> BSI TR-03183-3 v1.0.0 | D98: =IF($X98="","",INDEX(Assessment!$C:$C,$X98)) -> 4.4.2 Corresponding national CSIRT | E98: =IF($X98="","",INDEX(Assessment!$F:$F,$X98)) -> Incident & vulnerability reporting (CSIRT) | F98: =IF($X98="","",INDEX(Assessment!$G:$G,$X98)) -> High | G98: =IF($X98="","",INDEX(Assessment!$J:$J,$X98)) -> coordinate mitigation measures and schedules with the CSIRT - document it in the PSIRT notification procedure and keep a case log. | H98: =IF($X98="","",INDEX(Assessment!$L:$L,$X98)) -> PSIRT Lead / Compliance Officer | I98: =IF($X98="","",INDEX(Assessment!$N:$N,$X98)) -> M | X98: =IF(82<=$B$6,SMALL($Y$2:$Y$593,82),IF(82<=$B$6+$B$7,SMALL($Z$2:$Z$593,82-$B$6),"")) -> 522 | Y98: =IF(Assessment!$G98="Critical",ROW(Assessment!$G98),"") | Z98: =IF(Assessment!$G98="High",ROW(Assessment!$G98),"")
A99: =IF($X99="","",83) -> 83 | B99: =IF($X99="","",INDEX(Assessment!$A:$A,$X99)) -> TR3-4.4.4a | C99: =IF($X99="","",INDEX(Assessment!$B:$B,$X99)) -> BSI TR-03183-3 v1.0.0 | D99: =IF($X99="","",INDEX(Assessment!$C:$C,$X99)) -> 4.4.4 Assurances of the manufacturer to the reporting entity | E99: =IF($X99="","",INDEX(Assessment!$F:$F,$X99)) -> CVD policy - assurances to reporters | F99: =IF($X99="","",INDEX(Assessment!$G:$G,$X99)) -> High | G99: =IF($X99="","",INDEX(Assessment!$J:$J,$X99)) -> Write into the CVD policy / PSIRT procedure and apply in case handling: treat each incoming report confidentially to the extent permitted by law. | H99: =IF($X99="","",INDEX(Assessment!$L:$L,$X99)) -> PSIRT Lead (Legal reviews policy wording) | I99: =IF($X99="","",INDEX(Assessment!$N:$N,$X99)) -> M | X99: =IF(83<=$B$6,SMALL($Y$2:$Y$593,83),IF(83<=$B$6+$B$7,SMALL($Z$2:$Z$593,83-$B$6),"")) -> 525 | Y99: =IF(Assessment!$G99="Critical",ROW(Assessment!$G99),"") | Z99: =IF(Assessment!$G99="High",ROW(Assessment!$G99),"")
A100: =IF($X100="","",84) -> 84 | B100: =IF($X100="","",INDEX(Assessment!$A:$A,$X100)) -> TR3-4.4.4c | C100: =IF($X100="","",INDEX(Assessment!$B:$B,$X100)) -> BSI TR-03183-3 v1.0.0 | D100: =IF($X100="","",INDEX(Assessment!$C:$C,$X100)) -> 4.4.4 Assurances of the manufacturer to the reporting entity | E100: =IF($X100="","",INDEX(Assessment!$F:$F,$X100)) -> CVD policy - assurances to reporters | F100: =IF($X100="","",INDEX(Assessment!$G:$G,$X100)) -> High | G100: =IF($X100="","",INDEX(Assessment!$J:$J,$X100)) -> Write into the CVD policy / PSIRT procedure and apply in case handling: respond to each report or update within the guaranteed response times. | H100: =IF($X100="","",INDEX(Assessment!$L:$L,$X100)) -> PSIRT Lead (Legal reviews policy wording) | I100: =IF($X100="","",INDEX(Assessment!$N:$N,$X100)) -> M | X100: =IF(84<=$B$6,SMALL($Y$2:$Y$593,84),IF(84<=$B$6+$B$7,SMALL($Z$2:$Z$593,84-$B$6),"")) -> 527 | Y100: =IF(Assessment!$G100="Critical",ROW(Assessment!$G100),"") | Z100: =IF(Assessment!$G100="High",ROW(Assessment!$G100),"")
...

Sheet Method
A1: Method, role, assumptions and rating scale - 5. Solution Maintenance (RUN)
A2: Workbook | B2: Process workbook '5. Solution Maintenance (RUN)' - one of six; all six use the identical requirement register (same IDs, same order).
A3: Assessment date | B3: 18 October 2026
A4: Sources | B4: BSI TR-03183-1 v1.0.0 (General requirements, 31.07.2026); BSI TR-03183-2 v2.1.0 (SBOM, 2025-08-20); BSI TR-03183-3 v1.0.0 (Vulnerability reports and notifications, 2025-08-20). Markdown files supplied by the user.
A6: 1. Role
A7: Manufacturer | B7: Solution provider acting as CRA manufacturer of its solutions (products with digital elements incl. remote data processing it operates).
A8: Product category | B8: Default category (not important / critical) -> conformity by internal control (Module A self-assessment); no notified body required.
A9: Customers | B9: Governments (public administration) and airports: professional business users, typically NIS2 entities with own reporting duties; contracts are often tailor-made.
A10: Timeline | B10: CRA reporting obligations (Art. 14) apply from 11 Sep 2026 - already in force on the assessment date, also for solutions placed on the market earlier. All other obligations apply to products made available from 11 Dec 2027; earlier products only after a substantial modification.
A12: 2. Assumptions
A13: A1 Solution type | B13: Software-centric systems, possibly with appliances and with remote data processing operated by us, integrating own code with COTS and open-source components; installed at customer sites, often in segregated networks under customer change control.
A14: A2 CRA scope | B14: Solutions are in scope: not developed exclusively for national security or defence, not specifically designed to process classified information, not certified under the civil-aviation Regulation (EU) 2018/1139 (TR-1 3.2.1). Presale should confirm this per bid.
A15: A3 Starting maturity | B15: General ISMS and secure-development practices exist, but CRA/TR-specific capabilities do not: no product PSIRT or published CVD policy, no per-release SBOM pipeline, no ENISA reporting procedure, no CRA technical file or EU DoC. Where a capability already exists, lower the rating.
A16: A4 Customer operators | B16: Skilled IT/OT professionals (affects risk sharing, acceptance criteria and automatic updates).
A17: A5 Company | B17: Not a microenterprise; main establishment in an EU Member State, which determines the corresponding CSIRT (CRA Art. 14(7)).
A18: A6 Legal weight | B18: TR-03183 is BSI guidance and establishes no obligations by itself (TR-1 section 2). Requirements that implement CRA legal obligations are rated higher; TR-specific details are rated on effort and on customer/tender expectations (German public tenders increasingly reference TR-03183-2).
A19: A7 Umbrella statements | B19: Restating or umbrella statements are rated by their incremental impact; the substantive impact sits on the specific rows they summarise.
A20: A8 Out of scope | B20: The TR-1 OSCAL control catalogue (GitHub) is referenced but not contained in the sources and is not assessed.
A22: 3. Rating scale
A23: Critical | B23: Legal non-compliance or market-access risk if not addressed; needs a new capability, tool, role or organisational change.
A24: High | B24: Significant change to an existing process, new deliverables or roles, notable effort or cost.
A25: Medium | B25: Moderate adaptation of existing procedures, templates or tools.
A26: Low | B26: Minor adjustment, documentation or awareness only.
A27: Nil | B27: No impact on this process; the rationale states where the requirement is handled instead.
A28: Effort (S/M/L) | B28: S = days / template or configuration change; M = weeks or a cross-team change; L = months, new tooling, roles or budget; n/a = Nil.
A30: 4. Process scope
A31: 1. Presale | B31: Bids, RFP answers, contractual commitments, security claims, support-period commitments, pricing of compliance effort.
A32: 2. Solution Development | B32: Secure design, coding, dependency and component management, SBOM generation, security testing.
A33: 3. Solution Integration / Build | B33: Assembling own and third-party components, build pipeline, per-release SBOM, hardening, technical documentation, conformity evidence.
A34: 4. Solution Deployment | B34: Delivery and installation at the customer, secure default configuration, user and security instructions, update mechanism, handover of SBOM and documentation.
A35: 5. Solution Maintenance (RUN) << this workbook | B35: Vulnerability monitoring and handling, security updates, coordinated vulnerability disclosure, incident and vulnerability reporting, SBOM updates, support period.
A36: 6. Solution Decommissioning | B36: End-of-support notification, secure data removal, retention of documentation and records, final customer communication.
A38: 5. Requirement register
A39: Reading | B39: All three documents were read in full before assessing. Where the Markdown conversion lost or garbled text, the official BSI PDF of the same document was used and the row says so in Notes (TR-2 Tables 2-6; TR-1 5.9.1 NOTE and D.2 NOTE; TR-1 Annex B table structure and IDs).
A40: Included | B40: Every statement with BCP 14 keywords in capitals, plus equivalent wording: shall, must, has/have to, need(s) to, is/are required, is responsible, ought to, should, is recommended/advisable, it is necessary/important/essential to, may (permission), is (not) acceptable; imperative items under obligation or recommendation lead-ins; and the TR-1 3.4 applicability rules (reporting start, legacy products, substantial modification).
A41: Not registered | B41: Keyword definitions (TR-1 4.4, TR-2 2, TR-3 2); 'may/can/might' expressing possibility; rhetorical questions; descriptive or definitional text without normative wording (e.g. scope and exclusions in TR-1 3.2, perspective descriptions in 5.6); TR-1 criteria tables 1-7 and 11-13 and the example-specific evaluations of the Annex C camera; TR-2 8.2 format-mapping tables; TR-3 Annex 5 references; tables of contents.
A42: Atomic split | B42: A statement with several obligations is split into -a/-b/-c; list items are separate rows; '[…]' marks words that belong to the other sub-item. A leading [bracket] is the lead-in sentence; [Input: …] / [Output: …] show the input/output of TR-1 activity controls. Wording is otherwise verbatim (typographic quotes normalised, footnote markers removed).
A43: IDs | B43: Document IDs are reused: TR-1 controls RH_*, TR-1 Annex B ER.x (CRA Annex I Part I) and VH.x (Part II), TR-3 section + letter (e.g. TR3-4.2.1a). Other statements get TR1-001 / TR2-001 / TR3-001 ... in document order. Essential requirements appear once under their Annex B ID although their text is also printed in TR-1 3.9; Annex I Part I (2)(g) has no Annex B ID and uses a sequential ID.
A44: Register size | B44: ="Total "&(COUNTA(Assessment!$A:$A)-1)&" rows: TR-03183-1 = "&COUNTIF(Assessment!$B:$B,"BSI TR-03183-1 v1.0.0")&", TR-03183-2 = "&COUNTIF(Assessment!$B:$B,"BSI TR-03183-2 v2.1.0")&", TR-03183-3 = "&COUNTIF(Assessment!$B:$B,"BSI TR-03183-3 v1.0.0") -> Total 592 rows: TR-03183-1 = 282, TR-03183-2 = 128, TR-03183-3 = 182
A46: 6. Using the workbook
A47: Assessment sheet | B47: Header row frozen, autofilter on all columns, drop-down lists on Impact rating and Effort, colour coding: Critical red, High orange, Medium yellow, Low green, Nil grey. Change a rating with the drop-down; the Summary updates automatically.
A48: Summary sheet | B48: Counts per rating (overall and per source document) use COUNTIF/COUNTIFS; the Critical/High list is formula-driven via hidden helper columns X:Z on the Summary sheet - do not delete them.
A50: 7. Interpretation notes
A51: Equivalent wording | B51: TR-1 restates many CRA duties with lower-case 'must/has to/shall'; these were registered as equivalent wording although TR-1 4.4 defines only capitals as normative.
A52: 'ought to' | B52: TR-1 3.6 says the manufacturer 'ought to' monitor vulnerabilities; rated as mandatory because it restates the CRA Art. 13 duty.
A53: Annex B quirks | B53: Annex B skips ER.8 (data minimisation), numbers ER.3a without ER.3 and VH.2a without VH.2, prints 'Part II 4' for VH.6a, and truncates ER.14; the CRA text from TR-1 3.9 was used.
A54: TR-1 5.7.1 | B54: 'processes ... comply with ... Annex I Part I' was read as Part II (vulnerability-handling processes), as in the CRA.
A55: TR-2 appendix | B55: Section 8 is declared explanatory; its normatively worded sentences are registered but mostly rated Low.
A56: TR-3 90-day rule | B56: TR-3 4.4.10 sets a 90-day public-disclosure deadline that goes beyond the CRA (disclosure after a fix is available); rated High rather than Critical.
A57: Automatic updates | B57: 'where applicable' in ER.4a/VH.7a was read as allowing a justified exception for change-controlled airport/government sites.
